Workbook

Sheet PlantInfo
A1: Source | B1: Commissioning Group | C1: Name of Power Plant | D1: State | E1: District | F1: Commissioning Date | G1: Capacity (MW) | H1: Implementing Agency
A2: Coal | B2: pipeline | C2: Ennore SEZ Expansion SCTPP | D2: Tamil Nadu | E2: Tiruvallur | F2: 2027-06-01 | G2: 660 | H2: Tamil Nadu Generation & Distribution Corp. Ltd. (TANGEDCO)
A3: Coal | B3: pipeline | C3: Ennore SEZ Expansion SCTPP | D3: Tamil Nadu | E3: Tiruvallur | F3: 2027-08-01 | G3: 660 | H3: Tamil Nadu Generation & Distribution Corp. Ltd. (TANGEDCO)
A4: Coal | B4: retired | C4: Ennore TPS | D4: Tamil Nadu | E4: Thiruvallur | F4: 1970-03-01 | G4: 60 | H4: Tamil Nadu Generation & Distribution Corp. Ltd. (TANGEDCO)
A5: Coal | B5: retired | C5: Ennore TPS | D5: Tamil Nadu | E5: Thiruvallur | F5: 1971-02-01 | G5: 60 | H5: Tamil Nadu Generation & Distribution Corp. Ltd. (TANGEDCO)
A6: Coal | B6: retired | C6: Ennore TPS | D6: Tamil Nadu | E6: Thiruvallur | F6: 1972-05-01 | G6: 110 | H6: Tamil Nadu Generation & Distribution Corp. Ltd. (TANGEDCO)
A7: Coal | B7: retired | C7: Ennore TPS | D7: Tamil Nadu | E7: Thiruvallur | F7: 1973-05-01 | G7: 110 | H7: Tamil Nadu Generation & Distribution Corp. Ltd. (TANGEDCO)
A8: Coal | B8: retired | C8: Ennore TPS | D8: Tamil Nadu | E8: Thiruvallur | F8: 1975-12-01 | G8: 110 | H8: Tamil Nadu Generation & Distribution Corp. Ltd. (TANGEDCO)
A9: Coal | B9: operational | C9: ITPCL or Cuddalore TPP | D9: Tamil Nadu | E9: Cuddalore | F9: 2015-09-01 | G9: 600 | H9: IL&FS Tamil Nadu Power Co. Ltd.
A10: Coal | B10: operational | C10: ITPCL or Cuddalore TPP | D10: Tamil Nadu | E10: Cuddalore | F10: 2016-04-01 | G10: 600 | H10: IL&FS Tamil Nadu Power Co. Ltd.
A11: Coal | B11: operational | C11: Mettur TPS | D11: Tamil Nadu | E11: Salem | F11: 1987-01-07 | G11: 210 | H11: Tamil Nadu Generation & Distribution Corp. Ltd. (TANGEDCO)
A12: Coal | B12: operational | C12: Mettur TPS | D12: Tamil Nadu | E12: Salem | F12: 1987-01-12 | G12: 210 | H12: Tamil Nadu Generation & Distribution Corp. Ltd. (TANGEDCO)
A13: Coal | B13: operational | C13: Mettur TPS | D13: Tamil Nadu | E13: Salem | F13: 1989-03-22 | G13: 210 | H13: Tamil Nadu Generation & Distribution Corp. Ltd. (TANGEDCO)
... A142: Hydro | B142: operational | C142: Suruliyar Hydroelectric Power Project | D142: Tamil Nadu | E142: Theni | F142: 1978-08-27 | G142: 35 | H142: Tamil Nadu Generation & Distribution Co. Limited (TANGEDCO)
A143: Wind | B143: pipeline | C143: 151 MW SJVN Wind Palayam Green Shoe Tamil Nadu Karur | D143: Tamil Nadu | E143: Karur | G143: 151.2
A144: Wind | B144: pipeline | C144: 151.2 MW Wind SJVN FDRE Basis LOA Tamil Nadu Karur | D144: Tamil Nadu | E144: Karur | G144: 151.2
A145: Wind | B145: pipeline | C145: 82.5 MW NTPC FDRE Wind Tamil Nadu Karur | D145: Tamil Nadu | E145: Karur | G145: 82.5
A146: Wind | B146: pipeline | C146: 93.6 MW Karur - SJVN FDRE Green Shoe Tamil Nadu Karur | D146: Tamil Nadu | E146: Karur | G146: 93.6
A147: Wind | B147: pipeline | C147: Amplus Sun Beat Private Limited Tamil Nadu Karur | D147: Tamil Nadu | E147: Karur | G147: 80
A148: Wind | B148: pipeline | C148: Amplus Theta Energy Private Limited Tamil Nadu Karur | D148: Tamil Nadu | E148: Karur | G148: 65
A149: Wind | B149: pipeline | C149: Jindal Renewables - Wind Project - C&I Tamil Nadu Karur | D149: Tamil Nadu | E149: Karur | G149: 300
A150: Wind | B150: pipeline | C150: Jindal Renewables - Wind Project - C&I Tamil Nadu Karur | D150: Tamil Nadu | E150: Karur | G150: 50
A151: Wind | B151: operational | C151: Tamil Nadu-Ariyalur | D151: Tamil Nadu | E151: Ariyalur | G151: 22
A152: Wind | B152: operational | C152: Tamil Nadu-Chennai | D152: Tamil Nadu | E152: Chennai | G152: 3.125
A153: Wind | B153: operational | C153: Tamil Nadu-Coimbatore | D153: Tamil Nadu | E153: Coimbatore | G153: 2175.4
A154: Wind | B154: operational | C154: Tamil Nadu-Dharmapuri | D154: Tamil Nadu | E154: Dharmapuri | G154: 196
... A172: Wind | B172: operational | C172: Tamil Nadu-Viluppuram | D172: Tamil Nadu | E172: Viluppuram | G172: 1.7
A173: Solar | B173: pipeline | C173: INGEL Tamil Nadu 200.0 | D173: Tamil Nadu | E173: Thoothukudi | F173: 2027-12-31 | G173: 200 | H173: INGEL
A174: Solar | B174: operational | C174: Tamil Nadu Chennai 16 | D174: Tamil Nadu | E174: Chennai | G174: 16
A175: Solar | B175: operational | C175: Tamil Nadu Coimbatore 11.26 | D175: Tamil Nadu | E175: Coimbatore | G175: 11.26
A176: Solar | B176: operational | C176: Tamil Nadu Cuddalore 140 | D176: Tamil Nadu | E176: Cuddalore | G176: 140
A177: Solar | B177: operational | C177: Tamil Nadu Dindigul 109.46 | D177: Tamil Nadu | E177: Dindigul | G177: 109.46
A178: Solar | B178: operational | C178: Tamil Nadu Erode 7 | D178: Tamil Nadu | E178: Erode | G178: 7
A179: Solar | B179: operational | C179: Tamil Nadu Kanniyakumari 1 | D179: Tamil Nadu | E179: Kanniyakumari | G179: 1
A180: Solar | B180: operational | C180: Tamil Nadu Karur 156.49 | D180: Tamil Nadu | E180: Karur | G180: 156.49
A181: Solar | B181: operational | C181: Tamil Nadu Krishnagiri 0.75 | D181: Tamil Nadu | E181: Krishnagiri | G181: 0.75
A182: Solar | B182: operational | C182: Tamil Nadu Madurai 1 | D182: Tamil Nadu | E182: Madurai | G182: 1
A183: Solar | B183: operational | C183: Tamil Nadu N.A. 251 | D183: Tamil Nadu | E183: N.A. | G183: 251
A184: Solar | B184: operational | C184: Tamil Nadu N.A. Off -grid 75.91 | D184: Tamil Nadu | E184: N.A. | G184: 75.91
A185: Solar | B185: operational | C185: Tamil Nadu N.A. Others (Districts not specified) 9143.18 | D185: Tamil Nadu | E185: N.A. | G185: 9143.18
... A200: Solar | B200: operational | C200: Tamil Nadu Virudhunagar 685.4 | D200: Tamil Nadu | E200: Virudhunagar | G200: 685.4
A201: Oil & Gas | B201: operational | C201: Basin Bridge Gas Turbine Power Station | D201: Tamil Nadu | E201: Chennai | F201: 1996-02-12 | G201: 30 | H201: Tamil Nadu Generation and Distribution Corp. Ltd.
A202: Oil & Gas | B202: operational | C202: Basin Bridge Gas Turbine Power Station | D202: Tamil Nadu | E202: Chennai | F202: 1996-02-25 | G202: 30 | H202: Tamil Nadu Generation and Distribution Corp. Ltd.
A203: Oil & Gas | B203: operational | C203: Basin Bridge Gas Turbine Power Station | D203: Tamil Nadu | E203: Chennai | F203: 1996-03-26 | G203: 30 | H203: Tamil Nadu Generation and Distribution Corp. Ltd.
A204: Oil & Gas | B204: operational | C204: Basin Bridge Gas Turbine Power Station | D204: Tamil Nadu | E204: Chennai | F204: 1996-03-31 | G204: 30 | H204: Tamil Nadu Generation and Distribution Corp. Ltd.
A205: Oil & Gas | B205: Temporarily Closed | C205: Karuppur Combined Cycle Power Plant | D205: Tamil Nadu | E205: Thanjavur | F205: 2005-08-01 | G205: 70 | H205: Lanco Tanjore Power Co. Ltd.
A206: Oil & Gas | B206: Temporarily Closed | C206: Karuppur Combined Cycle Power Plant | D206: Tamil Nadu | E206: Thanjavur | F206: 2005-08-01 | G206: 49.8 | H206: Lanco Tanjore Power Co. Ltd.
A207: Oil & Gas | B207: operational | C207: Kovilkalappal (Thirumakotai) Gas Combined Cycle Gas Turbine Power Station | D207: Tamil Nadu | E207: Thiruvarur | F207: 2001-02-05 | G207: 69.65 | H207: Tamil Nadu Generation and Distribution Corp. Ltd.
A208: Oil & Gas | B208: operational | C208: Kovilkalappal (Thirumakotai) Gas Combined Cycle Gas Turbine Power Station | D208: Tamil Nadu | E208: Thiruvarur | F208: 2001-02-05 | G208: 38.23 | H208: Tamil Nadu Generation and Distribution Corp. Ltd.
A209: Oil & Gas | B209: operational | C209: Kuttalam Gas Turbine Power Station | D209: Tamil Nadu | E209: Nagapattinam | F209: 2003-11-27 | G209: 63 | H209: Tamil Nadu Generation and Distribution Corp. Ltd.
A210: Oil & Gas | B210: operational | C210: Kuttalam Gas Turbine Power Station | D210: Tamil Nadu | E210: Nagapattinam | F210: 2004-03-24 | G210: 37 | H210: Tamil Nadu Generation and Distribution Corp. Ltd.
A211: Oil & Gas | B211: operational | C211: Pillaiperumalnallur (PPN) Power Plant Phase I | D211: Tamil Nadu | E211: Nagapattinam | F211: 2001-04-26 | G211: 225 | H211: PPN Power Generating Co. Private Ltd.
A212: Oil & Gas | B212: operational | C212: Pillaiperumalnallur (PPN) Power Plant Phase I | D212: Tamil Nadu | E212: Nagapattinam | F212: 2001-04-26 | G212: 105.5 | H212: PPN Power Generating Co. Private Ltd.
... A317: Small-Hydro | B317: operational | C317: Sholayar II Power House | D317: Tamil Nadu | E317: Coimbatore | F317: 1971-03-29 | G317: 25 | H317: Tamil Nadu Generation and Distribution Corp. Ltd. (TANGEDCO)
A318: Small-Hydro | B318: operational | C318: Tamil Nadu Small Hydro Project Bunched | D318: Tamil Nadu | E318: Location TBC | F318: N.A. | G318: 0.35
A319: Small-Hydro | B319: operational | C319: Thirumurthy Mini Hydel Project | D319: Tamil Nadu | E319: Tiruppur | F319: 2000-03-20 | G319: 0.65 | H319: Tamil Nadu Generation and Distribution Corp. Ltd. (TANGEDCO)
A320: Small-Hydro | B320: operational | C320: Thirumurthy Mini Hydel Project | D320: Tamil Nadu | E320: Tiruppur | F320: 2000-03-20 | G320: 0.65 | H320: Tamil Nadu Generation and Distribution Corp. Ltd. (TANGEDCO)
A321: Small-Hydro | B321: operational | C321: Thirumurthy Mini Hydel Project | D321: Tamil Nadu | E321: Tiruppur | F321: 2000-03-20 | G321: 0.65 | H321: Tamil Nadu Generation and Distribution Corp. Ltd. (TANGEDCO)
A322: Small-Hydro | B322: operational | C322: Vaigai Hydro Power Project | D322: Tamil Nadu | E322: Kanniyakumari | F322: 1990-03-04 | G322: 3 | H322: Tamil Nadu Generation and Distribution Corp. Ltd. (TANGEDCO)
A323: Small-Hydro | B323: operational | C323: Vaigai Hydro Power Project | D323: Tamil Nadu | E323: Theni | F323: 1990-03-04 | G323: 3 | H323: Tamil Nadu Generation and Distribution Corp. Ltd. (TANGEDCO)

Sheet District Allocation
A1: Source Record ID | B1: Allocation ID | C1: Base Excel Row | D1: Source | E1: Commissioning Group | F1: Name of Power Plant | G1: State | H1: Source District | I1: Allocated District | J1: Commissioning Date | K1: Source Capacity (MW) | L1: Allocation Share | M1: Allocated Capacity (MW) | N1: Verified Allocated Capacity (MW) | O1: Implementing Agency | P1: Allocation Component | Q1: Allocation Method | R1: Confidence | S1: Source URL | T1: Notes
A2: SEP26-0002 | B2: base_row_0002 | C2: 2 | D2: Coal | E2: pipeline | F2: Ennore SEZ Expansion SCTPP | G2: Tamil Nadu | H2: Tiruvallur | I2: Tiruvallur | J2: 2027-06-01 | K2: 660 | L2: 1 | M2: =K2*L2 | N2: 660 | O2: Tamil Nadu Generation & Distribution Corp. Ltd. (TANGEDCO) | P2: Direct | Q2: District carried from Sep26 base workbook | R2: Existing | T2: Sep26 is authoritative for the source record.
A3: SEP26-0003 | B3: base_row_0003 | C3: 3 | D3: Coal | E3: pipeline | F3: Ennore SEZ Expansion SCTPP | G3: Tamil Nadu | H3: Tiruvallur | I3: Tiruvallur | J3: 2027-08-01 | K3: 660 | L3: 1 | M3: =K3*L3 | N3: 660 | O3: Tamil Nadu Generation & Distribution Corp. Ltd. (TANGEDCO) | P3: Direct | Q3: District carried from Sep26 base workbook | R3: Existing | T3: Sep26 is authoritative for the source record.
A4: SEP26-0004 | B4: base_row_0004 | C4: 4 | D4: Coal | E4: retired | F4: Ennore TPS | G4: Tamil Nadu | H4: Thiruvallur | I4: Tiruvallur | J4: 1970-03-01 | K4: 60 | L4: 1 | M4: =K4*L4 | N4: 60 | O4: Tamil Nadu Generation & Distribution Corp. Ltd. (TANGEDCO) | P4: Direct | Q4: District carried from Sep26 base workbook | R4: Existing | T4: Sep26 is authoritative for the source record.
A5: SEP26-0005 | B5: base_row_0005 | C5: 5 | D5: Coal | E5: retired | F5: Ennore TPS | G5: Tamil Nadu | H5: Thiruvallur | I5: Tiruvallur | J5: 1971-02-01 | K5: 60 | L5: 1 | M5: =K5*L5 | N5: 60 | O5: Tamil Nadu Generation & Distribution Corp. Ltd. (TANGEDCO) | P5: Direct | Q5: District carried from Sep26 base workbook | R5: Existing | T5: Sep26 is authoritative for the source record.
A6: SEP26-0006 | B6: base_row_0006 | C6: 6 | D6: Coal | E6: retired | F6: Ennore TPS | G6: Tamil Nadu | H6: Thiruvallur | I6: Tiruvallur | J6: 1972-05-01 | K6: 110 | L6: 1 | M6: =K6*L6 | N6: 110 | O6: Tamil Nadu Generation & Distribution Corp. Ltd. (TANGEDCO) | P6: Direct | Q6: District carried from Sep26 base workbook | R6: Existing | T6: Sep26 is authoritative for the source record.
A7: SEP26-0007 | B7: base_row_0007 | C7: 7 | D7: Coal | E7: retired | F7: Ennore TPS | G7: Tamil Nadu | H7: Thiruvallur | I7: Tiruvallur | J7: 1973-05-01 | K7: 110 | L7: 1 | M7: =K7*L7 | N7: 110 | O7: Tamil Nadu Generation & Distribution Corp. Ltd. (TANGEDCO) | P7: Direct | Q7: District carried from Sep26 base workbook | R7: Existing | T7: Sep26 is authoritative for the source record.
A8: SEP26-0008 | B8: base_row_0008 | C8: 8 | D8: Coal | E8: retired | F8: Ennore TPS | G8: Tamil Nadu | H8: Thiruvallur | I8: Tiruvallur | J8: 1975-12-01 | K8: 110 | L8: 1 | M8: =K8*L8 | N8: 110 | O8: Tamil Nadu Generation & Distribution Corp. Ltd. (TANGEDCO) | P8: Direct | Q8: District carried from Sep26 base workbook | R8: Existing | T8: Sep26 is authoritative for the source record.
A9: SEP26-0009 | B9: base_row_0009 | C9: 9 | D9: Coal | E9: operational | F9: ITPCL or Cuddalore TPP | G9: Tamil Nadu | H9: Cuddalore | I9: Cuddalore | J9: 2015-09-01 | K9: 600 | L9: 1 | M9: =K9*L9 | N9: 600 | O9: IL&FS Tamil Nadu Power Co. Ltd. | P9: Direct | Q9: District carried from Sep26 base workbook | R9: Existing | T9: Sep26 is authoritative for the source record.
A10: SEP26-0010 | B10: base_row_0010 | C10: 10 | D10: Coal | E10: operational | F10: ITPCL or Cuddalore TPP | G10: Tamil Nadu | H10: Cuddalore | I10: Cuddalore | J10: 2016-04-01 | K10: 600 | L10: 1 | M10: =K10*L10 | N10: 600 | O10: IL&FS Tamil Nadu Power Co. Ltd. | P10: Direct | Q10: District carried from Sep26 base workbook | R10: Existing | T10: Sep26 is authoritative for the source record.
A11: SEP26-0011 | B11: base_row_0011 | C11: 11 | D11: Coal | E11: operational | F11: Mettur TPS | G11: Tamil Nadu | H11: Salem | I11: Salem | J11: 1987-01-07 | K11: 210 | L11: 1 | M11: =K11*L11 | N11: 210 | O11: Tamil Nadu Generation & Distribution Corp. Ltd. (TANGEDCO) | P11: Direct | Q11: District carried from Sep26 base workbook | R11: Existing | T11: Sep26 is authoritative for the source record.
A12: SEP26-0012 | B12: base_row_0012 | C12: 12 | D12: Coal | E12: operational | F12: Mettur TPS | G12: Tamil Nadu | H12: Salem | I12: Salem | J12: 1987-01-12 | K12: 210 | L12: 1 | M12: =K12*L12 | N12: 210 | O12: Tamil Nadu Generation & Distribution Corp. Ltd. (TANGEDCO) | P12: Direct | Q12: District carried from Sep26 base workbook | R12: Existing | T12: Sep26 is authoritative for the source record.
A13: SEP26-0013 | B13: base_row_0013 | C13: 13 | D13: Coal | E13: operational | F13: Mettur TPS | G13: Tamil Nadu | H13: Salem | I13: Salem | J13: 1989-03-22 | K13: 210 | L13: 1 | M13: =K13*L13 | N13: 210 | O13: Tamil Nadu Generation & Distribution Corp. Ltd. (TANGEDCO) | P13: Direct | Q13: District carried from Sep26 base workbook | R13: Existing | T13: Sep26 is authoritative for the source record.
... A142: SEP26-0142 | B142: base_row_0142 | C142: 142 | D142: Hydro | E142: operational | F142: Suruliyar Hydroelectric Power Project | G142: Tamil Nadu | H142: Theni | I142: Theni | J142: 1978-08-27 | K142: 35 | L142: 1 | M142: =K142*L142 | N142: 35 | O142: Tamil Nadu Generation & Distribution Co. Limited (TANGEDCO) | P142: Direct | Q142: District carried from Sep26 base workbook | R142: Existing | T142: Sep26 is authoritative for the source record.
A143: SEP26-0143 | B143: base_row_0143 | C143: 143 | D143: Wind | E143: pipeline | F143: 151 MW SJVN Wind Palayam Green Shoe Tamil Nadu Karur | G143: Tamil Nadu | H143: Karur | I143: Karur | K143: 151.2 | L143: 1 | M143: =K143*L143 | N143: 151.2 | P143: Direct | Q143: District carried from Sep26 base workbook | R143: Existing | T143: Sep26 is authoritative for the source record.
A144: SEP26-0144 | B144: base_row_0144 | C144: 144 | D144: Wind | E144: pipeline | F144: 151.2 MW Wind SJVN FDRE Basis LOA Tamil Nadu Karur | G144: Tamil Nadu | H144: Karur | I144: Karur | K144: 151.2 | L144: 1 | M144: =K144*L144 | N144: 151.2 | P144: Direct | Q144: District carried from Sep26 base workbook | R144: Existing | T144: Sep26 is authoritative for the source record.
A145: SEP26-0145 | B145: base_row_0145 | C145: 145 | D145: Wind | E145: pipeline | F145: 82.5 MW NTPC FDRE Wind Tamil Nadu Karur | G145: Tamil Nadu | H145: Karur | I145: Karur | K145: 82.5 | L145: 1 | M145: =K145*L145 | N145: 82.5 | P145: Direct | Q145: District carried from Sep26 base workbook | R145: Existing | T145: Sep26 is authoritative for the source record.
A146: SEP26-0146 | B146: base_row_0146 | C146: 146 | D146: Wind | E146: pipeline | F146: 93.6 MW Karur - SJVN FDRE Green Shoe Tamil Nadu Karur | G146: Tamil Nadu | H146: Karur | I146: Karur | K146: 93.6 | L146: 1 | M146: =K146*L146 | N146: 93.6 | P146: Direct | Q146: District carried from Sep26 base workbook | R146: Existing | T146: Sep26 is authoritative for the source record.
A147: SEP26-0147 | B147: base_row_0147 | C147: 147 | D147: Wind | E147: pipeline | F147: Amplus Sun Beat Private Limited Tamil Nadu Karur | G147: Tamil Nadu | H147: Karur | I147: Karur | K147: 80 | L147: 1 | M147: =K147*L147 | N147: 80 | P147: Direct | Q147: District carried from Sep26 base workbook | R147: Existing | T147: Sep26 is authoritative for the source record.
A148: SEP26-0148 | B148: base_row_0148 | C148: 148 | D148: Wind | E148: pipeline | F148: Amplus Theta Energy Private Limited Tamil Nadu Karur | G148: Tamil Nadu | H148: Karur | I148: Karur | K148: 65 | L148: 1 | M148: =K148*L148 | N148: 65 | P148: Direct | Q148: District carried from Sep26 base workbook | R148: Existing | T148: Sep26 is authoritative for the source record.
A149: SEP26-0149 | B149: base_row_0149 | C149: 149 | D149: Wind | E149: pipeline | F149: Jindal Renewables - Wind Project - C&I Tamil Nadu Karur | G149: Tamil Nadu | H149: Karur | I149: Karur | K149: 300 | L149: 1 | M149: =K149*L149 | N149: 300 | P149: Direct | Q149: District carried from Sep26 base workbook | R149: Existing | T149: Sep26 is authoritative for the source record.
A150: SEP26-0150 | B150: base_row_0150 | C150: 150 | D150: Wind | E150: pipeline | F150: Jindal Renewables - Wind Project - C&I Tamil Nadu Karur | G150: Tamil Nadu | H150: Karur | I150: Karur | K150: 50 | L150: 1 | M150: =K150*L150 | N150: 50 | P150: Direct | Q150: District carried from Sep26 base workbook | R150: Existing | T150: Sep26 is authoritative for the source record.
A151: SEP26-0151 | B151: base_row_0151 | C151: 151 | D151: Wind | E151: operational | F151: Tamil Nadu-Ariyalur | G151: Tamil Nadu | H151: Ariyalur | I151: Ariyalur | K151: 22 | L151: 1 | M151: =K151*L151 | N151: 22 | P151: Direct | Q151: District carried from Sep26 base workbook | R151: Existing | T151: Sep26 is authoritative for the source record.
A152: SEP26-0152 | B152: base_row_0152 | C152: 152 | D152: Wind | E152: operational | F152: Tamil Nadu-Chennai | G152: Tamil Nadu | H152: Chennai | I152: Chennai | K152: 3.125 | L152: 1 | M152: =K152*L152 | N152: 3.125 | P152: Direct | Q152: District carried from Sep26 base workbook | R152: Existing | T152: Sep26 is authoritative for the source record.
A153: SEP26-0153 | B153: base_row_0153 | C153: 153 | D153: Wind | E153: operational | F153: Tamil Nadu-Coimbatore | G153: Tamil Nadu | H153: Coimbatore | I153: Coimbatore | K153: 2175.4 | L153: 1 | M153: =K153*L153 | N153: 2175.4 | P153: Direct | Q153: District carried from Sep26 base workbook | R153: Existing | T153: Sep26 is authoritative for the source record.
A154: SEP26-0154 | B154: base_row_0154 | C154: 154 | D154: Wind | E154: operational | F154: Tamil Nadu-Dharmapuri | G154: Tamil Nadu | H154: Dharmapuri | I154: Dharmapuri | K154: 196 | L154: 1 | M154: =K154*L154 | N154: 196 | P154: Direct | Q154: District carried from Sep26 base workbook | R154: Existing | T154: Sep26 is authoritative for the source record.
... A159: SEP26-0159 | B159: base_row_0159 | C159: 159 | D159: Wind | E159: operational | F159: Tamil Nadu-Karur | G159: Tamil Nadu | H159: Karur | I159: Karur | K159: 549.595 | L159: 1 | M159: =K159*L159 | N159: 549.595 | P159: Direct | Q159: District carried from Sep26 base workbook | R159: Existing | T159: Sep26 is authoritative for the source record.
A160: SEP26-0160 | B160: wind_unspecified | C160: 160 | D160: Wind | E160: operational | F160: Tamil Nadu-N.A. | G160: Tamil Nadu | H160: N.A. | I160: Dindigul | K160: 256.375 | L160: 0.0060256568 | M160: =K160*L160 | N160: 1.5448278 | P160: Wind Residual | Q160: Residual-gap allocation using current district assignment of supplied OSM turbines and Sep26 known district capacities | R160: Medium | S160: https://cdn.jsdelivr.net/gh/udit-001/india-maps-data@2884453/geojson/states/tamil-nadu.geojson | T160: Recalculated for Sep26. Tenkasi is separate; Chengalpattu, Kallakurichi, Ranipet, Tirupathur, and Mayiladuthurai are recombined to the established allocation geography.
A161: SEP26-0160 | B161: wind_unspecified | C161: 160 | D161: Wind | E161: operational | F161: Tamil Nadu-N.A. | G161: Tamil Nadu | H161: N.A. | I161: Tenkasi | K161: 256.375 | L161: 0.40357922 | M161: =K161*L161 | N161: 103.46762 | P161: Wind Residual | Q161: Residual-gap allocation using current district assignment of supplied OSM turbines and Sep26 known district capacities | R161: Medium | S161: https://cdn.jsdelivr.net/gh/udit-001/india-maps-data@2884453/geojson/states/tamil-nadu.geojson | T161: Recalculated for Sep26. Tenkasi is separate; Chengalpattu, Kallakurichi, Ranipet, Tirupathur, and Mayiladuthurai are recombined to the established allocation geography.
A162: SEP26-0160 | B162: wind_unspecified | C162: 160 | D162: Wind | E162: operational | F162: Tamil Nadu-N.A. | G162: Tamil Nadu | H162: N.A. | I162: Tiruppur | K162: 256.375 | L162: 0.59034698 | M162: =K162*L162 | N162: 151.35021 | P162: Wind Residual | Q162: Residual-gap allocation using current district assignment of supplied OSM turbines and Sep26 known district capacities | R162: Medium | S162: https://cdn.jsdelivr.net/gh/udit-001/india-maps-data@2884453/geojson/states/tamil-nadu.geojson | T162: Recalculated for Sep26. Tenkasi is separate; Chengalpattu, Kallakurichi, Ranipet, Tirupathur, and Mayiladuthurai are recombined to the established allocation geography.
A163: SEP26-0160 | B163: wind_unspecified | C163: 160 | D163: Wind | E163: operational | F163: Tamil Nadu-N.A. | G163: Tamil Nadu | H163: N.A. | I163: Viluppuram | K163: 256.375 | L163: 4.8141459e-05 | M163: =K163*L163 | N163: 0.012342267 | P163: Wind Residual | Q163: Residual-gap allocation using current district assignment of supplied OSM turbines and Sep26 known district capacities | R163: Medium | S163: https://cdn.jsdelivr.net/gh/udit-001/india-maps-data@2884453/geojson/states/tamil-nadu.geojson | T163: Recalculated for Sep26. Tenkasi is separate; Chengalpattu, Kallakurichi, Ranipet, Tirupathur, and Mayiladuthurai are recombined to the established allocation geography.
A164: SEP26-0161 | B164: base_row_0161 | C164: 161 | D164: Wind | E164: operational | F164: Tamil Nadu-Ramanathapuram | G164: Tamil Nadu | H164: Ramanathapuram | I164: Ramanathapuram | K164: 34.03 | L164: 1 | M164: =K164*L164 | N164: 34.03 | P164: Direct | Q164: District carried from Sep26 base workbook | R164: Existing | T164: Sep26 is authoritative for the source record.
A165: SEP26-0162 | B165: base_row_0162 | C165: 162 | D165: Wind | E165: operational | F165: Tamil Nadu-Salem | G165: Tamil Nadu | H165: Salem | I165: Salem | K165: 3.4 | L165: 1 | M165: =K165*L165 | N165: 3.4 | P165: Direct | Q165: District carried from Sep26 base workbook | R165: Existing | T165: Sep26 is authoritative for the source record.
A166: SEP26-0163 | B166: base_row_0163 | C166: 163 | D166: Wind | E166: operational | F166: Tamil Nadu-Tenkasi | G166: Tamil Nadu | H166: Tenkasi | I166: Tenkasi | K166: 22.88 | L166: 1 | M166: =K166*L166 | N166: 22.88 | P166: Direct | Q166: District carried from Sep26 base workbook | R166: Existing | T166: Sep26 is authoritative for the source record.
A167: SEP26-0164 | B167: base_row_0164 | C167: 164 | D167: Wind | E167: operational | F167: Tamil Nadu-Thanjavur | G167: Tamil Nadu | H167: Thanjavur | I167: Thanjavur | K167: 8.8 | L167: 1 | M167: =K167*L167 | N167: 8.8 | P167: Direct | Q167: District carried from Sep26 base workbook | R167: Existing | T167: Sep26 is authoritative for the source record.
A168: SEP26-0165 | B168: base_row_0165 | C168: 165 | D168: Wind | E168: operational | F168: Tamil Nadu-Theni | G168: Tamil Nadu | H168: Theni | I168: Theni | K168: 574.6 | L168: 1 | M168: =K168*L168 | N168: 574.6 | P168: Direct | Q168: District carried from Sep26 base workbook | R168: Existing | T168: Sep26 is authoritative for the source record.
A169: SEP26-0166 | B169: base_row_0166 | C169: 166 | D169: Wind | E169: operational | F169: Tamil Nadu-Thiruvallur | G169: Tamil Nadu | H169: Thiruvallur | I169: Tiruvallur | K169: 7.2 | L169: 1 | M169: =K169*L169 | N169: 7.2 | P169: Direct | Q169: District carried from Sep26 base workbook | R169: Existing | T169: Sep26 is authoritative for the source record.
A170: SEP26-0167 | B170: base_row_0167 | C170: 167 | D170: Wind | E170: operational | F170: Tamil Nadu-Thoothukkudi | G170: Tamil Nadu | H170: Thoothukkudi | I170: Thoothukudi | K170: 2662.925 | L170: 1 | M170: =K170*L170 | N170: 2662.925 | P170: Direct | Q170: District carried from Sep26 base workbook | R170: Existing | T170: Sep26 is authoritative for the source record.
A171: SEP26-0168 | B171: base_row_0168 | C171: 168 | D171: Wind | E171: operational | F171: Tamil Nadu-Tiruchirappalli | G171: Tamil Nadu | H171: Tiruchirappalli | I171: Tiruchirappalli | K171: 16.9 | L171: 1 | M171: =K171*L171 | N171: 16.9 | P171: Direct | Q171: District carried from Sep26 base workbook | R171: Existing | T171: Sep26 is authoritative for the source record.
A172: SEP26-0169 | B172: base_row_0169 | C172: 169 | D172: Wind | E172: operational | F172: Tamil Nadu-Tirunelveli | G172: Tamil Nadu | H172: Tirunelveli | I172: Tirunelveli | K172: 3797.725 | L172: 1 | M172: =K172*L172 | N172: 3797.725 | P172: Direct | Q172: District carried from Sep26 base workbook | R172: Existing | T172: Sep26 is authoritative for the source record.
A173: SEP26-0170 | B173: base_row_0170 | C173: 170 | D173: Wind | E173: operational | F173: Tamil Nadu-Tiruppur | G173: Tamil Nadu | H173: Tiruppur | I173: Tiruppur | K173: 862.395 | L173: 1 | M173: =K173*L173 | N173: 862.395 | P173: Direct | Q173: District carried from Sep26 base workbook | R173: Existing | T173: Sep26 is authoritative for the source record.
A174: SEP26-0171 | B174: base_row_0171 | C174: 171 | D174: Wind | E174: operational | F174: Tamil Nadu-Tiruppur & Karur | G174: Tamil Nadu | H174: Tiruppur & Karur | I174: Tiruppur | K174: 300 | L174: 0.5 | M174: =K174*L174 | N174: 150 | P174: Direct | Q174: Equal split across districts named in the Sep26 source row | R174: Medium | T174: Sep26 is authoritative for the source record.
A175: SEP26-0171 | B175: base_row_0171 | C175: 171 | D175: Wind | E175: operational | F175: Tamil Nadu-Tiruppur & Karur | G175: Tamil Nadu | H175: Tiruppur & Karur | I175: Karur | K175: 300 | L175: 0.5 | M175: =K175*L175 | N175: 150 | P175: Direct | Q175: Equal split across districts named in the Sep26 source row | R175: Medium | T175: Sep26 is authoritative for the source record.
A176: SEP26-0172 | B176: base_row_0172 | C176: 172 | D176: Wind | E176: operational | F176: Tamil Nadu-Viluppuram | G176: Tamil Nadu | H176: Viluppuram | I176: Viluppuram | K176: 1.7 | L176: 1 | M176: =K176*L176 | N176: 1.7 | P176: Direct | Q176: District carried from Sep26 base workbook | R176: Existing | T176: Sep26 is authoritative for the source record.
A177: SEP26-0173 | B177: base_row_0173 | C177: 173 | D177: Solar | E177: pipeline | F177: INGEL Tamil Nadu 200.0 | G177: Tamil Nadu | H177: Thoothukudi | I177: Thoothukudi | J177: 2027-12-31 | K177: 200 | L177: 1 | M177: =K177*L177 | N177: 200 | O177: INGEL | P177: Solar Utility | Q177: District carried from Sep26 base workbook | R177: Existing | T177: Sep26 is authoritative for the source record.
A178: SEP26-0174 | B178: base_row_0174 | C178: 174 | D178: Solar | E178: operational | F178: Tamil Nadu Chennai 16 | G178: Tamil Nadu | H178: Chennai | I178: Chennai | K178: 16 | L178: 1 | M178: =K178*L178 | N178: 16 | P178: Solar Utility | Q178: District carried from Sep26 base workbook | R178: Existing | T178: Sep26 is authoritative for the source record.
A179: SEP26-0175 | B179: base_row_0175 | C179: 175 | D179: Solar | E179: operational | F179: Tamil Nadu Coimbatore 11.26 | G179: Tamil Nadu | H179: Coimbatore | I179: Coimbatore | K179: 11.26 | L179: 1 | M179: =K179*L179 | N179: 11.26 | P179: Solar Utility | Q179: District carried from Sep26 base workbook | R179: Existing | T179: Sep26 is authoritative for the source record.
A180: SEP26-0176 | B180: base_row_0176 | C180: 176 | D180: Solar | E180: operational | F180: Tamil Nadu Cuddalore 140 | G180: Tamil Nadu | H180: Cuddalore | I180: Cuddalore | K180: 140 | L180: 1 | M180: =K180*L180 | N180: 140 | P180: Solar Utility | Q180: District carried from Sep26 base workbook | R180: Existing | T180: Sep26 is authoritative for the source record.
A181: SEP26-0177 | B181: base_row_0177 | C181: 177 | D181: Solar | E181: operational | F181: Tamil Nadu Dindigul 109.46 | G181: Tamil Nadu | H181: Dindigul | I181: Dindigul | K181: 109.46 | L181: 1 | M181: =K181*L181 | N181: 109.46 | P181: Solar Utility | Q181: District carried from Sep26 base workbook | R181: Existing | T181: Sep26 is authoritative for the source record.
A182: SEP26-0178 | B182: base_row_0178 | C182: 178 | D182: Solar | E182: operational | F182: Tamil Nadu Erode 7 | G182: Tamil Nadu | H182: Erode | I182: Erode | K182: 7 | L182: 1 | M182: =K182*L182 | N182: 7 | P182: Solar Utility | Q182: District carried from Sep26 base workbook | R182: Existing | T182: Sep26 is authoritative for the source record.
A183: SEP26-0179 | B183: base_row_0179 | C183: 179 | D183: Solar | E183: operational | F183: Tamil Nadu Kanniyakumari 1 | G183: Tamil Nadu | H183: Kanniyakumari | I183: Kanyakumari | K183: 1 | L183: 1 | M183: =K183*L183 | N183: 1 | P183: Solar Utility | Q183: District carried from Sep26 base workbook | R183: Existing | T183: Sep26 is authoritative for the source record.
A184: SEP26-0180 | B184: base_row_0180 | C184: 180 | D184: Solar | E184: operational | F184: Tamil Nadu Karur 156.49 | G184: Tamil Nadu | H184: Karur | I184: Karur | K184: 156.49 | L184: 1 | M184: =K184*L184 | N184: 156.49 | P184: Solar Utility | Q184: District carried from Sep26 base workbook | R184: Existing | T184: Sep26 is authoritative for the source record.
A185: SEP26-0181 | B185: base_row_0181 | C185: 181 | D185: Solar | E185: operational | F185: Tamil Nadu Krishnagiri 0.75 | G185: Tamil Nadu | H185: Krishnagiri | I185: Krishnagiri | K185: 0.75 | L185: 1 | M185: =K185*L185 | N185: 0.75 | P185: Solar Utility | Q185: District carried from Sep26 base workbook | R185: Existing | T185: Sep26 is authoritative for the source record.
A186: SEP26-0182 | B186: base_row_0182 | C186: 182 | D186: Solar | E186: operational | F186: Tamil Nadu Madurai 1 | G186: Tamil Nadu | H186: Madurai | I186: Madurai | K186: 1 | L186: 1 | M186: =K186*L186 | N186: 1 | P186: Solar Utility | Q186: District carried from Sep26 base workbook | R186: Existing | T186: Sep26 is authoritative for the source record.
A187: SEP26-0183 | B187: solar_utility_251 | C187: 183 | D187: Solar | E187: operational | F187: Tamil Nadu N.A. 251 | G187: Tamil Nadu | H187: N.A. | I187: Ariyalur | K187: 251 | L187: 0.0021921444 | M187: =K187*L187 | N187: 0.55022825 | P187: Solar Utility | Q187: Hybrid utility-scale target: supplied OSM/Overpass plant footprints and MW tags, calibrated at 49.71 MW/km² for untagged plants; official district-handbook capacities used as lower-bound anchors; residual normalized after retaining directly allocated ICED capacity | R187: Medium | S187: https://www.openstreetmap.org/copyright | Tamil Nadu district statistical handbooks (see Solar District Evidence) | T187: Updated from Sep26 capacity using validated allocation shares. The former combined Tirunelveli share is split between Tirunelveli and Tenkasi using current OSM plant geography.
A188: SEP26-0183 | B188: solar_utility_251 | C188: 183 | D188: Solar | E188: operational | F188: Tamil Nadu N.A. 251 | G188: Tamil Nadu | H188: N.A. | I188: Coimbatore | K188: 251 | L188: 0.0067032405 | M188: =K188*L188 | N188: 1.6825134 | P188: Solar Utility | Q188: Hybrid utility-scale target: supplied OSM/Overpass plant footprints and MW tags, calibrated at 49.71 MW/km² for untagged plants; official district-handbook capacities used as lower-bound anchors; residual normalized after retaining directly allocated ICED capacity | R188: Medium | S188: https://www.openstreetmap.org/copyright | Tamil Nadu district statistical handbooks (see Solar District Evidence) | T188: Updated from Sep26 capacity using validated allocation shares. The former combined Tirunelveli share is split between Tirunelveli and Tenkasi using current OSM plant geography.
A189: SEP26-0183 | B189: solar_utility_251 | C189: 183 | D189: Solar | E189: operational | F189: Tamil Nadu N.A. 251 | G189: Tamil Nadu | H189: N.A. | I189: Cuddalore | K189: 251 | L189: 0.020518168 | M189: =K189*L189 | N189: 5.1500603 | P189: Solar Utility | Q189: Hybrid utility-scale target: supplied OSM/Overpass plant footprints and MW tags, calibrated at 49.71 MW/km² for untagged plants; official district-handbook capacities used as lower-bound anchors; residual normalized after retaining directly allocated ICED capacity | R189: Medium | S189: https://www.openstreetmap.org/copyright | Tamil Nadu district statistical handbooks (see Solar District Evidence) | T189: Updated from Sep26 capacity using validated allocation shares. The former combined Tirunelveli share is split between Tirunelveli and Tenkasi using current OSM plant geography.
A190: SEP26-0183 | B190: solar_utility_251 | C190: 183 | D190: Solar | E190: operational | F190: Tamil Nadu N.A. 251 | G190: Tamil Nadu | H190: N.A. | I190: Dharmapuri | K190: 251 | L190: 0.0011862281 | M190: =K190*L190 | N190: 0.29774326 | P190: Solar Utility | Q190: Hybrid utility-scale target: supplied OSM/Overpass plant footprints and MW tags, calibrated at 49.71 MW/km² for untagged plants; official district-handbook capacities used as lower-bound anchors; residual normalized after retaining directly allocated ICED capacity | R190: Medium | S190: https://www.openstreetmap.org/copyright | Tamil Nadu district statistical handbooks (see Solar District Evidence) | T190: Updated from Sep26 capacity using validated allocation shares. The former combined Tirunelveli share is split between Tirunelveli and Tenkasi using current OSM plant geography.
A191: SEP26-0183 | B191: solar_utility_251 | C191: 183 | D191: Solar | E191: operational | F191: Tamil Nadu N.A. 251 | G191: Tamil Nadu | H191: N.A. | I191: Dindigul | K191: 251 | L191: 0.093110905 | M191: =K191*L191 | N191: 23.370837 | P191: Solar Utility | Q191: Hybrid utility-scale target: supplied OSM/Overpass plant footprints and MW tags, calibrated at 49.71 MW/km² for untagged plants; official district-handbook capacities used as lower-bound anchors; residual normalized after retaining directly allocated ICED capacity | R191: Medium | S191: https://www.openstreetmap.org/copyright | Tamil Nadu district statistical handbooks (see Solar District Evidence) | T191: Updated from Sep26 capacity using validated allocation shares. The former combined Tirunelveli share is split between Tirunelveli and Tenkasi using current OSM plant geography.
A192: SEP26-0183 | B192: solar_utility_251 | C192: 183 | D192: Solar | E192: operational | F192: Tamil Nadu N.A. 251 | G192: Tamil Nadu | H192: N.A. | I192: Erode | K192: 251 | L192: 0.0056708076 | M192: =K192*L192 | N192: 1.4233727 | P192: Solar Utility | Q192: Hybrid utility-scale target: supplied OSM/Overpass plant footprints and MW tags, calibrated at 49.71 MW/km² for untagged plants; official district-handbook capacities used as lower-bound anchors; residual normalized after retaining directly allocated ICED capacity | R192: Medium | S192: https://www.openstreetmap.org/copyright | Tamil Nadu district statistical handbooks (see Solar District Evidence) | T192: Updated from Sep26 capacity using validated allocation shares. The former combined Tirunelveli share is split between Tirunelveli and Tenkasi using current OSM plant geography.
A193: SEP26-0183 | B193: solar_utility_251 | C193: 183 | D193: Solar | E193: operational | F193: Tamil Nadu N.A. 251 | G193: Tamil Nadu | H193: N.A. | I193: Kanchipuram | K193: 251 | L193: 0.0033548102 | M193: =K193*L193 | N193: 0.84205736 | P193: Solar Utility | Q193: Hybrid utility-scale target: supplied OSM/Overpass plant footprints and MW tags, calibrated at 49.71 MW/km² for untagged plants; official district-handbook capacities used as lower-bound anchors; residual normalized after retaining directly allocated ICED capacity | R193: Medium | S193: https://www.openstreetmap.org/copyright | Tamil Nadu district statistical handbooks (see Solar District Evidence) | T193: Updated from Sep26 capacity using validated allocation shares. The former combined Tirunelveli share is split between Tirunelveli and Tenkasi using current OSM plant geography.
A194: SEP26-0183 | B194: solar_utility_251 | C194: 183 | D194: Solar | E194: operational | F194: Tamil Nadu N.A. 251 | G194: Tamil Nadu | H194: N.A. | I194: Kanyakumari | K194: 251 | L194: 0.00011283154 | M194: =K194*L194 | N194: 0.028320717 | P194: Solar Utility | Q194: Hybrid utility-scale target: supplied OSM/Overpass plant footprints and MW tags, calibrated at 49.71 MW/km² for untagged plants; official district-handbook capacities used as lower-bound anchors; residual normalized after retaining directly allocated ICED capacity | R194: Medium | S194: https://www.openstreetmap.org/copyright | Tamil Nadu district statistical handbooks (see Solar District Evidence) | T194: Updated from Sep26 capacity using validated allocation shares. The former combined Tirunelveli share is split between Tirunelveli and Tenkasi using current OSM plant geography.
A195: SEP26-0183 | B195: solar_utility_251 | C195: 183 | D195: Solar | E195: operational | F195: Tamil Nadu N.A. 251 | G195: Tamil Nadu | H195: N.A. | I195: Karur | K195: 251 | L195: 0.052023027 | M195: =K195*L195 | N195: 13.05778 | P195: Solar Utility | Q195: Hybrid utility-scale target: supplied OSM/Overpass plant footprints and MW tags, calibrated at 49.71 MW/km² for untagged plants; official district-handbook capacities used as lower-bound anchors; residual normalized after retaining directly allocated ICED capacity | R195: Medium | S195: https://www.openstreetmap.org/copyright | Tamil Nadu district statistical handbooks (see Solar District Evidence) | T195: Updated from Sep26 capacity using validated allocation shares. The former combined Tirunelveli share is split between Tirunelveli and Tenkasi using current OSM plant geography.
A196: SEP26-0183 | B196: solar_utility_251 | C196: 183 | D196: Solar | E196: operational | F196: Tamil Nadu N.A. 251 | G196: Tamil Nadu | H196: N.A. | I196: Krishnagiri | K196: 251 | L196: 0.0008285934 | M196: =K196*L196 | N196: 0.20797694 | P196: Solar Utility | Q196: Hybrid utility-scale target: supplied OSM/Overpass plant footprints and MW tags, calibrated at 49.71 MW/km² for untagged plants; official district-handbook capacities used as lower-bound anchors; residual normalized after retaining directly allocated ICED capacity | R196: Medium | S196: https://www.openstreetmap.org/copyright | Tamil Nadu district statistical handbooks (see Solar District Evidence) | T196: Updated from Sep26 capacity using validated allocation shares. The former combined Tirunelveli share is split between Tirunelveli and Tenkasi using current OSM plant geography.
A197: SEP26-0183 | B197: solar_utility_251 | C197: 183 | D197: Solar | E197: operational | F197: Tamil Nadu N.A. 251 | G197: Tamil Nadu | H197: N.A. | I197: Madurai | K197: 251 | L197: 0.0081000941 | M197: =K197*L197 | N197: 2.0331236 | P197: Solar Utility | Q197: Hybrid utility-scale target: supplied OSM/Overpass plant footprints and MW tags, calibrated at 49.71 MW/km² for untagged plants; official district-handbook capacities used as lower-bound anchors; residual normalized after retaining directly allocated ICED capacity | R197: Medium | S197: https://www.openstreetmap.org/copyright | Tamil Nadu district statistical handbooks (see Solar District Evidence) | T197: Updated from Sep26 capacity using validated allocation shares. The former combined Tirunelveli share is split between Tirunelveli and Tenkasi using current OSM plant geography.
A198: SEP26-0183 | B198: solar_utility_251 | C198: 183 | D198: Solar | E198: operational | F198: Tamil Nadu N.A. 251 | G198: Tamil Nadu | H198: N.A. | I198: Nagapattinam | K198: 251 | L198: 0.00041950283 | M198: =K198*L198 | N198: 0.10529521 | P198: Solar Utility | Q198: Hybrid utility-scale target: supplied OSM/Overpass plant footprints and MW tags, calibrated at 49.71 MW/km² for untagged plants; official district-handbook capacities used as lower-bound anchors; residual normalized after retaining directly allocated ICED capacity | R198: Medium | S198: https://www.openstreetmap.org/copyright | Tamil Nadu district statistical handbooks (see Solar District Evidence) | T198: Updated from Sep26 capacity using validated allocation shares. The former combined Tirunelveli share is split between Tirunelveli and Tenkasi using current OSM plant geography.
... A307: SEP26-0186 | B307: solar_rooftop | C307: 186 | D307: Solar | E307: operational | F307: Tamil Nadu N.A. Rooftop (Grid Connected) 1635.8 | G307: Tamil Nadu | H307: N.A. | I307: Virudhunagar | K307: 1635.8 | L307: 0.025373632 | M307: =K307*L307 | N307: 41.506188 | P307: Solar Rooftop | Q307: District share of 83,906 PM Surya Ghar rooftop installations as of 20 July 2026; six post-2011 districts recombined to the workbook's 32-district boundary system | R307: Medium | S307: https://sansad.in/getFile/lsapps/loksabhaquestions/annex/188/AS59_dKLc7G.pdf?source=lsapps | T307: Updated from Sep26 capacity using validated allocation shares. The former combined Tirunelveli share is split between Tirunelveli and Tenkasi using current OSM plant geography.
A308: SEP26-0187 | B308: base_row_0187 | C308: 187 | D308: Solar | E308: operational | F308: Tamil Nadu Nagapattinam 5 | G308: Tamil Nadu | H308: Nagapattinam | I308: Nagapattinam | K308: 5 | L308: 1 | M308: =K308*L308 | N308: 5 | P308: Solar Utility | Q308: District carried from Sep26 base workbook | R308: Existing | T308: Sep26 is authoritative for the source record.
A309: SEP26-0188 | B309: base_row_0188 | C309: 188 | D309: Solar | E309: operational | F309: Tamil Nadu Perambalur 10 | G309: Tamil Nadu | H309: Perambalur | I309: Perambalur | K309: 10 | L309: 1 | M309: =K309*L309 | N309: 10 | P309: Solar Utility | Q309: District carried from Sep26 base workbook | R309: Existing | T309: Sep26 is authoritative for the source record.
A310: SEP26-0189 | B310: base_row_0189 | C310: 189 | D310: Solar | E310: operational | F310: Tamil Nadu Pudukkottai 20 | G310: Tamil Nadu | H310: Pudukkottai | I310: Pudukkottai | K310: 20 | L310: 1 | M310: =K310*L310 | N310: 20 | P310: Solar Utility | Q310: District carried from Sep26 base workbook | R310: Existing | T310: Sep26 is authoritative for the source record.
A311: SEP26-0190 | B311: base_row_0190 | C311: 190 | D311: Solar | E311: operational | F311: Tamil Nadu Ramanathapuram 245 | G311: Tamil Nadu | H311: Ramanathapuram | I311: Ramanathapuram | K311: 245 | L311: 1 | M311: =K311*L311 | N311: 245 | P311: Solar Utility | Q311: District carried from Sep26 base workbook | R311: Existing | T311: Sep26 is authoritative for the source record.
A312: SEP26-0191 | B312: base_row_0191 | C312: 191 | D312: Solar | E312: operational | F312: Tamil Nadu Ramanathapuram Kamuthi Solar Power Project 648 | G312: Tamil Nadu | H312: Ramanathapuram | I312: Ramanathapuram | K312: 648 | L312: 1 | M312: =K312*L312 | N312: 648 | P312: Solar Utility | Q312: District carried from Sep26 base workbook | R312: Existing | T312: Sep26 is authoritative for the source record.
A313: SEP26-0192 | B313: base_row_0192 | C313: 192 | D313: Solar | E313: operational | F313: Tamil Nadu Sivaganga 16.55 | G313: Tamil Nadu | H313: Sivaganga | I313: Sivaganga | K313: 16.55 | L313: 1 | M313: =K313*L313 | N313: 16.55 | P313: Solar Utility | Q313: District carried from Sep26 base workbook | R313: Existing | T313: Sep26 is authoritative for the source record.
A314: SEP26-0193 | B314: base_row_0193 | C314: 193 | D314: Solar | E314: operational | F314: Tamil Nadu Thoothukkudi 28 | G314: Tamil Nadu | H314: Thoothukkudi | I314: Thoothukudi | K314: 28 | L314: 1 | M314: =K314*L314 | N314: 28 | P314: Solar Utility | Q314: District carried from Sep26 base workbook | R314: Existing | T314: Sep26 is authoritative for the source record.
A315: SEP26-0194 | B315: base_row_0194 | C315: 194 | D315: Solar | E315: operational | F315: Tamil Nadu Tiruchirappalli 169 | G315: Tamil Nadu | H315: Tiruchirappalli | I315: Tiruchirappalli | K315: 169 | L315: 1 | M315: =K315*L315 | N315: 169 | P315: Solar Utility | Q315: District carried from Sep26 base workbook | R315: Existing | T315: Sep26 is authoritative for the source record.
A316: SEP26-0195 | B316: base_row_0195 | C316: 195 | D316: Solar | E316: operational | F316: Tamil Nadu Tirunelveli 309.36 | G316: Tamil Nadu | H316: Tirunelveli | I316: Tirunelveli | K316: 309.36 | L316: 1 | M316: =K316*L316 | N316: 309.36 | P316: Solar Utility | Q316: District carried from Sep26 base workbook | R316: Existing | T316: Sep26 is authoritative for the source record.
A317: SEP26-0196 | B317: base_row_0196 | C317: 196 | D317: Solar | E317: operational | F317: Tamil Nadu Tirunelveli, Tuticorin, Virudhunagar and Ramanathapuram 351 | G317: Tamil Nadu | H317: Tirunelveli, Tuticorin, Virudhunagar and Ramanathapuram | I317: Tirunelveli | K317: 351 | L317: 0.25 | M317: =K317*L317 | N317: 87.75 | P317: Solar Utility | Q317: Equal split across districts named in the Sep26 source row | R317: Medium | T317: Sep26 is authoritative for the source record.
A318: SEP26-0196 | B318: base_row_0196 | C318: 196 | D318: Solar | E318: operational | F318: Tamil Nadu Tirunelveli, Tuticorin, Virudhunagar and Ramanathapuram 351 | G318: Tamil Nadu | H318: Tirunelveli, Tuticorin, Virudhunagar and Ramanathapuram | I318: Thoothukudi | K318: 351 | L318: 0.25 | M318: =K318*L318 | N318: 87.75 | P318: Solar Utility | Q318: Equal split across districts named in the Sep26 source row | R318: Medium | T318: Sep26 is authoritative for the source record.
A319: SEP26-0196 | B319: base_row_0196 | C319: 196 | D319: Solar | E319: operational | F319: Tamil Nadu Tirunelveli, Tuticorin, Virudhunagar and Ramanathapuram 351 | G319: Tamil Nadu | H319: Tirunelveli, Tuticorin, Virudhunagar and Ramanathapuram | I319: Virudhunagar | K319: 351 | L319: 0.25 | M319: =K319*L319 | N319: 87.75 | P319: Solar Utility | Q319: Equal split across districts named in the Sep26 source row | R319: Medium | T319: Sep26 is authoritative for the source record.
... A324: SEP26-0200 | B324: base_row_0200 | C324: 200 | D324: Solar | E324: operational | F324: Tamil Nadu Virudhunagar 685.4 | G324: Tamil Nadu | H324: Virudhunagar | I324: Virudhunagar | K324: 685.4 | L324: 1 | M324: =K324*L324 | N324: 685.4 | P324: Solar Utility | Q324: District carried from Sep26 base workbook | R324: Existing | T324: Sep26 is authoritative for the source record.
A325: SEP26-0201 | B325: base_row_0201 | C325: 201 | D325: Oil & Gas | E325: operational | F325: Basin Bridge Gas Turbine Power Station | G325: Tamil Nadu | H325: Chennai | I325: Chennai | J325: 1996-02-12 | K325: 30 | L325: 1 | M325: =K325*L325 | N325: 30 | O325: Tamil Nadu Generation and Distribution Corp. Ltd. | P325: Direct | Q325: District carried from Sep26 base workbook | R325: Existing | T325: Sep26 is authoritative for the source record.
A326: SEP26-0202 | B326: base_row_0202 | C326: 202 | D326: Oil & Gas | E326: operational | F326: Basin Bridge Gas Turbine Power Station | G326: Tamil Nadu | H326: Chennai | I326: Chennai | J326: 1996-02-25 | K326: 30 | L326: 1 | M326: =K326*L326 | N326: 30 | O326: Tamil Nadu Generation and Distribution Corp. Ltd. | P326: Direct | Q326: District carried from Sep26 base workbook | R326: Existing | T326: Sep26 is authoritative for the source record.
A327: SEP26-0203 | B327: base_row_0203 | C327: 203 | D327: Oil & Gas | E327: operational | F327: Basin Bridge Gas Turbine Power Station | G327: Tamil Nadu | H327: Chennai | I327: Chennai | J327: 1996-03-26 | K327: 30 | L327: 1 | M327: =K327*L327 | N327: 30 | O327: Tamil Nadu Generation and Distribution Corp. Ltd. | P327: Direct | Q327: District carried from Sep26 base workbook | R327: Existing | T327: Sep26 is authoritative for the source record.
A328: SEP26-0204 | B328: base_row_0204 | C328: 204 | D328: Oil & Gas | E328: operational | F328: Basin Bridge Gas Turbine Power Station | G328: Tamil Nadu | H328: Chennai | I328: Chennai | J328: 1996-03-31 | K328: 30 | L328: 1 | M328: =K328*L328 | N328: 30 | O328: Tamil Nadu Generation and Distribution Corp. Ltd. | P328: Direct | Q328: District carried from Sep26 base workbook | R328: Existing | T328: Sep26 is authoritative for the source record.
A329: SEP26-0205 | B329: base_row_0205 | C329: 205 | D329: Oil & Gas | E329: Temporarily Closed | F329: Karuppur Combined Cycle Power Plant | G329: Tamil Nadu | H329: Thanjavur | I329: Thanjavur | J329: 2005-08-01 | K329: 70 | L329: 1 | M329: =K329*L329 | N329: 70 | O329: Lanco Tanjore Power Co. Ltd. | P329: Direct | Q329: District carried from Sep26 base workbook | R329: Existing | T329: Sep26 is authoritative for the source record.
A330: SEP26-0206 | B330: base_row_0206 | C330: 206 | D330: Oil & Gas | E330: Temporarily Closed | F330: Karuppur Combined Cycle Power Plant | G330: Tamil Nadu | H330: Thanjavur | I330: Thanjavur | J330: 2005-08-01 | K330: 49.8 | L330: 1 | M330: =K330*L330 | N330: 49.8 | O330: Lanco Tanjore Power Co. Ltd. | P330: Direct | Q330: District carried from Sep26 base workbook | R330: Existing | T330: Sep26 is authoritative for the source record.
A331: SEP26-0207 | B331: base_row_0207 | C331: 207 | D331: Oil & Gas | E331: operational | F331: Kovilkalappal (Thirumakotai) Gas Combined Cycle Gas Turbine Power Station | G331: Tamil Nadu | H331: Thiruvarur | I331: Thiruvarur | J331: 2001-02-05 | K331: 69.65 | L331: 1 | M331: =K331*L331 | N331: 69.65 | O331: Tamil Nadu Generation and Distribution Corp. Ltd. | P331: Direct | Q331: District carried from Sep26 base workbook | R331: Existing | T331: Sep26 is authoritative for the source record.
A332: SEP26-0208 | B332: base_row_0208 | C332: 208 | D332: Oil & Gas | E332: operational | F332: Kovilkalappal (Thirumakotai) Gas Combined Cycle Gas Turbine Power Station | G332: Tamil Nadu | H332: Thiruvarur | I332: Thiruvarur | J332: 2001-02-05 | K332: 38.23 | L332: 1 | M332: =K332*L332 | N332: 38.23 | O332: Tamil Nadu Generation and Distribution Corp. Ltd. | P332: Direct | Q332: District carried from Sep26 base workbook | R332: Existing | T332: Sep26 is authoritative for the source record.
A333: SEP26-0209 | B333: base_row_0209 | C333: 209 | D333: Oil & Gas | E333: operational | F333: Kuttalam Gas Turbine Power Station | G333: Tamil Nadu | H333: Nagapattinam | I333: Nagapattinam | J333: 2003-11-27 | K333: 63 | L333: 1 | M333: =K333*L333 | N333: 63 | O333: Tamil Nadu Generation and Distribution Corp. Ltd. | P333: Direct | Q333: District carried from Sep26 base workbook | R333: Existing | T333: Sep26 is authoritative for the source record.
A334: SEP26-0210 | B334: base_row_0210 | C334: 210 | D334: Oil & Gas | E334: operational | F334: Kuttalam Gas Turbine Power Station | G334: Tamil Nadu | H334: Nagapattinam | I334: Nagapattinam | J334: 2004-03-24 | K334: 37 | L334: 1 | M334: =K334*L334 | N334: 37 | O334: Tamil Nadu Generation and Distribution Corp. Ltd. | P334: Direct | Q334: District carried from Sep26 base workbook | R334: Existing | T334: Sep26 is authoritative for the source record.
A335: SEP26-0211 | B335: base_row_0211 | C335: 211 | D335: Oil & Gas | E335: operational | F335: Pillaiperumalnallur (PPN) Power Plant Phase I | G335: Tamil Nadu | H335: Nagapattinam | I335: Nagapattinam | J335: 2001-04-26 | K335: 225 | L335: 1 | M335: =K335*L335 | N335: 225 | O335: PPN Power Generating Co. Private Ltd. | P335: Direct | Q335: District carried from Sep26 base workbook | R335: Existing | T335: Sep26 is authoritative for the source record.
A336: SEP26-0212 | B336: base_row_0212 | C336: 212 | D336: Oil & Gas | E336: operational | F336: Pillaiperumalnallur (PPN) Power Plant Phase I | G336: Tamil Nadu | H336: Nagapattinam | I336: Nagapattinam | J336: 2001-04-26 | K336: 105.5 | L336: 1 | M336: =K336*L336 | N336: 105.5 | O336: PPN Power Generating Co. Private Ltd. | P336: Direct | Q336: District carried from Sep26 base workbook | R336: Existing | T336: Sep26 is authoritative for the source record.
... A441: SEP26-0317 | B441: base_row_0317 | C441: 317 | D441: Small-Hydro | E441: operational | F441: Sholayar II Power House | G441: Tamil Nadu | H441: Coimbatore | I441: Coimbatore | J441: 1971-03-29 | K441: 25 | L441: 1 | M441: =K441*L441 | N441: 25 | O441: Tamil Nadu Generation and Distribution Corp. Ltd. (TANGEDCO) | P441: Direct | Q441: District carried from Sep26 base workbook | R441: Existing | T441: Sep26 is authoritative for the source record.
A442: SEP26-0318 | B442: base_row_0318 | C442: 318 | D442: Small-Hydro | E442: operational | F442: Tamil Nadu Small Hydro Project Bunched | G442: Tamil Nadu | H442: Location TBC | I442: Location TBC | J442: N.A. | K442: 0.35 | L442: 1 | M442: =K442*L442 | N442: 0.35 | P442: Direct | Q442: District carried from Sep26 base workbook | R442: Existing | T442: Sep26 is authoritative for the source record.
A443: SEP26-0319 | B443: base_row_0319 | C443: 319 | D443: Small-Hydro | E443: operational | F443: Thirumurthy Mini Hydel Project | G443: Tamil Nadu | H443: Tiruppur | I443: Tiruppur | J443: 2000-03-20 | K443: 0.65 | L443: 1 | M443: =K443*L443 | N443: 0.65 | O443: Tamil Nadu Generation and Distribution Corp. Ltd. (TANGEDCO) | P443: Direct | Q443: District carried from Sep26 base workbook | R443: Existing | T443: Sep26 is authoritative for the source record.
A444: SEP26-0320 | B444: base_row_0320 | C444: 320 | D444: Small-Hydro | E444: operational | F444: Thirumurthy Mini Hydel Project | G444: Tamil Nadu | H444: Tiruppur | I444: Tiruppur | J444: 2000-03-20 | K444: 0.65 | L444: 1 | M444: =K444*L444 | N444: 0.65 | O444: Tamil Nadu Generation and Distribution Corp. Ltd. (TANGEDCO) | P444: Direct | Q444: District carried from Sep26 base workbook | R444: Existing | T444: Sep26 is authoritative for the source record.
A445: SEP26-0321 | B445: base_row_0321 | C445: 321 | D445: Small-Hydro | E445: operational | F445: Thirumurthy Mini Hydel Project | G445: Tamil Nadu | H445: Tiruppur | I445: Tiruppur | J445: 2000-03-20 | K445: 0.65 | L445: 1 | M445: =K445*L445 | N445: 0.65 | O445: Tamil Nadu Generation and Distribution Corp. Ltd. (TANGEDCO) | P445: Direct | Q445: District carried from Sep26 base workbook | R445: Existing | T445: Sep26 is authoritative for the source record.
A446: SEP26-0322 | B446: base_row_0322 | C446: 322 | D446: Small-Hydro | E446: operational | F446: Vaigai Hydro Power Project | G446: Tamil Nadu | H446: Kanniyakumari | I446: Kanyakumari | J446: 1990-03-04 | K446: 3 | L446: 1 | M446: =K446*L446 | N446: 3 | O446: Tamil Nadu Generation and Distribution Corp. Ltd. (TANGEDCO) | P446: Direct | Q446: District carried from Sep26 base workbook | R446: Existing | T446: Sep26 is authoritative for the source record.
A447: SEP26-0323 | B447: base_row_0323 | C447: 323 | D447: Small-Hydro | E447: operational | F447: Vaigai Hydro Power Project | G447: Tamil Nadu | H447: Theni | I447: Theni | J447: 1990-03-04 | K447: 3 | L447: 1 | M447: =K447*L447 | N447: 3 | O447: Tamil Nadu Generation and Distribution Corp. Ltd. (TANGEDCO) | P447: Direct | Q447: District carried from Sep26 base workbook | R447: Existing | T447: Sep26 is authoritative for the source record.

Sheet Allocation QC
A1: Source Record ID | B1: Base Excel Row | C1: Source | D1: Name of Power Plant | E1: Base Capacity (MW) | F1: Formula Allocated (MW) | G1: Formula Difference (MW) | H1: Formula Check | I1: Verified Allocated (MW) | J1: Verified Difference (MW) | K1: Verified Check | L1: Allocation Rows
A2: SEP26-0002 | B2: 2 | C2: Coal | D2: Ennore SEZ Expansion SCTPP | E2: 660 | F2: =SUMIF('District Allocation'!$A$2:$A$447,A2,'District Allocation'!$M$2:$M$447) | G2: =F2-E2 | H2: =IF(ABS(G2)<=0.000001,"OK","FAIL") | I2: 660 | J2: 0 | K2: OK | L2: 1
A3: SEP26-0003 | B3: 3 | C3: Coal | D3: Ennore SEZ Expansion SCTPP | E3: 660 | F3: =SUMIF('District Allocation'!$A$2:$A$447,A3,'District Allocation'!$M$2:$M$447) | G3: =F3-E3 | H3: =IF(ABS(G3)<=0.000001,"OK","FAIL") | I3: 660 | J3: 0 | K3: OK | L3: 1
A4: SEP26-0004 | B4: 4 | C4: Coal | D4: Ennore TPS | E4: 60 | F4: =SUMIF('District Allocation'!$A$2:$A$447,A4,'District Allocation'!$M$2:$M$447) | G4: =F4-E4 | H4: =IF(ABS(G4)<=0.000001,"OK","FAIL") | I4: 60 | J4: 0 | K4: OK | L4: 1
A5: SEP26-0005 | B5: 5 | C5: Coal | D5: Ennore TPS | E5: 60 | F5: =SUMIF('District Allocation'!$A$2:$A$447,A5,'District Allocation'!$M$2:$M$447) | G5: =F5-E5 | H5: =IF(ABS(G5)<=0.000001,"OK","FAIL") | I5: 60 | J5: 0 | K5: OK | L5: 1
A6: SEP26-0006 | B6: 6 | C6: Coal | D6: Ennore TPS | E6: 110 | F6: =SUMIF('District Allocation'!$A$2:$A$447,A6,'District Allocation'!$M$2:$M$447) | G6: =F6-E6 | H6: =IF(ABS(G6)<=0.000001,"OK","FAIL") | I6: 110 | J6: 0 | K6: OK | L6: 1
A7: SEP26-0007 | B7: 7 | C7: Coal | D7: Ennore TPS | E7: 110 | F7: =SUMIF('District Allocation'!$A$2:$A$447,A7,'District Allocation'!$M$2:$M$447) | G7: =F7-E7 | H7: =IF(ABS(G7)<=0.000001,"OK","FAIL") | I7: 110 | J7: 0 | K7: OK | L7: 1
A8: SEP26-0008 | B8: 8 | C8: Coal | D8: Ennore TPS | E8: 110 | F8: =SUMIF('District Allocation'!$A$2:$A$447,A8,'District Allocation'!$M$2:$M$447) | G8: =F8-E8 | H8: =IF(ABS(G8)<=0.000001,"OK","FAIL") | I8: 110 | J8: 0 | K8: OK | L8: 1
A9: SEP26-0009 | B9: 9 | C9: Coal | D9: ITPCL or Cuddalore TPP | E9: 600 | F9: =SUMIF('District Allocation'!$A$2:$A$447,A9,'District Allocation'!$M$2:$M$447) | G9: =F9-E9 | H9: =IF(ABS(G9)<=0.000001,"OK","FAIL") | I9: 600 | J9: 0 | K9: OK | L9: 1
A10: SEP26-0010 | B10: 10 | C10: Coal | D10: ITPCL or Cuddalore TPP | E10: 600 | F10: =SUMIF('District Allocation'!$A$2:$A$447,A10,'District Allocation'!$M$2:$M$447) | G10: =F10-E10 | H10: =IF(ABS(G10)<=0.000001,"OK","FAIL") | I10: 600 | J10: 0 | K10: OK | L10: 1
A11: SEP26-0011 | B11: 11 | C11: Coal | D11: Mettur TPS | E11: 210 | F11: =SUMIF('District Allocation'!$A$2:$A$447,A11,'District Allocation'!$M$2:$M$447) | G11: =F11-E11 | H11: =IF(ABS(G11)<=0.000001,"OK","FAIL") | I11: 210 | J11: 0 | K11: OK | L11: 1
A12: SEP26-0012 | B12: 12 | C12: Coal | D12: Mettur TPS | E12: 210 | F12: =SUMIF('District Allocation'!$A$2:$A$447,A12,'District Allocation'!$M$2:$M$447) | G12: =F12-E12 | H12: =IF(ABS(G12)<=0.000001,"OK","FAIL") | I12: 210 | J12: 0 | K12: OK | L12: 1
A13: SEP26-0013 | B13: 13 | C13: Coal | D13: Mettur TPS | E13: 210 | F13: =SUMIF('District Allocation'!$A$2:$A$447,A13,'District Allocation'!$M$2:$M$447) | G13: =F13-E13 | H13: =IF(ABS(G13)<=0.000001,"OK","FAIL") | I13: 210 | J13: 0 | K13: OK | L13: 1
... A323: SEP26-0323 | B323: 323 | C323: Small-Hydro | D323: Vaigai Hydro Power Project | E323: 3 | F323: =SUMIF('District Allocation'!$A$2:$A$447,A323,'District Allocation'!$M$2:$M$447) | G323: =F323-E323 | H323: =IF(ABS(G323)<=0.000001,"OK","FAIL") | I323: 3 | J323: 0 | K323: OK | L323: 1

Sheet Methodology
A1: Tamil Nadu Sep26 District Allocation - Methodology and Sources
A2: Quality control | B2: Value
A3: Sep26 base rows | B3: 322
A4: District allocation rows | B4: 446
A5: Rows failing verified reconciliation | B5: 0
A6: Operational solar MW | B6: 14121.46
A7: Operational wind MW | B7: 12299.49
A8: Wind turbine points assigned | B8: 12807
A9: Solar plant points assigned | B9: 343
A11: Topic | B11: Method / interpretation
A12: Authority | B12: Sep26 PlantInfo is authoritative for every source record, capacity, status, date, district, and agency.
A13: Scope | B13: Only statewide or unresolved solar and wind rows are redistributed. Direct Sep26 district records are retained.
A14: Stable matching | B14: Semantic allocation IDs are used; Excel row numbers and names containing capacity values are not used as merge keys.
A15: Solar utility | B15: Validated utility allocation shares are retained. The updated 9,143.18 MW unspecified row is multiplied by those shares.
A16: Solar Tenkasi | B16: The old combined Tirunelveli utility-solar share is split between Tirunelveli and Tenkasi using supplied OSM plant capacity proxies rejoined to current boundaries.
A17: Rooftop and off-grid | B17: The previous PM Surya Ghar-derived shares are retained because those allocations are based on installation counts rather than plant coordinates.
A18: Wind | B18: OSM turbine proxy is scaled to Sep26 operational wind. Known Sep26 district MW is subtracted; positive gaps are normalized to the 256.375 MW unresolved record.
A19: Boundary system | B19: Tenkasi is separate. Chengalpattu->Kanchipuram; Kallakurichi->Viluppuram; Mayiladuthurai->Nagapattinam; Ranipet and Tirupathur->Vellore.
A20: Boundary source | B20: https://cdn.jsdelivr.net/gh/udit-001/india-maps-data@2884453/geojson/states/tamil-nadu.geojson
A21: Limitations | B21: OSM is community-maintained. Most wind turbines lack MW tags, so turbine count is the main wind proxy. Solar footprint area is also a proxy where explicit MW tags are absent.

Sheet District Summary
A1: Operational Capacity Aggregated by Allocated District and Technology (MW)
A2: Operational records only. Values are independently verified from the allocation table. Sep26 remains authoritative for all source capacities.
A3: District | B3: Coal | C3: Oil & Gas | D3: Nuclear | E3: Bio Power | F3: Hydro | G3: Small-Hydro | H3: Wind | I3: Solar Utility | J3: Solar Rooftop | K3: Solar Off-grid | L3: Solar Total | M3: Total
A4: Ariyalur | B4: 0 | C4: 0 | D4: 0 | E4: 0 | F4: 0 | G4: 0 | H4: 22 | I4: 5.561021 | J4: 4.016099 | K4: 0.093184397 | L4: 9.6703044 | M4: 31.670304
A5: Chennai | B5: 0 | C5: 120 | D5: 0 | E5: 0.25 | F5: 0 | G5: 0 | H5: 3.125 | I5: 18.073221 | J5: 183.45384 | K5: 4.2681021 | L5: 205.79516 | M5: 329.17016
A6: Coimbatore | B6: 0 | C6: 0 | D6: 0 | E6: 11.6 | F6: 854 | G6: 53.5 | H6: 2175.4 | I6: 124.46219 | J6: 209.09059 | K6: 5.3839133 | L6: 338.93669 | M6: 3433.4367
A7: Cuddalore | B7: 4840 | C7: 0 | D7: 0 | E7: 90.68 | F7: 0 | G7: 0 | H7: 0 | I7: 944.04902 | J7: 36.554299 | K7: 5.0104028 | L7: 985.61372 | M7: 5916.2937
A8: Dharmapuri | B8: 0 | C8: 0 | D8: 0 | E8: 15 | F8: 0 | G8: 0 | H8: 196 | I8: 127.40246 | J8: 12.847618 | K8: 0.98660486 | L8: 141.23669 | M8: 352.23669
A9: Dindigul | B9: 0 | C9: 0 | D9: 0 | E9: 7.5 | F9: 0 | G9: 0 | H9: 319.62983 | I9: 407.8599 | J9: 23.823655 | K9: 0.89702609 | L9: 432.58058 | M9: 759.71041
A10: Erode | B10: 0 | C10: 0 | D10: 0 | E10: 97 | F10: 90 | G10: 16 | H10: 129.33 | I10: 825.79533 | J10: 78.255443 | K10: 6.2680727 | L10: 910.31885 | M10: 1242.6488
A11: Kanchipuram | B11: 0 | C11: 0 | D11: 440 | E11: 63 | F11: 0 | G11: 0 | H11: 7.65 | I11: 530.9621 | J11: 182.55704 | K11: 7.127541 | L11: 720.64668 | M11: 1231.2967
A12: Kanyakumari | B12: 0 | C12: 0 | D12: 0 | E12: 0 | F12: 100 | G12: 17.3 | H12: 349.375 | I12: 1.2862305 | J12: 36.300856 | K12: 0.84227838 | L12: 38.429365 | M12: 505.10436
A13: Karur | B13: 0 | C13: 0 | D13: 0 | E13: 22 | F13: 0 | G13: 0 | H13: 699.595 | I13: 470.90518 | J13: 43.163316 | K13: 2.0113138 | L13: 516.07981 | M13: 1237.6748
A14: Krishnagiri | B14: 0 | C14: 0 | D14: 0 | E14: 0 | F14: 0 | G14: 0 | H14: 0 | I14: 2.8519716 | J14: 17.760515 | K14: 0.41209216 | L14: 21.024579 | M14: 21.024579
A15: Location TBC | B15: 0 | C15: 0 | D15: 0 | E15: 0 | F15: 0 | G15: 0.35 | H15: 0 | I15: 0 | J15: 0 | K15: 0 | L15: 0 | M15: 0.35
... A38: Virudhunagar | B38: 0 | C38: 0 | D38: 0 | E38: 14.95 | F38: 0 | G38: 0 | H38: 0 | I38: 1170.5649 | J38: 41.506188 | K38: 1.6492665 | L38: 1213.7203 | M38: 1228.6703

Sheet Report Comparison
A1: District-Aggregated Capacity vs Tamil Nadu Resource Adequacy Report
A2: Important: the workbook represents operational physical capacity in the ICED dataset, while Table 6 reports capacity contracted to Tamil Nadu as of 31 March 2025. The comparison is therefore diagnostic, not a like-for-like validation.
A4: Technology | B4: District aggregate (MW) | C4: RA report Table 6 (MW) | D4: Difference (MW) | E4: Difference (%) | F4: Alignment note
A5: Coal | B5: ='District Summary'!B36 | C5: 12808 | D5: =B5-C5 | E5: =IF(C5=0,"",D5/C5) | F5: Physical installed capacity versus contracted capacity.
A6: Gas | B6: ='District Summary'!C36 | C6: 408 | D6: =B6-C6 | E6: =IF(C6=0,"",D6/C6) | F6: Workbook source: Oil & Gas.
A7: Nuclear | B7: ='District Summary'!D36 | C7: 1448 | D7: =B7-C7 | E7: =IF(C7=0,"",D7/C7) | F7: Physical station capacity versus Tamil Nadu's contracted share.
A8: Biomass | B8: ='District Summary'!E36 | C8: 891 | D8: =B8-C8 | E8: =IF(C8=0,"",D8/C8) | F8: Workbook source: Bio Power, including residual statewide categories.
A9: Hydro | B9: ='District Summary'!F36 | C9: 1866 | D9: =B9-C9 | E9: =IF(C9=0,"",D9/C9) | F9: Excludes the 400 MW Kadamparai PSP from workbook Hydro.
A10: PSP | B10: ='District Summary'!G36 | C10: 400 | D10: =B10-C10 | E10: =IF(C10=0,"",D10/C10) | F10: Workbook PSP is the 400 MW Kadamparai station.
A11: Hydro DRE | B11: ='District Summary'!H36 | C11: 58 | D11: =B11-C11 | E11: =IF(C11=0,"",D11/C11) | F11: Workbook source: Small-Hydro.
A12: Wind | B12: ='District Summary'!I36 | C12: 9331 | D12: =B12-C12 | E12: =IF(C12=0,"",D12/C12) | F12: Operational wind capacity in the workbook.
A13: Solar | B13: ='District Summary'!J36 | C13: 9006 | D13: =B13-C13 | E13: =IF(C13=0,"",D13/C13) | F13: Excludes rooftop and off-grid solar from workbook Solar.
A14: Solar DRE Rooftop | B14: ='District Summary'!K36 | C14: 1003 | D14: =B14-C14 | E14: =IF(C14=0,"",D14/C14) | F14: Workbook statewide rooftop category.
A15: Solar Off-grid | B15: ='District Summary'!L36 | F15: No separate Solar Off-grid line is given in Table 6.
A16: Comparable total excl. off-grid | B16: =SUM(B5:B14) | C16: 37220 | D16: =B16-C16 | E16: =D16/C16 | F16: The report states 37,220 MW; its displayed rounded components sum to 37,219 MW.
A17: Workbook total incl. off-grid | B17: =SUM(B5:B15) | F17: Includes 75.91 MW Solar Off-grid not separately reported in Table 6.
A19: Source and interpretation
A20: Report: upload/Tamil_Nadu_Resource_Adequacy_Report_2035_36_1.pdf - Table 6, page 5: Fuel-wise Contracted Capacity as on March 2025.
A21: Workbook: operational rows in District Allocation; pipeline, retired, and temporarily closed rows excluded.
A22: A positive difference does not necessarily mean the workbook is wrong: physical installed capacity, contracted shares, and reference dates differ.

Sheet Prayas TN Records
A1: Raw location | B1: Standardized district | C1: Name of plant | D1: Technology | E1: Subtype | F1: Installed capacity (MW) | G1: Commissioning date | H1: Financial year | I1: Use in validation? | J1: Data-quality note | K1: Source CSV row
A2: Karur | B2: Karur | C2: M/s. Kovai Medical Centre& Hospitals Ltd | D2: Solar | F2: 4 | G2: 42382 | H2: 13/01/2016 | I2: Yes | K2: 539
A3: Virudhunagar | B3: Virudhunagar | C3: M/s. MM Forgings Ltd | D3: Solar | F3: 1.8 | G3: 41546 | H3: 29/09/2013 | I3: Yes | K3: 542
A4: Virudhunagar | B4: Virudhunagar | C4: M/s. AK Ahamed & Co Narthampatti | D4: Solar | F4: 1 | G4: 42309 | H4: 01/11/2015 | I4: Yes | K4: 543
A5: Bharuch | B5: Bharuch | C5: Green Infra | D5: Solar | F5: 250 | G5: 43380 | H5: 07/10/2018 | I5: No | J5: Excluded: district is outside Tamil Nadu; source state tag appears incorrect. | K5: 921
A6: Cuddalore | B6: Cuddalore | C6: M/s. M.R.K. Co.Op Sugar Mills , Senthiathpoe | D6: Bagasse | F6: 7.5 | G6: 33770 | H6: 15/06/1992 | I6: Yes | K6: 992
A7: Tiruvannamalai | B7: Tiruvannamalai | C7: M/s. Cheyyar Co.Op Sugar Mills | D7: Bagasse | F7: 7.5 | G7: 34046 | H7: 18/03/1993 | I7: Yes | K7: 993
A8: Cuddalore | B8: Cuddalore | C8: M/s. Terra Energy Ltd | D8: Bagasse | F8: 18.68 | G8: 35016 | H8: 13/11/1995 | I8: Yes | K8: 994
A9: Theni | B9: Theni | C9: M/s. Rajashree Sugars & Chemicals Ltd | D9: Bagasse | F9: 12 | G9: 35153 | H9: 29/03/1996 | I9: Yes | K9: 995
A10: Tiruchirapalli | B10: Tiruchirappalli | C10: M/s. Kothari Sugars & Chemicals Ltd | D10: Bagasse | F10: 12 | G10: 35423 | H10: 24/12/1996 | I10: Yes | J10: District spelling standardized from Tiruchirapalli. | K10: 996
A11: Tiruvannamalai | B11: Tiruvannamalai | C11: M/s. Dharani Sugars & Chemicals Ltd | D11: Bagasse | F11: 15 | G11: 35332 | H11: 24/09/1996 | I11: Yes | K11: 997
A12: Cuddalore | B12: Cuddalore | C12: M/s. EID Parry (India) Ltd | D12: Bagasse | F12: 24.5 | G12: 35567 | H12: 17/05/1997 | I12: Yes | K12: 998
A13: Thanjavur | B13: Thanjavur | C13: M/s. Terra Energy Ltd | D13: Bagasse | F13: 28.42 | G13: 35566 | H13: 16/05/1997 | I13: Yes | K13: 999
A14: Dharmapuri | B14: Dharmapuri | C14: M/s. Subramania Siva Co-Op Sugar Mills,Gopalapuram | D14: Bagasse | F14: 5 | G14: 35962 | H14: 16/06/1998 | I14: Yes | K14: 1000
A15: Cuddalore | B15: Cuddalore | C15: M/s. Ambika Sugars (M/s SREL)Pennadam | D15: Bagasse | F15: 40 | G15: 37701 | H15: 21/03/2003 | I15: Yes | K15: 1001
A16: Erode | B16: Erode | C16: M/s. Bannari Amman Sugars Ltd | D16: Bagasse | F16: 20 | G16: 37404 | H16: 28/05/2002 | I16: Yes | K16: 1002
A17: Thanjavur | B17: Thanjavur | C17: M/s. Auro Energy Ltd ,Kottur | D17: Bagasse | F17: 16 | G17: 37613 | H17: 23/12/2002 | I17: Yes | K17: 1003
A18: Erode | B18: Erode | C18: M/s. Shakti Sugars Ltd ,Sakit Nagar | D18: Bagasse | F18: 32 | G18: 37935 | H18: 10/11/2003 | I18: Yes | K18: 1004
A19: Pudukkottai | B19: Pudukkottai | C19: M/s. EID Parry (India) Ltd,Aranthangi,Pudukottai | D19: Bagasse | F19: 18 | G19: 38806 | H19: 30/03/2006 | I19: Yes | K19: 1005
A20: Villupuram | B20: Viluppuram | C20: M/s. Rajashree Sugars & Chemicals Ltd,Mundiambakkam,Villupuram | D20: Bagasse | F20: 22 | G20: 38504 | H20: 01/06/2005 | I20: Yes | J20: District spelling standardized from Villupuram. | K20: 1006
A21: Perambalur | B21: Perambalur | C21: M/s. Kothari Sugars & Chemicals Ltd.Sathamangalam, | D21: Bagasse | F21: 22 | G21: 39148 | H21: 07/03/2007 | I21: Yes | K21: 1007
A22: Erode | B22: Erode | C22: M/s. Sakti Sugars Ltd | D22: Bagasse | F22: 24 | G22: 39341 | H22: 16/09/2007 | I22: Yes | K22: 1008
A23: Kanchipuram | B23: Kanchipuram | C23: M/s.S.V Sugars Mills Ltd | D23: Bagasse | F23: 45 | G23: 39288 | H23: 25/07/2007 | I23: Yes | K23: 1009
A24: Karur | B24: Karur | C24: M/s. EID Parry (India) Ltd | D24: Bagasse | F24: 22 | G24: 39318 | H24: 24/08/2007 | I24: Yes | K24: 1010
A25: Sivaganga | B25: Sivaganga | C25: M/s. Sakti Sugars Ltd | D25: Bagasse | F25: 35 | G25: 39479 | H25: 01/02/2008 | I25: Yes | K25: 1011
A26: Villupuram | B26: Viluppuram | C26: M/s. Rajashree Sugars & Chemicals Ltd Semmedu ,Villupuram | D26: Bagasse | F26: 23 | G26: 39730 | H26: 09/10/2008 | I26: Yes | J26: District spelling standardized from Villupuram. | K26: 1012
A27: Perambalur | B27: Perambalur | C27: M/s. Dhanalakahmi Srinivasan Sugars Pvt Ltd | D27: Bagasse | F27: 25 | G27: 40234 | H27: 25/02/2010 | I27: Yes | K27: 1013
A28: Tiruchirapalli | B28: Tiruchirappalli | C28: M/s. EID Parry (India) Ltd, Pettavaithalai | D28: Bagasse | F28: 20 | G28: 40191 | H28: 13/01/2010 | I28: Yes | J28: District spelling standardized from Tiruchirapalli. | K28: 1014
A29: Tiruvannamalai | B29: Tiruvannamalai | C29: M/s. Bannari Amman Sugars and Chemicals Ltd, Kolundampattu Village | D29: Bagasse | F29: 28.8 | G29: 40205 | H29: 27/01/2010 | I29: Yes | K29: 1015
A30: Villupuram | B30: Viluppuram | C30: M/s. Dharani Sugars & Chemicals, Kalayanallur Village | D30: Bagasse | F30: 22 | G30: 40098 | H30: 12/10/2009 | I30: Yes | J30: District spelling standardized from Villupuram. | K30: 1016
A31: Tirunelveli | B31: Tirunelveli | C31: M/s. Empee Sugars & Chemicals Ltd | D31: Bagasse | F31: 50 | G31: 40296 | H31: 28/04/2010 | I31: Yes | K31: 1017
A32: Villupuram | B32: Viluppuram | C32: M/s. Mardras Sugars & Chemicals | D32: Bagasse | F32: 25 | G32: 40683 | H32: 20/05/2011 | I32: Yes | J32: District spelling standardized from Villupuram. | K32: 1018
A33: Erode | B33: Erode | C33: M/s.Ponni Sugars Limited | D33: Bagasse | F33: 19 | G33: 41169 | H33: 17/09/2012 | I33: Yes | K33: 1019
A34: Erode | B34: Erode | C34: M/s.Chengalrayan Co-Operative Sugar Mills | D34: Bagasse | F34: 18 | G34: 42417 | H34: 17/02/2016 | I34: Yes | K34: 1020
A35: Erode | B35: Erode | C35: M/s. Cheyyar Co-Operative Sugar Mills | D35: Bagasse | F35: 15 | G35: 42766 | H35: 31/01/2017 | I35: Yes | K35: 1021
A36: Vellore | B36: Vellore | C36: M/s. Vellore Co-Operative Sugar Mills | D36: Bagasse | F36: 15 | G36: 42754 | H36: 19/01/2017 | I36: Yes | K36: 1022
A37: Cuddalore | B37: Cuddalore | C37: M/s.Perambalur Sugar Mills | D37: Bagasse | F37: 18 | G37: 43514 | H37: 18/02/2019 | I37: Yes | K37: 1023
A38: Thanjavur | B38: Thanjavur | C38: M/s.Arignar Anna Sugars Mills, | D38: Bagasse | F38: 15 | G38: 43347 | H38: 04/09/2018 | I38: Yes | K38: 1024
A39: Sivaganga | B39: Sivaganga | C39: M/s.Sapphire Industrial Infrastrucres Pvt Ltd | D39: Solar | F39: 5 | G39: 40532 | H39: 20/12/2010 | I39: Yes | K39: 2478
A40: karur | B40: Karur | C40: M/s. Shankar Abodes | D40: Solar | F40: 2 | G40: 40390 | H40: 31/07/2010 | I40: Yes | J40: District spelling standardized from karur. | K40: 2479
A41: Madurai | B41: Madurai | C41: M/s. Great Shine Holdings Pvt Ltd | D41: Solar | F41: 1 | G41: 40936 | H41: 28/01/2012 | I41: Yes | K41: 2480
A42: Nagapattinam | B42: Nagapattinam | C42: M/s. B& G Solar Pvt Ltd | D42: Solar | F42: 1 | G42: 40704 | H42: 10/06/2011 | I42: Yes | K42: 2481
A43: Sivaganga | B43: Sivaganga | C43: M/s. RL Clean Power Pvt Ltd | D43: Solar | F43: 1 | G43: 40749 | H43: 25/07/2011 | I43: Yes | K43: 2482
A44: Sivaganga | B44: Sivaganga | C44: M/s. CCCL Infrastructure | D44: Solar | F44: 5 | G44: 40997 | H44: 29/03/2012 | I44: Yes | K44: 2483
A45: Thoothukudi | B45: Thoothukudi | C45: M/s. Amson Power Pvt Ltd | D45: Solar | F45: 1 | G45: 40982 | H45: 14/03/2012 | I45: Yes | K45: 2484
A46: Thoothukudi | B46: Thoothukudi | C46: M/s. Harrisons Power Pvt Ltd | D46: Solar | F46: 1 | G46: 40982 | H46: 14/03/2012 | I46: Yes | K46: 2485
A47: Coimbtore | B47: Coimbatore | C47: M/s. Numeric Power System | D47: Solar | F47: 1 | G47: 41038 | H47: 09/05/2012 | I47: Yes | J47: District spelling standardized from Coimbtore. | K47: 2486
A48: Sivaganga | B48: Sivaganga | C48: M/s. Noel Media & Advertising Pvt Ltd | D48: Solar | F48: 1 | G48: 41085 | H48: 25/06/2012 | I48: Yes | K48: 2487
A49: Tirupur | B49: Tiruppur | C49: M/s .Alpine Knits India Pvt Ltd | D49: Solar | F49: 1 | G49: 41363 | H49: 30/03/2013 | I49: Yes | J49: District spelling standardized from Tirupur. | K49: 2488
A50: Tirupur | B50: Tiruppur | C50: M/s .Gaajananda Jewellery India Pvt Ltd | D50: Solar | F50: 1 | G50: 41363 | H50: 30/03/2013 | I50: Yes | J50: District spelling standardized from Tirupur. | K50: 2489
A51: Tirupur | B51: Tiruppur | C51: M/s. Sathy Silks Pvt Ltd | D51: Solar | F51: 1 | G51: 41363 | H51: 30/03/2013 | I51: Yes | J51: District spelling standardized from Tirupur. | K51: 2490
A52: Coimbtore | B52: Coimbatore | C52: M/s.Sri Ranganathar Industries Pvt Ltd | D52: Solar | F52: 1 | G52: 41725 | H52: 27/03/2014 | I52: Yes | J52: District spelling standardized from Coimbtore. | K52: 2491
A53: Dindigul | B53: Dindigul | C53: M/s. Ultra Cosmic Solar Energy Pvt Ltd | D53: Solar | F53: 1 | G53: 41623 | H53: 15/12/2013 | I53: Yes | K53: 2492
A54: Erode | B54: Erode | C54: M/s .Freelok Fashion | D54: Solar | F54: 1 | G54: 41467 | H54: 12/07/2013 | I54: Yes | K54: 2493
A55: Erode | B55: Erode | C55: M/s. Armstrong Spinning Mills Pvt Ltd | D55: Solar | F55: 1 | G55: 41712 | H55: 14/03/2014 | I55: Yes | K55: 2494
A56: Erode | B56: Erode | C56: M/s. Cheenu Enterprises | D56: Solar | F56: 2 | G56: 41668 | H56: 29/01/2014 | I56: Yes | K56: 2495
A57: Karur | B57: Karur | C57: M/s. Asian Fabricx Pvt Ltd | D57: Solar | F57: 1.5 | G57: 41704 | H57: 06/03/2014 | I57: Yes | K57: 2496
A58: Karur | B58: Karur | C58: M/s. Amex Alloy | D58: Solar | F58: 2 | G58: 41726 | H58: 28/03/2014 | I58: Yes | K58: 2497
A59: Karur | B59: Karur | C59: M/s. Adhavan Solar Projects | D59: Solar | F59: 3 | G59: 41717 | H59: 19/03/2014 | I59: Yes | K59: 2498
A60: Karur | B60: Karur | C60: M/s. Asian Solar Pvt Ltd | D60: Solar | F60: 3 | G60: 41717 | H60: 19/03/2014 | I60: Yes | K60: 2499
A61: Karur | B61: Karur | C61: M/s. Swelect Energy System Pvt Ltd | D61: Solar | F61: 10 | G61: 41726 | H61: 28/03/2014 | I61: Yes | K61: 2500
A62: Tiruchirapalli | B62: Tiruchirappalli | C62: M/s. Sri Vinayaga Green Power Generation | D62: Solar | F62: 5 | G62: 41691 | H62: 21/02/2014 | I62: Yes | J62: District spelling standardized from Tiruchirapalli. | K62: 2501
A63: Tiruchirapalli | B63: Tiruchirappalli | C63: M/s. Apex Clothing Company India Ltd | D63: Solar | F63: 15 | G63: 41699 | H63: 01/03/2014 | I63: Yes | J63: District spelling standardized from Tiruchirapalli. | K63: 2502
A64: Tirunelveli | B64: Tirunelveli | C64: M/s. Orange Sorting Machines Pvt Ltd | D64: Solar | F64: 0.8 | G64: 41727 | H64: 29/03/2014 | I64: Yes | K64: 2503
A65: Tirunelveli | B65: Tirunelveli | C65: M/s. Gomathy International | D65: Solar | F65: 1 | G65: 41727 | H65: 29/03/2014 | I65: Yes | K65: 2504
A66: Tirunelveli | B66: Tirunelveli | C66: M/s. Flow Link System Pvt Ltd | D66: Solar | F66: 1.26 | G66: 41639 | H66: 31/12/2013 | I66: Yes | K66: 2505
A67: Tirupur | B67: Tiruppur | C67: M/s. Sulochana Cotton Mills Pvt Ltd | D67: Solar | F67: 2 | G67: 41724 | H67: 26/03/2014 | I67: Yes | J67: District spelling standardized from Tirupur. | K67: 2506
A68: Tirupur | B68: Tiruppur | C68: M/s. SRG Apparels Private Ltd | D68: Solar | F68: 1 | G68: 41676 | H68: 06/02/2014 | I68: Yes | J68: District spelling standardized from Tirupur. | K68: 2507
A69: Tirupur | B69: Tiruppur | C69: M/s. Sathy Silks Pvt Ltd | D69: Solar | F69: 1 | G69: 41726 | H69: 28/03/2014 | I69: Yes | J69: District spelling standardized from Tirupur. | K69: 2508
A70: Tirupur | B70: Tiruppur | C70: M/s.Nachas Wind Energy Pvt Ltd | D70: Solar | F70: 1 | G70: 41726 | H70: 28/03/2014 | I70: Yes | J70: District spelling standardized from Tirupur. | K70: 2509
A71: Tirupur | B71: Tiruppur | C71: M/s.SCM international Implex Pvt Ltd | D71: Solar | F71: 1 | G71: 41726 | H71: 28/03/2014 | I71: Yes | J71: District spelling standardized from Tirupur. | K71: 2510
A72: Tirupur | B72: Tiruppur | C72: M/s.Space Textiles Pvt Ltd | D72: Solar | F72: 1 | G72: 41726 | H72: 28/03/2014 | I72: Yes | J72: District spelling standardized from Tirupur. | K72: 2511
A73: Tirupur | B73: Tiruppur | C73: M/s.The KTM Jewellery Ltd | D73: Solar | F73: 1 | G73: 41726 | H73: 28/03/2014 | I73: Yes | J73: District spelling standardized from Tirupur. | K73: 2512
A74: Tirupur | B74: Tiruppur | C74: M/s. Fab Colours | D74: Solar | F74: 1 | G74: 41728 | H74: 30/03/2014 | I74: Yes | J74: District spelling standardized from Tirupur. | K74: 2513
A75: Tirupur | B75: Tiruppur | C75: M/s. Ragam Exports | D75: Solar | F75: 1 | G75: 41728 | H75: 30/03/2014 | I75: Yes | J75: District spelling standardized from Tirupur. | K75: 2514
A76: Tirupur | B76: Tiruppur | C76: M/s. Sivajyothy Spinning Mills Pvt Ltd | D76: Solar | F76: 1 | G76: 41728 | H76: 30/03/2014 | I76: Yes | J76: District spelling standardized from Tirupur. | K76: 2515
A77: Tirupur | B77: Tiruppur | C77: M/s. Srilakshmi Processors | D77: Solar | F77: 1 | G77: 41728 | H77: 30/03/2014 | I77: Yes | J77: District spelling standardized from Tirupur. | K77: 2516
A78: Tirupur | B78: Tiruppur | C78: M/s. Murugan Tex | D78: Solar | F78: 2 | G78: 41729 | H78: 31/03/2014 | I78: Yes | J78: District spelling standardized from Tirupur. | K78: 2517
A79: Vellore | B79: Vellore | C79: M/s. BHEL Limited | D79: Solar | F79: 5 | G79: 41704 | H79: 06/03/2014 | I79: Yes | K79: 2518
A80: Virudhunagar | B80: Virudhunagar | C80: M/s. IM GearsPvt Ltd | D80: Solar | F80: 0.9 | G80: 41727 | H80: 29/03/2014 | I80: Yes | K80: 2519
A81: Virudhunagar | B81: Virudhunagar | C81: M/s. Super Auto Forge Pvt Ltd | D81: Solar | F81: 1 | G81: 41546 | H81: 29/09/2013 | I81: Yes | K81: 2520
A82: Virudhunagar | B82: Virudhunagar | C82: M/s .JVS Export | D82: Solar | F82: 5 | G82: 41546 | H82: 29/09/2013 | I82: Yes | K82: 2521
A83: Dindigul | B83: Dindigul | C83: M/s. Naga Ltd | D83: Solar | F83: 0.6 | G83: 41825 | H83: 05/07/2014 | I83: Yes | K83: 2522
A84: Karur | B84: Karur | C84: M/s. Swelect Energy System Pvt Ltd | D84: Solar | F84: 1 | G84: 41740 | H84: 11/04/2014 | I84: Yes | K84: 2523
A85: Karur | B85: Karur | C85: M/s. Swelect Energy System Pvt Ltd | D85: Solar | F85: 1 | G85: 41740 | H85: 11/04/2014 | I85: Yes | K85: 2524
A86: Karur | B86: Karur | C86: M/s. Yajur Energy Solution Pvt Ltd | D86: Solar | F86: 1 | G86: 41740 | H86: 11/04/2014 | I86: Yes | K86: 2525
A87: Karur | B87: Karur | C87: M/s. Asian Fabricx Pvt Ltd | D87: Solar | F87: 1 | G87: 41835 | H87: 15/07/2014 | I87: Yes | K87: 2526
A88: Karur | B88: Karur | C88: M/s. Karur Sree Rama Trading Pvt Ltd | D88: Solar | F88: 1 | G88: 41835 | H88: 15/07/2014 | I88: Yes | K88: 2527
A89: Karur | B89: Karur | C89: M/s. Asian Fabricx Pvt Ltd | D89: Solar | F89: 2 | G89: 41835 | H89: 15/07/2014 | I89: Yes | K89: 2528
A90: Ramanathapuram | B90: Ramanathapuram | C90: M/s. G.R. Thanga Maaligai Jewellers Pvt Ltd | D90: Solar | F90: 5 | G90: 42093 | H90: 30/03/2015 | I90: Yes | K90: 2529
A91: Sivaganga | B91: Sivaganga | C91: M/s.Mayor Sri Ramanathan Chettiar Centre | D91: Solar | F91: 0.55 | G91: 42079 | H91: 16/03/2015 | I91: Yes | K91: 2530
A92: Tiruchirapalli | B92: Tiruchirappalli | C92: M/s. Apex Clothing Company India Ltd | D92: Solar | F92: 5 | G92: 41740 | H92: 11/04/2014 | I92: Yes | J92: District spelling standardized from Tiruchirapalli. | K92: 2531
A93: Tiruchirapalli | B93: Tiruchirappalli | C93: M/s. GRT (Firm) | D93: Solar | F93: 5 | G93: 42094 | H93: 31/03/2015 | I93: Yes | J93: District spelling standardized from Tiruchirapalli. | K93: 2532
A94: Tiruchirapalli | B94: Tiruchirappalli | C94: M/s. GRT And Sons | D94: Solar | F94: 5 | G94: 42094 | H94: 31/03/2015 | I94: Yes | J94: District spelling standardized from Tiruchirapalli. | K94: 2533
A95: Tirunelveli | B95: Tirunelveli | C95: M/s. Sei Arjan Solar Power Pvt Ltd | D95: Solar | F95: 6.3 | G95: 42004 | H95: 31/12/2014 | I95: Yes | K95: 2534
A96: Tirupur | B96: Tiruppur | C96: M/s.Sulochana Cotton Spinning Mills Pvt Ltd | D96: Solar | F96: 0.5 | G96: 42091 | H96: 28/03/2015 | I96: Yes | J96: District spelling standardized from Tirupur. | K96: 2535
A97: Tirupur | B97: Tiruppur | C97: M/s. Sakthi Murugan Agro Food Ltd | D97: Solar | F97: 1 | G97: 42016 | H97: 12/01/2015 | I97: Yes | J97: District spelling standardized from Tirupur. | K97: 2536
A98: Tirupur | B98: Tiruppur | C98: M/s. Sakthi Murugan Roller Flour Mills Ltd | D98: Solar | F98: 1 | G98: 42016 | H98: 12/01/2015 | I98: Yes | J98: District spelling standardized from Tirupur. | K98: 2537
A99: Tuticorin | B99: Thoothukudi | C99: M/s. Nazareth Green Energy Enterprise | D99: Solar | F99: 1 | G99: 41983 | H99: 10/12/2014 | I99: Yes | J99: District spelling standardized from Tuticorin. | K99: 2538
A100: Virudhunagar | B100: Virudhunagar | C100: M/s. Autotech Industries Pvt Ltd | D100: Solar | F100: 0.9 | G100: 42094 | H100: 31/03/2015 | I100: Yes | K100: 2539
...

Sheet Prayas Validation
A1: Prayas Historical Validation of ICED District Allocation
A2: Prayas file contains 9,980 Tamil Nadu-tagged records through 2019-10-10. Distribution shares are compared because ICED is newer. Bharuch and Kachchh records (450 MW) are excluded as state-tag errors.
A3: District | B3: ICED Wind MW | C3: Prayas Wind MW | D3: Prayas–ICED wind share | E3: ICED Solar MW | F3: Prayas Solar MW | G3: Prayas–ICED solar share | H3: ICED Biomass MW | I3: Prayas Bagasse MW | J3: Prayas–ICED bio share | K3: Assessment
A4: Ariyalur | B4: ='District Summary'!I4 | C4: =SUMIFS('Prayas TN Records'!$F$2:$F$9981,'Prayas TN Records'!$B$2:$B$9981,$A4,'Prayas TN Records'!$D$2:$D$9981,"Wind",'Prayas TN Records'!$I$2:$I$9981,"Yes") | D4: =IF(SUM($C$4:$C$35)=0,0,C4/SUM($C$4:$C$35))-IF(SUM($B$4:$B$35)=0,0,B4/SUM($B$4:$B$35)) | E4: ='District Summary'!J4 | F4: =SUMIFS('Prayas TN Records'!$F$2:$F$9981,'Prayas TN Records'!$B$2:$B$9981,$A4,'Prayas TN Records'!$D$2:$D$9981,"Solar",'Prayas TN Records'!$I$2:$I$9981,"Yes") | G4: =IF(SUM($F$4:$F$35)=0,0,F4/SUM($F$4:$F$35))-IF(SUM($E$4:$E$35)=0,0,E4/SUM($E$4:$E$35)) | H4: ='District Summary'!E4 | I4: =SUMIFS('Prayas TN Records'!$F$2:$F$9981,'Prayas TN Records'!$B$2:$B$9981,$A4,'Prayas TN Records'!$D$2:$D$9981,"Bagasse",'Prayas TN Records'!$I$2:$I$9981,"Yes") | J4: =IF(SUM($I$4:$I$35)=0,0,I4/SUM($I$4:$I$35))-IF(SUM($H$4:$H$35)=0,0,H4/SUM($H$4:$H$35)) | K4: =IF(MAX(ABS(D4),ABS(G4),ABS(J4))>=0.05,"Large distribution difference",IF(MAX(ABS(D4),ABS(G4),ABS(J4))>=0.02,"Moderate difference","Broadly aligned"))
A5: Chennai | B5: ='District Summary'!I5 | C5: =SUMIFS('Prayas TN Records'!$F$2:$F$9981,'Prayas TN Records'!$B$2:$B$9981,$A5,'Prayas TN Records'!$D$2:$D$9981,"Wind",'Prayas TN Records'!$I$2:$I$9981,"Yes") | D5: =IF(SUM($C$4:$C$35)=0,0,C5/SUM($C$4:$C$35))-IF(SUM($B$4:$B$35)=0,0,B5/SUM($B$4:$B$35)) | E5: ='District Summary'!J5 | F5: =SUMIFS('Prayas TN Records'!$F$2:$F$9981,'Prayas TN Records'!$B$2:$B$9981,$A5,'Prayas TN Records'!$D$2:$D$9981,"Solar",'Prayas TN Records'!$I$2:$I$9981,"Yes") | G5: =IF(SUM($F$4:$F$35)=0,0,F5/SUM($F$4:$F$35))-IF(SUM($E$4:$E$35)=0,0,E5/SUM($E$4:$E$35)) | H5: ='District Summary'!E5 | I5: =SUMIFS('Prayas TN Records'!$F$2:$F$9981,'Prayas TN Records'!$B$2:$B$9981,$A5,'Prayas TN Records'!$D$2:$D$9981,"Bagasse",'Prayas TN Records'!$I$2:$I$9981,"Yes") | J5: =IF(SUM($I$4:$I$35)=0,0,I5/SUM($I$4:$I$35))-IF(SUM($H$4:$H$35)=0,0,H5/SUM($H$4:$H$35)) | K5: =IF(MAX(ABS(D5),ABS(G5),ABS(J5))>=0.05,"Large distribution difference",IF(MAX(ABS(D5),ABS(G5),ABS(J5))>=0.02,"Moderate difference","Broadly aligned"))
A6: Coimbatore | B6: ='District Summary'!I6 | C6: =SUMIFS('Prayas TN Records'!$F$2:$F$9981,'Prayas TN Records'!$B$2:$B$9981,$A6,'Prayas TN Records'!$D$2:$D$9981,"Wind",'Prayas TN Records'!$I$2:$I$9981,"Yes") | D6: =IF(SUM($C$4:$C$35)=0,0,C6/SUM($C$4:$C$35))-IF(SUM($B$4:$B$35)=0,0,B6/SUM($B$4:$B$35)) | E6: ='District Summary'!J6 | F6: =SUMIFS('Prayas TN Records'!$F$2:$F$9981,'Prayas TN Records'!$B$2:$B$9981,$A6,'Prayas TN Records'!$D$2:$D$9981,"Solar",'Prayas TN Records'!$I$2:$I$9981,"Yes") | G6: =IF(SUM($F$4:$F$35)=0,0,F6/SUM($F$4:$F$35))-IF(SUM($E$4:$E$35)=0,0,E6/SUM($E$4:$E$35)) | H6: ='District Summary'!E6 | I6: =SUMIFS('Prayas TN Records'!$F$2:$F$9981,'Prayas TN Records'!$B$2:$B$9981,$A6,'Prayas TN Records'!$D$2:$D$9981,"Bagasse",'Prayas TN Records'!$I$2:$I$9981,"Yes") | J6: =IF(SUM($I$4:$I$35)=0,0,I6/SUM($I$4:$I$35))-IF(SUM($H$4:$H$35)=0,0,H6/SUM($H$4:$H$35)) | K6: =IF(MAX(ABS(D6),ABS(G6),ABS(J6))>=0.05,"Large distribution difference",IF(MAX(ABS(D6),ABS(G6),ABS(J6))>=0.02,"Moderate difference","Broadly aligned"))
A7: Cuddalore | B7: ='District Summary'!I7 | C7: =SUMIFS('Prayas TN Records'!$F$2:$F$9981,'Prayas TN Records'!$B$2:$B$9981,$A7,'Prayas TN Records'!$D$2:$D$9981,"Wind",'Prayas TN Records'!$I$2:$I$9981,"Yes") | D7: =IF(SUM($C$4:$C$35)=0,0,C7/SUM($C$4:$C$35))-IF(SUM($B$4:$B$35)=0,0,B7/SUM($B$4:$B$35)) | E7: ='District Summary'!J7 | F7: =SUMIFS('Prayas TN Records'!$F$2:$F$9981,'Prayas TN Records'!$B$2:$B$9981,$A7,'Prayas TN Records'!$D$2:$D$9981,"Solar",'Prayas TN Records'!$I$2:$I$9981,"Yes") | G7: =IF(SUM($F$4:$F$35)=0,0,F7/SUM($F$4:$F$35))-IF(SUM($E$4:$E$35)=0,0,E7/SUM($E$4:$E$35)) | H7: ='District Summary'!E7 | I7: =SUMIFS('Prayas TN Records'!$F$2:$F$9981,'Prayas TN Records'!$B$2:$B$9981,$A7,'Prayas TN Records'!$D$2:$D$9981,"Bagasse",'Prayas TN Records'!$I$2:$I$9981,"Yes") | J7: =IF(SUM($I$4:$I$35)=0,0,I7/SUM($I$4:$I$35))-IF(SUM($H$4:$H$35)=0,0,H7/SUM($H$4:$H$35)) | K7: =IF(MAX(ABS(D7),ABS(G7),ABS(J7))>=0.05,"Large distribution difference",IF(MAX(ABS(D7),ABS(G7),ABS(J7))>=0.02,"Moderate difference","Broadly aligned"))
A8: Dharmapuri | B8: ='District Summary'!I8 | C8: =SUMIFS('Prayas TN Records'!$F$2:$F$9981,'Prayas TN Records'!$B$2:$B$9981,$A8,'Prayas TN Records'!$D$2:$D$9981,"Wind",'Prayas TN Records'!$I$2:$I$9981,"Yes") | D8: =IF(SUM($C$4:$C$35)=0,0,C8/SUM($C$4:$C$35))-IF(SUM($B$4:$B$35)=0,0,B8/SUM($B$4:$B$35)) | E8: ='District Summary'!J8 | F8: =SUMIFS('Prayas TN Records'!$F$2:$F$9981,'Prayas TN Records'!$B$2:$B$9981,$A8,'Prayas TN Records'!$D$2:$D$9981,"Solar",'Prayas TN Records'!$I$2:$I$9981,"Yes") | G8: =IF(SUM($F$4:$F$35)=0,0,F8/SUM($F$4:$F$35))-IF(SUM($E$4:$E$35)=0,0,E8/SUM($E$4:$E$35)) | H8: ='District Summary'!E8 | I8: =SUMIFS('Prayas TN Records'!$F$2:$F$9981,'Prayas TN Records'!$B$2:$B$9981,$A8,'Prayas TN Records'!$D$2:$D$9981,"Bagasse",'Prayas TN Records'!$I$2:$I$9981,"Yes") | J8: =IF(SUM($I$4:$I$35)=0,0,I8/SUM($I$4:$I$35))-IF(SUM($H$4:$H$35)=0,0,H8/SUM($H$4:$H$35)) | K8: =IF(MAX(ABS(D8),ABS(G8),ABS(J8))>=0.05,"Large distribution difference",IF(MAX(ABS(D8),ABS(G8),ABS(J8))>=0.02,"Moderate difference","Broadly aligned"))
A9: Dindigul | B9: ='District Summary'!I9 | C9: =SUMIFS('Prayas TN Records'!$F$2:$F$9981,'Prayas TN Records'!$B$2:$B$9981,$A9,'Prayas TN Records'!$D$2:$D$9981,"Wind",'Prayas TN Records'!$I$2:$I$9981,"Yes") | D9: =IF(SUM($C$4:$C$35)=0,0,C9/SUM($C$4:$C$35))-IF(SUM($B$4:$B$35)=0,0,B9/SUM($B$4:$B$35)) | E9: ='District Summary'!J9 | F9: =SUMIFS('Prayas TN Records'!$F$2:$F$9981,'Prayas TN Records'!$B$2:$B$9981,$A9,'Prayas TN Records'!$D$2:$D$9981,"Solar",'Prayas TN Records'!$I$2:$I$9981,"Yes") | G9: =IF(SUM($F$4:$F$35)=0,0,F9/SUM($F$4:$F$35))-IF(SUM($E$4:$E$35)=0,0,E9/SUM($E$4:$E$35)) | H9: ='District Summary'!E9 | I9: =SUMIFS('Prayas TN Records'!$F$2:$F$9981,'Prayas TN Records'!$B$2:$B$9981,$A9,'Prayas TN Records'!$D$2:$D$9981,"Bagasse",'Prayas TN Records'!$I$2:$I$9981,"Yes") | J9: =IF(SUM($I$4:$I$35)=0,0,I9/SUM($I$4:$I$35))-IF(SUM($H$4:$H$35)=0,0,H9/SUM($H$4:$H$35)) | K9: =IF(MAX(ABS(D9),ABS(G9),ABS(J9))>=0.05,"Large distribution difference",IF(MAX(ABS(D9),ABS(G9),ABS(J9))>=0.02,"Moderate difference","Broadly aligned"))
A10: Erode | B10: ='District Summary'!I10 | C10: =SUMIFS('Prayas TN Records'!$F$2:$F$9981,'Prayas TN Records'!$B$2:$B$9981,$A10,'Prayas TN Records'!$D$2:$D$9981,"Wind",'Prayas TN Records'!$I$2:$I$9981,"Yes") | D10: =IF(SUM($C$4:$C$35)=0,0,C10/SUM($C$4:$C$35))-IF(SUM($B$4:$B$35)=0,0,B10/SUM($B$4:$B$35)) | E10: ='District Summary'!J10 | F10: =SUMIFS('Prayas TN Records'!$F$2:$F$9981,'Prayas TN Records'!$B$2:$B$9981,$A10,'Prayas TN Records'!$D$2:$D$9981,"Solar",'Prayas TN Records'!$I$2:$I$9981,"Yes") | G10: =IF(SUM($F$4:$F$35)=0,0,F10/SUM($F$4:$F$35))-IF(SUM($E$4:$E$35)=0,0,E10/SUM($E$4:$E$35)) | H10: ='District Summary'!E10 | I10: =SUMIFS('Prayas TN Records'!$F$2:$F$9981,'Prayas TN Records'!$B$2:$B$9981,$A10,'Prayas TN Records'!$D$2:$D$9981,"Bagasse",'Prayas TN Records'!$I$2:$I$9981,"Yes") | J10: =IF(SUM($I$4:$I$35)=0,0,I10/SUM($I$4:$I$35))-IF(SUM($H$4:$H$35)=0,0,H10/SUM($H$4:$H$35)) | K10: =IF(MAX(ABS(D10),ABS(G10),ABS(J10))>=0.05,"Large distribution difference",IF(MAX(ABS(D10),ABS(G10),ABS(J10))>=0.02,"Moderate difference","Broadly aligned"))
A11: Kanchipuram | B11: ='District Summary'!I11 | C11: =SUMIFS('Prayas TN Records'!$F$2:$F$9981,'Prayas TN Records'!$B$2:$B$9981,$A11,'Prayas TN Records'!$D$2:$D$9981,"Wind",'Prayas TN Records'!$I$2:$I$9981,"Yes") | D11: =IF(SUM($C$4:$C$35)=0,0,C11/SUM($C$4:$C$35))-IF(SUM($B$4:$B$35)=0,0,B11/SUM($B$4:$B$35)) | E11: ='District Summary'!J11 | F11: =SUMIFS('Prayas TN Records'!$F$2:$F$9981,'Prayas TN Records'!$B$2:$B$9981,$A11,'Prayas TN Records'!$D$2:$D$9981,"Solar",'Prayas TN Records'!$I$2:$I$9981,"Yes") | G11: =IF(SUM($F$4:$F$35)=0,0,F11/SUM($F$4:$F$35))-IF(SUM($E$4:$E$35)=0,0,E11/SUM($E$4:$E$35)) | H11: ='District Summary'!E11 | I11: =SUMIFS('Prayas TN Records'!$F$2:$F$9981,'Prayas TN Records'!$B$2:$B$9981,$A11,'Prayas TN Records'!$D$2:$D$9981,"Bagasse",'Prayas TN Records'!$I$2:$I$9981,"Yes") | J11: =IF(SUM($I$4:$I$35)=0,0,I11/SUM($I$4:$I$35))-IF(SUM($H$4:$H$35)=0,0,H11/SUM($H$4:$H$35)) | K11: =IF(MAX(ABS(D11),ABS(G11),ABS(J11))>=0.05,"Large distribution difference",IF(MAX(ABS(D11),ABS(G11),ABS(J11))>=0.02,"Moderate difference","Broadly aligned"))
A12: Kanyakumari | B12: ='District Summary'!I12 | C12: =SUMIFS('Prayas TN Records'!$F$2:$F$9981,'Prayas TN Records'!$B$2:$B$9981,$A12,'Prayas TN Records'!$D$2:$D$9981,"Wind",'Prayas TN Records'!$I$2:$I$9981,"Yes") | D12: =IF(SUM($C$4:$C$35)=0,0,C12/SUM($C$4:$C$35))-IF(SUM($B$4:$B$35)=0,0,B12/SUM($B$4:$B$35)) | E12: ='District Summary'!J12 | F12: =SUMIFS('Prayas TN Records'!$F$2:$F$9981,'Prayas TN Records'!$B$2:$B$9981,$A12,'Prayas TN Records'!$D$2:$D$9981,"Solar",'Prayas TN Records'!$I$2:$I$9981,"Yes") | G12: =IF(SUM($F$4:$F$35)=0,0,F12/SUM($F$4:$F$35))-IF(SUM($E$4:$E$35)=0,0,E12/SUM($E$4:$E$35)) | H12: ='District Summary'!E12 | I12: =SUMIFS('Prayas TN Records'!$F$2:$F$9981,'Prayas TN Records'!$B$2:$B$9981,$A12,'Prayas TN Records'!$D$2:$D$9981,"Bagasse",'Prayas TN Records'!$I$2:$I$9981,"Yes") | J12: =IF(SUM($I$4:$I$35)=0,0,I12/SUM($I$4:$I$35))-IF(SUM($H$4:$H$35)=0,0,H12/SUM($H$4:$H$35)) | K12: =IF(MAX(ABS(D12),ABS(G12),ABS(J12))>=0.05,"Large distribution difference",IF(MAX(ABS(D12),ABS(G12),ABS(J12))>=0.02,"Moderate difference","Broadly aligned"))
A13: Karur | B13: ='District Summary'!I13 | C13: =SUMIFS('Prayas TN Records'!$F$2:$F$9981,'Prayas TN Records'!$B$2:$B$9981,$A13,'Prayas TN Records'!$D$2:$D$9981,"Wind",'Prayas TN Records'!$I$2:$I$9981,"Yes") | D13: =IF(SUM($C$4:$C$35)=0,0,C13/SUM($C$4:$C$35))-IF(SUM($B$4:$B$35)=0,0,B13/SUM($B$4:$B$35)) | E13: ='District Summary'!J13 | F13: =SUMIFS('Prayas TN Records'!$F$2:$F$9981,'Prayas TN Records'!$B$2:$B$9981,$A13,'Prayas TN Records'!$D$2:$D$9981,"Solar",'Prayas TN Records'!$I$2:$I$9981,"Yes") | G13: =IF(SUM($F$4:$F$35)=0,0,F13/SUM($F$4:$F$35))-IF(SUM($E$4:$E$35)=0,0,E13/SUM($E$4:$E$35)) | H13: ='District Summary'!E13 | I13: =SUMIFS('Prayas TN Records'!$F$2:$F$9981,'Prayas TN Records'!$B$2:$B$9981,$A13,'Prayas TN Records'!$D$2:$D$9981,"Bagasse",'Prayas TN Records'!$I$2:$I$9981,"Yes") | J13: =IF(SUM($I$4:$I$35)=0,0,I13/SUM($I$4:$I$35))-IF(SUM($H$4:$H$35)=0,0,H13/SUM($H$4:$H$35)) | K13: =IF(MAX(ABS(D13),ABS(G13),ABS(J13))>=0.05,"Large distribution difference",IF(MAX(ABS(D13),ABS(G13),ABS(J13))>=0.02,"Moderate difference","Broadly aligned"))
A14: Krishnagiri | B14: ='District Summary'!I14 | C14: =SUMIFS('Prayas TN Records'!$F$2:$F$9981,'Prayas TN Records'!$B$2:$B$9981,$A14,'Prayas TN Records'!$D$2:$D$9981,"Wind",'Prayas TN Records'!$I$2:$I$9981,"Yes") | D14: =IF(SUM($C$4:$C$35)=0,0,C14/SUM($C$4:$C$35))-IF(SUM($B$4:$B$35)=0,0,B14/SUM($B$4:$B$35)) | E14: ='District Summary'!J14 | F14: =SUMIFS('Prayas TN Records'!$F$2:$F$9981,'Prayas TN Records'!$B$2:$B$9981,$A14,'Prayas TN Records'!$D$2:$D$9981,"Solar",'Prayas TN Records'!$I$2:$I$9981,"Yes") | G14: =IF(SUM($F$4:$F$35)=0,0,F14/SUM($F$4:$F$35))-IF(SUM($E$4:$E$35)=0,0,E14/SUM($E$4:$E$35)) | H14: ='District Summary'!E14 | I14: =SUMIFS('Prayas TN Records'!$F$2:$F$9981,'Prayas TN Records'!$B$2:$B$9981,$A14,'Prayas TN Records'!$D$2:$D$9981,"Bagasse",'Prayas TN Records'!$I$2:$I$9981,"Yes") | J14: =IF(SUM($I$4:$I$35)=0,0,I14/SUM($I$4:$I$35))-IF(SUM($H$4:$H$35)=0,0,H14/SUM($H$4:$H$35)) | K14: =IF(MAX(ABS(D14),ABS(G14),ABS(J14))>=0.05,"Large distribution difference",IF(MAX(ABS(D14),ABS(G14),ABS(J14))>=0.02,"Moderate difference","Broadly aligned"))
A15: Madurai | B15: ='District Summary'!I15 | C15: =SUMIFS('Prayas TN Records'!$F$2:$F$9981,'Prayas TN Records'!$B$2:$B$9981,$A15,'Prayas TN Records'!$D$2:$D$9981,"Wind",'Prayas TN Records'!$I$2:$I$9981,"Yes") | D15: =IF(SUM($C$4:$C$35)=0,0,C15/SUM($C$4:$C$35))-IF(SUM($B$4:$B$35)=0,0,B15/SUM($B$4:$B$35)) | E15: ='District Summary'!J15 | F15: =SUMIFS('Prayas TN Records'!$F$2:$F$9981,'Prayas TN Records'!$B$2:$B$9981,$A15,'Prayas TN Records'!$D$2:$D$9981,"Solar",'Prayas TN Records'!$I$2:$I$9981,"Yes") | G15: =IF(SUM($F$4:$F$35)=0,0,F15/SUM($F$4:$F$35))-IF(SUM($E$4:$E$35)=0,0,E15/SUM($E$4:$E$35)) | H15: ='District Summary'!E15 | I15: =SUMIFS('Prayas TN Records'!$F$2:$F$9981,'Prayas TN Records'!$B$2:$B$9981,$A15,'Prayas TN Records'!$D$2:$D$9981,"Bagasse",'Prayas TN Records'!$I$2:$I$9981,"Yes") | J15: =IF(SUM($I$4:$I$35)=0,0,I15/SUM($I$4:$I$35))-IF(SUM($H$4:$H$35)=0,0,H15/SUM($H$4:$H$35)) | K15: =IF(MAX(ABS(D15),ABS(G15),ABS(J15))>=0.05,"Large distribution difference",IF(MAX(ABS(D15),ABS(G15),ABS(J15))>=0.02,"Moderate difference","Broadly aligned"))
... A35: Virudhunagar | B35: ='District Summary'!I35 | C35: =SUMIFS('Prayas TN Records'!$F$2:$F$9981,'Prayas TN Records'!$B$2:$B$9981,$A35,'Prayas TN Records'!$D$2:$D$9981,"Wind",'Prayas TN Records'!$I$2:$I$9981,"Yes") | D35: =IF(SUM($C$4:$C$35)=0,0,C35/SUM($C$4:$C$35))-IF(SUM($B$4:$B$35)=0,0,B35/SUM($B$4:$B$35)) | E35: ='District Summary'!J35 | F35: =SUMIFS('Prayas TN Records'!$F$2:$F$9981,'Prayas TN Records'!$B$2:$B$9981,$A35,'Prayas TN Records'!$D$2:$D$9981,"Solar",'Prayas TN Records'!$I$2:$I$9981,"Yes") | G35: =IF(SUM($F$4:$F$35)=0,0,F35/SUM($F$4:$F$35))-IF(SUM($E$4:$E$35)=0,0,E35/SUM($E$4:$E$35)) | H35: ='District Summary'!E35 | I35: =SUMIFS('Prayas TN Records'!$F$2:$F$9981,'Prayas TN Records'!$B$2:$B$9981,$A35,'Prayas TN Records'!$D$2:$D$9981,"Bagasse",'Prayas TN Records'!$I$2:$I$9981,"Yes") | J35: =IF(SUM($I$4:$I$35)=0,0,I35/SUM($I$4:$I$35))-IF(SUM($H$4:$H$35)=0,0,H35/SUM($H$4:$H$35)) | K35: =IF(MAX(ABS(D35),ABS(G35),ABS(J35))>=0.05,"Large distribution difference",IF(MAX(ABS(D35),ABS(G35),ABS(J35))>=0.02,"Moderate difference","Broadly aligned"))
A36: Total | B36: =SUM(B4:B35) | C36: =SUM(C4:C35) | E36: =SUM(E4:E35) | F36: =SUM(F4:F35) | H36: =SUM(H4:H35) | I36: =SUM(I4:I35) | K36: Historical benchmark only

Sheet Prayas Plant Evidence
A1: Plant-level Corrections and Residual Decomposition
A2: Prayas is used as historical evidence. Direct ICED corrections require agreement with CEA; missing plants are deducted from the statewide residual so total capacity is unchanged.
A4: Action | B4: Plant | C4: Prayas raw district | D4: Applied district | E4: Prayas MW | F4: Applied MW | G4: Prayas commissioning date | H4: ICED original row | I4: Confidence | J4: Evidence note
A5: Correct district | B5: Kothari Sugars & Chemicals Ltd., Kattur/Lalgudi | C5: Tiruchirapalli | D5: Tiruchirappalli | E5: 12 | F5: 12 | G5: 35423 | H5: 243 | I5: High | J5: Prayas identifies Tiruchirappalli; CEA confirms Kattur/Lalgudi, Trichy. CEA capacity is 11 MW, so ICED's 12 MW is retained.
A6: Correct district | B6: Madras Sugars & Chemicals Ltd., Vengur | C6: Villupuram | D6: Viluppuram | E6: 25 | F6: 25 | G6: 40683 | H6: 246 | I6: High | J6: Prayas and CEA both identify the 25 MW Vengur unit in Viluppuram.
A7: Fill missing plant | B7: Chengalrayan Co-operative Sugar Mills | C7: Erode | D7: Viluppuram | E7: 18 | F7: 18 | G7: 42417 | H7: 251 | I7: Medium | J7: Prayas plant is matched to the ICED residual; raw Prayas district corrected using official Tamil Nadu location evidence.
A8: Fill missing plant | B8: Vellore Co-operative Sugar Mills | C8: Vellore | D8: Vellore | E8: 15 | F8: 15 | G8: 42754 | H8: 251 | I8: Medium | J8: Prayas and CEA plant records agree.
A9: Fill missing plant | B9: Arignar Anna Co-operative Sugar Mills | C9: Thanjavur | D9: Thanjavur | E9: 15 | F9: 15 | G9: 43347 | H9: 251 | I9: Medium | J9: Prayas and CEA plant records agree.
A10: Fill missing plant | B10: Perambalur Co-operative Sugar Mills | C10: Cuddalore | D10: Perambalur | E10: 18 | F10: 18 | G10: 43514 | H10: 251 | I10: Medium | J10: Prayas plant is matched to the ICED residual; raw Prayas district corrected using CEA/Tamil Nadu evidence.
A11: Fill missing plant | B11: Cheyyar Co-operative Sugar Mills (15 MW unit) | C11: Erode | D11: Tiruvannamalai | E11: 15 | F11: 15 | G11: 42766 | H11: 251 | I11: Medium | J11: Prayas plant is matched to the ICED residual; raw Prayas district corrected using CEA/Tamil Nadu evidence.
A12: Fill missing plant | B12: Dharmapuri District Co-operative Sugar Mills | C12: Not in Prayas extract | D12: Dharmapuri | F12: 12 | H12: 251 | I12: Medium | J12: Later CEA plant record supplements the older Prayas extract.
A13: Residual proxy | B13: Unidentified balance of statewide bio-power residual | C13: — | D13: Multiple districts | F13: 45.2 | H13: 251 | I13: Low | J13: Remaining 45.2 MW retains the earlier ICED district proxy shares.
A15: Source | B15: Reference
A16: Prayas portal and supplied CSV | B16: https://energy.prayaspune.org/renewable-energy-data-portal/plant-wise-re
A17: CEA plant-wise renewable report | B17: https://cea.nic.in/wp-content/uploads/resd/2023/09/August_Plantwise_Details_2022.pdf

Sheet Solar District Evidence
A1: Sep26 Solar Allocation - Updated District Evidence
A2: Validated shares are retained. Current plant-coordinate geography is used only to split the former combined Tirunelveli utility share between Tirunelveli and Tenkasi.
A3: District | B3: Current OSM Solar Proxy MW | C3: Allocated Utility MW | D3: Allocated Rooftop MW | E3: Allocated Off-grid MW | F3: Total Allocated Solar MW | G3: Boundary Source
A4: Ariyalur | B4: 9.5248503 | C4: 5.561021 | D4: 4.016099 | E4: 0.093184397 | F4: 9.6703044 | G4: https://cdn.jsdelivr.net/gh/udit-001/india-maps-data@2884453/geojson/states/tamil-nadu.geojson
A5: Chennai | B5: 1.3277726 | C5: 18.073221 | D5: 183.45384 | E5: 4.2681021 | F5: 205.79516 | G5: https://cdn.jsdelivr.net/gh/udit-001/india-maps-data@2884453/geojson/states/tamil-nadu.geojson
A6: Coimbatore | B6: 34.446289 | C6: 124.46219 | D6: 209.09059 | E6: 5.3839133 | F6: 338.93669 | G6: https://cdn.jsdelivr.net/gh/udit-001/india-maps-data@2884453/geojson/states/tamil-nadu.geojson
A7: Cuddalore | B7: 155.30639 | C7: 944.04902 | D7: 36.554299 | E7: 5.0104028 | F7: 985.61372 | G7: https://cdn.jsdelivr.net/gh/udit-001/india-maps-data@2884453/geojson/states/tamil-nadu.geojson
A8: Dharmapuri | B8: 5.154152 | C8: 127.40246 | D8: 12.847618 | E8: 0.98660486 | F8: 141.23669 | G8: https://cdn.jsdelivr.net/gh/udit-001/india-maps-data@2884453/geojson/states/tamil-nadu.geojson
A9: Dindigul | B9: 374.69222 | C9: 407.8599 | D9: 23.823655 | E9: 0.89702609 | F9: 432.58058 | G9: https://cdn.jsdelivr.net/gh/udit-001/india-maps-data@2884453/geojson/states/tamil-nadu.geojson
A10: Erode | B10: 27.94737 | C10: 825.79533 | D10: 78.255443 | E10: 6.2680727 | F10: 910.31885 | G10: https://cdn.jsdelivr.net/gh/udit-001/india-maps-data@2884453/geojson/states/tamil-nadu.geojson
A11: Kanchipuram | B11: 14.576624 | C11: 530.9621 | D11: 182.55704 | E11: 7.127541 | F11: 720.64668 | G11: https://cdn.jsdelivr.net/gh/udit-001/india-maps-data@2884453/geojson/states/tamil-nadu.geojson
A12: Kanyakumari | B12: 0.96278868 | C12: 1.2862305 | D12: 36.300856 | E12: 0.84227838 | F12: 38.429365 | G12: https://cdn.jsdelivr.net/gh/udit-001/india-maps-data@2884453/geojson/states/tamil-nadu.geojson
A13: Karur | B13: 291.45121 | C13: 470.90518 | D13: 43.163316 | E13: 2.0113138 | F13: 516.07981 | G13: https://cdn.jsdelivr.net/gh/udit-001/india-maps-data@2884453/geojson/states/tamil-nadu.geojson
A14: Krishnagiri | B14: 3.9546342 | C14: 2.8519716 | D14: 17.760515 | E14: 0.41209216 | F14: 21.024579 | G14: https://cdn.jsdelivr.net/gh/udit-001/india-maps-data@2884453/geojson/states/tamil-nadu.geojson
A15: Madurai | B15: 75.667382 | C15: 104.47711 | D15: 65.466312 | E15: 1.9779996 | F15: 171.92142 | G15: https://cdn.jsdelivr.net/gh/udit-001/india-maps-data@2884453/geojson/states/tamil-nadu.geojson
... A37: Virudhunagar | B37: 793.68001 | C37: 1170.5649 | D37: 41.506188 | E37: 1.6492665 | F37: 1213.7203 | G37: https://cdn.jsdelivr.net/gh/udit-001/india-maps-data@2884453/geojson/states/tamil-nadu.geojson

Sheet Solar Allocation QC
A1: Allocation ID | B1: Source Record ID | C1: Name of Power Plant | D1: Source MW | E1: Verified Allocated MW | F1: Difference MW | G1: Check | H1: Allocation Rows
A2: base_row_0173 | B2: SEP26-0173 | C2: INGEL Tamil Nadu 200.0 | D2: 200 | E2: 200 | F2: 0 | G2: OK | H2: 1
A3: base_row_0174 | B3: SEP26-0174 | C3: Tamil Nadu Chennai 16 | D3: 16 | E3: 16 | F3: 0 | G3: OK | H3: 1
A4: base_row_0175 | B4: SEP26-0175 | C4: Tamil Nadu Coimbatore 11.26 | D4: 11.26 | E4: 11.26 | F4: 0 | G4: OK | H4: 1
A5: base_row_0176 | B5: SEP26-0176 | C5: Tamil Nadu Cuddalore 140 | D5: 140 | E5: 140 | F5: 0 | G5: OK | H5: 1
A6: base_row_0177 | B6: SEP26-0177 | C6: Tamil Nadu Dindigul 109.46 | D6: 109.46 | E6: 109.46 | F6: 0 | G6: OK | H6: 1
A7: base_row_0178 | B7: SEP26-0178 | C7: Tamil Nadu Erode 7 | D7: 7 | E7: 7 | F7: 0 | G7: OK | H7: 1
A8: base_row_0179 | B8: SEP26-0179 | C8: Tamil Nadu Kanniyakumari 1 | D8: 1 | E8: 1 | F8: 0 | G8: OK | H8: 1
A9: base_row_0180 | B9: SEP26-0180 | C9: Tamil Nadu Karur 156.49 | D9: 156.49 | E9: 156.49 | F9: 0 | G9: OK | H9: 1
A10: base_row_0181 | B10: SEP26-0181 | C10: Tamil Nadu Krishnagiri 0.75 | D10: 0.75 | E10: 0.75 | F10: 0 | G10: OK | H10: 1
A11: base_row_0182 | B11: SEP26-0182 | C11: Tamil Nadu Madurai 1 | D11: 1 | E11: 1 | F11: 0 | G11: OK | H11: 1
A12: base_row_0187 | B12: SEP26-0187 | C12: Tamil Nadu Nagapattinam 5 | D12: 5 | E12: 5 | F12: 0 | G12: OK | H12: 1
A13: base_row_0188 | B13: SEP26-0188 | C13: Tamil Nadu Perambalur 10 | D13: 10 | E13: 10 | F13: 0 | G13: OK | H13: 1
... A29: solar_utility_other | B29: SEP26-0185 | C29: Tamil Nadu N.A. Others (Districts not specified) 9143.18 | D29: 9143.18 | E29: 9143.18 | F29: 0 | G29: OK | H29: 30

Sheet Overpass Solar Plants
A1: Supplied Overpass / OpenStreetMap solar-plant evidence
A2: Extract timestamp: 2026-08-19T12:01:02Z. Untagged plant footprints are estimated at 49.71 MW/km², the median of 30 capacity-tagged plants. These estimates are used for distribution weights only.
A4: OSM ID | B4: Plant name | C4: Modern district | D4: Harmonized district | E4: Latitude | F4: Longitude | G4: Mapped area km² | H4: Explicit MW | I4: Estimated MW | J4: Capacity basis | K4: OSM URL
A5: relation/8550920 | B5: Solarpark Kamuthi | C5: Ramanathapuram | D5: Ramanathapuram | E5: 9.33285 | F5: 78.390487 | G5: 11.069615 | H5: 648 | I5: 648 | J5: OSM MW tag | K5: https://www.openstreetmap.org/relation/8550920
A6: way/1264134432 | C6: Thoothukudi | D6: Thoothukudi | E6: 9.1763243 | F6: 77.99903 | G6: 3.3763365 | I6: 167.83702 | J6: footprint estimate | K6: https://www.openstreetmap.org/way/1264134432
A7: way/964517522 | C7: Thoothukudi | D7: Thoothukudi | E7: 8.9704545 | F7: 77.898441 | G7: 2.9091473 | I7: 144.61314 | J7: footprint estimate | K7: https://www.openstreetmap.org/way/964517522
A8: relation/8553387 | B8: Neyveli Solar Project | C8: Cuddalore | D8: Cuddalore | E8: 11.610547 | F8: 79.510422 | G8: 2.7201609 | H8: 130 | I8: 130 | J8: OSM MW tag | K8: https://www.openstreetmap.org/relation/8553387
A9: way/743737307 | C9: Virudhunagar | D9: Virudhunagar | E9: 9.4894929 | F9: 78.224845 | G9: 2.2924384 | I9: 113.95666 | J9: footprint estimate | K9: https://www.openstreetmap.org/way/743737307
A10: way/1432129281 | C10: Thoothukudi | D10: Thoothukudi | E10: 9.0456447 | F10: 77.975817 | G10: 2.1240288 | I10: 105.58505 | J10: footprint estimate | K10: https://www.openstreetmap.org/way/1432129281
A11: relation/13466525 | C11: Thoothukudi | D11: Thoothukudi | E11: 8.9691863 | F11: 77.898471 | G11: 1.7501897 | I11: 87.001584 | J11: footprint estimate | K11: https://www.openstreetmap.org/relation/13466525
A12: way/986260255 | C12: Theni | D12: Theni | E12: 10.138803 | F12: 77.711932 | G12: 1.6863823 | I12: 83.829733 | J12: footprint estimate | K12: https://www.openstreetmap.org/way/986260255
A13: way/986279191 | C13: Tirunelveli | D13: Tirunelveli | E13: 8.8466389 | F13: 77.596822 | G13: 1.5802405 | I13: 78.553444 | J13: footprint estimate | K13: https://www.openstreetmap.org/way/986279191
A14: relation/13533021 | C14: Thoothukudi | D14: Thoothukudi | E14: 8.9135991 | F14: 77.823234 | G14: 1.5196824 | I14: 75.54311 | J14: footprint estimate | K14: https://www.openstreetmap.org/relation/13533021
A15: way/719469800 | C15: Ramanathapuram | D15: Ramanathapuram | E15: 9.3912144 | F15: 78.351353 | G15: 1.5012977 | I15: 74.62921 | J15: footprint estimate | K15: https://www.openstreetmap.org/way/719469800
A16: way/986279190 | C16: Tenkasi | D16: Tirunelveli | E16: 8.8414104 | F16: 77.586118 | G16: 1.4765233 | I16: 73.39768 | J16: footprint estimate | K16: https://www.openstreetmap.org/way/986279190
A17: way/867822460 | C17: Ramanathapuram | D17: Ramanathapuram | E17: 9.2213396 | F17: 78.385141 | G17: 1.4693665 | I17: 73.041917 | J17: footprint estimate | K17: https://www.openstreetmap.org/way/867822460
A18: way/719469801 | C18: Virudhunagar | D18: Virudhunagar | E18: 9.3587713 | F18: 78.216304 | G18: 1.4107144 | I18: 70.126332 | J18: footprint estimate | K18: https://www.openstreetmap.org/way/719469801
A19: way/1264199856 | C19: Dindigul | D19: Dindigul | E19: 10.180112 | F19: 77.805814 | G19: 1.3466628 | I19: 66.94234 | J19: footprint estimate | K19: https://www.openstreetmap.org/way/1264199856
A20: way/1432129272 | C20: Thoothukudi | D20: Thoothukudi | E20: 8.8370313 | F20: 78.033279 | G20: 1.2586595 | I20: 62.567716 | J20: footprint estimate | K20: https://www.openstreetmap.org/way/1432129272
A21: way/590858784 | B21: Narikudi | C21: Virudhunagar | D21: Virudhunagar | E21: 9.5720485 | F21: 78.311133 | G21: 2.6816427 | H21: 60 | I21: 60 | J21: OSM MW tag | K21: https://www.openstreetmap.org/way/590858784
A22: way/964222299 | C22: Thoothukudi | D22: Thoothukudi | E22: 8.9346161 | F22: 77.836524 | G22: 1.1140566 | I22: 55.379535 | J22: footprint estimate | K22: https://www.openstreetmap.org/way/964222299
A23: way/1260732913 | C23: Tenkasi | D23: Tirunelveli | E23: 8.8945123 | F23: 77.562456 | G23: 1.0645863 | I23: 52.920372 | J23: footprint estimate | K23: https://www.openstreetmap.org/way/1260732913
A24: way/986250513 | C24: Tiruppur | D24: Tiruppur | E24: 10.774814 | F24: 77.231367 | G24: 1.008129 | I24: 50.113891 | J24: footprint estimate | K24: https://www.openstreetmap.org/way/986250513
A25: way/1210056315 | C25: Virudhunagar | D25: Virudhunagar | E25: 9.3015365 | F25: 78.297503 | G25: 1.007831 | I25: 50.099078 | J25: footprint estimate | K25: https://www.openstreetmap.org/way/1210056315
A26: way/590858788 | B26: Tiruchuli | C26: Virudhunagar | D26: Virudhunagar | E26: 9.5214072 | F26: 78.227831 | G26: 1.4674854 | H26: 50 | I26: 50 | J26: OSM MW tag | K26: https://www.openstreetmap.org/way/590858788
A27: way/830292750 | B27: Kallurani Aadhavan | C27: Virudhunagar | D27: Virudhunagar | E27: 9.4459764 | F27: 78.149333 | G27: 0.17124072 | H27: 50 | I27: 50 | J27: OSM MW tag | K27: https://www.openstreetmap.org/way/830292750
A28: way/986247881 | B28: Ponnusangampatti | C28: Tiruchirappalli | D28: Tiruchirappalli | E28: 11.065254 | F28: 78.493435 | G28: 1.4131866 | H28: 50 | I28: 50 | J28: OSM MW tag | K28: https://www.openstreetmap.org/way/986247881
A29: way/986279202 | C29: Virudhunagar | D29: Virudhunagar | E29: 9.325643 | F29: 77.601781 | G29: 0.84475496 | H29: 50 | I29: 50 | J29: OSM MW tag | K29: https://www.openstreetmap.org/way/986279202
A30: way/986279203 | B30: Sattur | C30: Virudhunagar | D30: Virudhunagar | E30: 9.411261 | F30: 78.003481 | G30: 0.8007411 | H30: 50 | I30: 50 | J30: OSM MW tag | K30: https://www.openstreetmap.org/way/986279203
A31: way/466142896 | B31: Kayanathar | C31: Tirunelveli | D31: Tirunelveli | E31: 8.9125558 | F31: 77.745844 | G31: 0.85231371 | H31: 49 | I31: 49 | J31: OSM MW tag | K31: https://www.openstreetmap.org/way/466142896
A32: way/986260251 | C32: Sivagangai | D32: Sivaganga | E32: 9.9414704 | F32: 78.716653 | G32: 0.8853236 | I32: 44.009261 | J32: footprint estimate | K32: https://www.openstreetmap.org/way/986260251
A33: way/618762305 | B33: Shezhilanallur | C33: Tirunelveli | D33: Tirunelveli | E33: 8.9168994 | F33: 77.715117 | G33: 0.85540023 | I33: 42.521776 | J33: footprint estimate | K33: https://www.openstreetmap.org/way/618762305
A34: way/998302166 | C34: Karur | D34: Karur | E34: 10.873952 | F34: 78.295774 | G34: 0.84054265 | I34: 41.783209 | J34: footprint estimate | K34: https://www.openstreetmap.org/way/998302166
A35: way/1002687119 | B35: Moolippatti | C35: Virudhunagar | D35: Virudhunagar | E35: 9.6433332 | F35: 77.851159 | G35: 0.79079836 | H35: 40 | I35: 40 | J35: OSM MW tag | K35: https://www.openstreetmap.org/way/1002687119
A36: way/618762302 | C36: Tirunelveli | D36: Tirunelveli | E36: 8.9218708 | F36: 77.701159 | G36: 0.80012558 | I36: 39.774084 | J36: footprint estimate | K36: https://www.openstreetmap.org/way/618762302
A37: way/986279189 | C37: Tirunelveli | D37: Tirunelveli | E37: 8.8540784 | F37: 77.605456 | G37: 0.75582987 | I37: 37.572153 | J37: footprint estimate | K37: https://www.openstreetmap.org/way/986279189
A38: way/1432129271 | C38: Thoothukudi | D38: Thoothukudi | E38: 8.8503575 | F38: 78.036635 | G38: 0.73866683 | I38: 36.718982 | J38: footprint estimate | K38: https://www.openstreetmap.org/way/1432129271
A39: way/751947969 | B39: Chengam | C39: Tiruvannamalai | D39: Tiruvannamalai | E39: 12.344401 | F39: 78.947235 | G39: 0.65069925 | H39: 36 | I39: 36 | J39: OSM MW tag | K39: https://www.openstreetmap.org/way/751947969
A40: way/1262529561 | C40: Tirunelveli | D40: Tirunelveli | E40: 8.8733089 | F40: 77.631048 | G40: 0.69636219 | I40: 34.616027 | J40: footprint estimate | K40: https://www.openstreetmap.org/way/1262529561
A41: way/986279192 | C41: Thoothukudi | D41: Thoothukudi | E41: 8.8799029 | F41: 77.852621 | G41: 0.6884527 | I41: 34.222848 | J41: footprint estimate | K41: https://www.openstreetmap.org/way/986279192
A42: way/1432129280 | C42: Thoothukudi | D42: Thoothukudi | E42: 9.0211366 | F42: 77.98652 | G42: 0.6852794 | I42: 34.065103 | J42: footprint estimate | K42: https://www.openstreetmap.org/way/1432129280
A43: way/986403903 | C43: Tirunelveli | D43: Tirunelveli | E43: 8.8851761 | F43: 77.678366 | G43: 0.68526229 | I43: 34.064253 | J43: footprint estimate | K43: https://www.openstreetmap.org/way/986403903
A44: way/1432129284 | C44: Thoothukudi | D44: Thoothukudi | E44: 9.0602199 | F44: 77.9701 | G44: 0.68207739 | I44: 33.905932 | J44: footprint estimate | K44: https://www.openstreetmap.org/way/1432129284
A45: way/867822462 | C45: Ramanathapuram | D45: Ramanathapuram | E45: 9.2209918 | F45: 78.407813 | G45: 0.67939722 | I45: 33.772701 | J45: footprint estimate | K45: https://www.openstreetmap.org/way/867822462
A46: way/998302168 | C46: Karur | D46: Karur | E46: 10.880681 | F46: 78.345568 | G46: 0.65843753 | I46: 32.7308 | J46: footprint estimate | K46: https://www.openstreetmap.org/way/998302168
A47: way/1268390447 | C47: Dindigul | D47: Dindigul | E47: 10.078306 | F47: 77.810782 | G47: 0.64556607 | I47: 32.090962 | J47: footprint estimate | K47: https://www.openstreetmap.org/way/1268390447
A48: way/1268329098 | C48: Tenkasi | D48: Tirunelveli | E48: 8.9383096 | F48: 77.660355 | G48: 0.64537297 | I48: 32.081363 | J48: footprint estimate | K48: https://www.openstreetmap.org/way/1268329098
A49: way/1432129273 | C49: Thoothukudi | D49: Thoothukudi | E49: 9.0317557 | F49: 78.073229 | G49: 0.63998608 | I49: 31.813581 | J49: footprint estimate | K49: https://www.openstreetmap.org/way/1432129273
A50: way/719469797 | C50: Virudhunagar | D50: Virudhunagar | E50: 9.491209 | F50: 78.267195 | G50: 0.62446755 | I50: 31.042158 | J50: footprint estimate | K50: https://www.openstreetmap.org/way/719469797
A51: way/986260254 | B51: Eluvanampatty | C51: Dindigul | D51: Dindigul | E51: 10.13364 | F51: 77.691871 | G51: 0.97166982 | H51: 30 | I51: 30 | J51: OSM MW tag | K51: https://www.openstreetmap.org/way/986260254
A52: way/719469796 | C52: Virudhunagar | D52: Virudhunagar | E52: 9.4990243 | F52: 78.261037 | G52: 0.57963035 | I52: 28.81331 | J52: footprint estimate | K52: https://www.openstreetmap.org/way/719469796
A53: way/830287986 | B53: GRT 6 | C53: Virudhunagar | D53: Virudhunagar | E53: 9.4413376 | F53: 78.051787 | G53: 0.5433848 | I53: 27.011551 | J53: footprint estimate | K53: https://www.openstreetmap.org/way/830287986
A54: way/986260252 | C54: Theni | D54: Theni | E54: 10.105015 | F54: 77.697516 | G54: 0.53530182 | I54: 26.609748 | J54: footprint estimate | K54: https://www.openstreetmap.org/way/986260252
A55: way/986260253 | C55: Theni | D55: Theni | E55: 10.11538 | F55: 77.663317 | G55: 0.52157475 | I55: 25.927378 | J55: footprint estimate | K55: https://www.openstreetmap.org/way/986260253
A56: relation/17368770 | C56: Karur | D56: Karur | E56: 10.96449 | F56: 77.780671 | G56: 0.51593836 | I56: 25.647194 | J56: footprint estimate | K56: https://www.openstreetmap.org/relation/17368770
A57: way/986279204 | B57: NLC Ramanathapuram | C57: Ramanathapuram | D57: Ramanathapuram | E57: 9.4420268 | F57: 78.576175 | G57: 0.51414502 | I57: 25.558047 | J57: footprint estimate | K57: https://www.openstreetmap.org/way/986279204
A58: relation/17348197 | B58: SPIC Thoothukudi Floating Solar PV Park | C58: Thoothukudi | D58: Thoothukudi | E58: 8.7339987 | F58: 78.128769 | G58: 0.19248448 | H58: 25.3 | I58: 25.3 | J58: OSM MW tag | K58: https://www.openstreetmap.org/relation/17348197
A59: way/1210056316 | C59: Virudhunagar | D59: Virudhunagar | E59: 9.3049469 | F59: 78.278024 | G59: 0.49756218 | I59: 24.733717 | J59: footprint estimate | K59: https://www.openstreetmap.org/way/1210056316
A60: way/864904512 | C60: Virudhunagar | D60: Virudhunagar | E60: 9.3371525 | F60: 78.257552 | G60: 0.4857287 | I60: 24.145478 | J60: footprint estimate | K60: https://www.openstreetmap.org/way/864904512
A61: relation/20982849 | C61: Tiruppur | D61: Tiruppur | E61: 10.829614 | F61: 77.533432 | G61: 0.44606728 | I61: 22.173916 | J61: footprint estimate | K61: https://www.openstreetmap.org/relation/20982849
A62: way/1260732914 | C62: Tenkasi | D62: Tirunelveli | E62: 8.9044884 | F62: 77.548248 | G62: 0.40818873 | I62: 20.290981 | J62: footprint estimate | K62: https://www.openstreetmap.org/way/1260732914
A63: way/1268305324 | C63: Thoothukudi | D63: Thoothukudi | E63: 8.6614063 | F63: 77.942513 | G63: 0.4024496 | I63: 20.00569 | J63: footprint estimate | K63: https://www.openstreetmap.org/way/1268305324
A64: way/986247883 | B64: Musri | C64: Tiruchirappalli | D64: Tiruchirappalli | E64: 11.079757 | F64: 78.505782 | G64: 0.55227393 | H64: 20 | I64: 20 | J64: OSM MW tag | K64: https://www.openstreetmap.org/way/986247883
A65: way/986260257 | B65: Agaram A | C65: Dindigul | D65: Dindigul | E65: 10.455718 | F65: 77.923935 | G65: 0.51817999 | H65: 20 | I65: 20 | J65: OSM MW tag | K65: https://www.openstreetmap.org/way/986260257
A66: way/1432135179 | C66: Thoothukudi | D66: Thoothukudi | E66: 8.9125392 | F66: 78.052729 | G66: 0.37696171 | I66: 18.738692 | J66: footprint estimate | K66: https://www.openstreetmap.org/way/1432135179
A67: way/986403902 | C67: Tenkasi | D67: Tirunelveli | E67: 8.7880785 | F67: 77.518731 | G67: 0.37329894 | I67: 18.556617 | J67: footprint estimate | K67: https://www.openstreetmap.org/way/986403902
A68: way/590858783 | B68: Melamudimannar | C68: Ramanathapuram | D68: Ramanathapuram | E68: 9.4163277 | F68: 78.247583 | G68: 0.36856689 | H68: 18 | I68: 18 | J68: OSM MW tag | K68: https://www.openstreetmap.org/way/590858783
A69: way/1262929961 | C69: Dindigul | D69: Dindigul | E69: 10.49533 | F69: 77.921058 | G69: 0.35603928 | I69: 17.698642 | J69: footprint estimate | K69: https://www.openstreetmap.org/way/1262929961
A70: way/1432129275 | C70: Thoothukudi | D70: Thoothukudi | E70: 9.0290546 | F70: 78.08918 | G70: 0.34981746 | I70: 17.389357 | J70: footprint estimate | K70: https://www.openstreetmap.org/way/1432129275
A71: way/999721679 | C71: Karur | D71: Karur | E71: 10.836319 | F71: 78.424176 | G71: 0.34957715 | I71: 17.377411 | J71: footprint estimate | K71: https://www.openstreetmap.org/way/999721679
A72: way/1268427543 | C72: Tiruppur | D72: Tiruppur | E72: 10.501686 | F72: 77.254904 | G72: 0.33551623 | I72: 16.678446 | J72: footprint estimate | K72: https://www.openstreetmap.org/way/1268427543
A73: way/1231732018 | C73: Karur | D73: Karur | E73: 10.705778 | F73: 78.299016 | G73: 0.31842162 | I73: 15.828676 | J73: footprint estimate | K73: https://www.openstreetmap.org/way/1231732018
A74: way/1268403341 | C74: Dindigul | D74: Dindigul | E74: 10.441817 | F74: 78.048732 | G74: 0.30492596 | I74: 15.157809 | J74: footprint estimate | K74: https://www.openstreetmap.org/way/1268403341
A75: way/1268435659 | C75: Dindigul | D75: Dindigul | E75: 10.594292 | F75: 78.009554 | G75: 0.30299681 | I75: 15.061912 | J75: footprint estimate | K75: https://www.openstreetmap.org/way/1268435659
A76: way/1268573578 | C76: Tiruvannamalai | D76: Tiruvannamalai | E76: 12.58188 | F76: 79.289312 | G76: 0.30289831 | I76: 15.057015 | J76: footprint estimate | K76: https://www.openstreetmap.org/way/1268573578
A77: way/1227456589 | C77: Dindigul | D77: Dindigul | E77: 10.612661 | F77: 78.099036 | G77: 0.30271105 | I77: 15.047706 | J77: footprint estimate | K77: https://www.openstreetmap.org/way/1227456589
A78: way/1227641007 | B78: Moovanur | C78: Tiruchirappalli | D78: Tiruchirappalli | E78: 11.001433 | F78: 78.611541 | G78: 0.26358168 | H78: 15 | I78: 15 | J78: OSM MW tag | K78: https://www.openstreetmap.org/way/1227641007
A79: way/1268378844 | C79: Virudhunagar | D79: Virudhunagar | E79: 9.6317922 | F79: 77.687931 | G79: 0.28957996 | I79: 14.394963 | J79: footprint estimate | K79: https://www.openstreetmap.org/way/1268378844
A80: way/1268334409 | C80: Virudhunagar | D80: Virudhunagar | E80: 9.3778893 | F80: 78.020788 | G80: 0.28376039 | I80: 14.105673 | J80: footprint estimate | K80: https://www.openstreetmap.org/way/1268334409
A81: way/618569316 | B81: Amathur | C81: Virudhunagar | D81: Virudhunagar | E81: 9.5534884 | F81: 77.884748 | G81: 0.25442402 | H81: 14 | I81: 14 | J81: OSM MW tag | K81: https://www.openstreetmap.org/way/618569316
A82: way/999721676 | C82: Coimbatore | D82: Coimbatore | E82: 10.837807 | F82: 77.067206 | G82: 0.28104197 | I82: 13.970541 | J82: footprint estimate | K82: https://www.openstreetmap.org/way/999721676
A83: way/1432135180 | C83: Thoothukudi | D83: Thoothukudi | E83: 8.9060774 | F83: 78.04756 | G83: 0.27669379 | I83: 13.754394 | J83: footprint estimate | K83: https://www.openstreetmap.org/way/1432135180
A84: way/1231732016 | C84: Karur | D84: Karur | E84: 10.792414 | F84: 78.308762 | G84: 0.2715895 | I84: 13.500661 | J84: footprint estimate | K84: https://www.openstreetmap.org/way/1231732016
A85: way/1431998762 | C85: Tiruchirappalli | D85: Tiruchirappalli | E85: 11.135479 | F85: 78.436198 | G85: 0.26956937 | I85: 13.40024 | J85: footprint estimate | K85: https://www.openstreetmap.org/way/1431998762
A86: way/964184651 | C86: Thoothukudi | D86: Thoothukudi | E86: 8.9456979 | F86: 77.832289 | G86: 0.25771003 | I86: 12.810715 | J86: footprint estimate | K86: https://www.openstreetmap.org/way/964184651
A87: way/1268453051 | C87: Karur | D87: Karur | E87: 10.75599 | F87: 77.874311 | G87: 0.25154938 | I87: 12.50447 | J87: footprint estimate | K87: https://www.openstreetmap.org/way/1268453051
A88: way/986279195 | C88: Thoothukudi | D88: Thoothukudi | E88: 8.9008617 | F88: 77.797468 | G88: 0.24613279 | I88: 12.235212 | J88: footprint estimate | K88: https://www.openstreetmap.org/way/986279195
A89: way/1268432836 | C89: Tiruchirappalli | D89: Tiruchirappalli | E89: 10.537024 | F89: 78.235911 | G89: 0.24238578 | I89: 12.048949 | J89: footprint estimate | K89: https://www.openstreetmap.org/way/1268432836
A90: way/1262931340 | C90: Dindigul | D90: Dindigul | E90: 10.119279 | F90: 77.723718 | G90: 0.24077823 | I90: 11.969038 | J90: footprint estimate | K90: https://www.openstreetmap.org/way/1262931340
A91: relation/16765870 | C91: Thoothukudi | D91: Thoothukudi | E91: 8.7665528 | F91: 77.980018 | G91: 0.23746429 | I91: 11.804303 | J91: footprint estimate | K91: https://www.openstreetmap.org/relation/16765870
A92: way/1348009026 | C92: Ranipet | D92: Vellore | E92: 12.781241 | F92: 79.446054 | G92: 0.23224888 | I92: 11.545046 | J92: footprint estimate | K92: https://www.openstreetmap.org/way/1348009026
A93: way/1432129279 | C93: Thoothukudi | D93: Thoothukudi | E93: 9.0235527 | F93: 78.00233 | G93: 0.23136411 | I93: 11.501064 | J93: footprint estimate | K93: https://www.openstreetmap.org/way/1432129279
... A106: way/1227457839 | C106: Virudhunagar | D106: Virudhunagar | E106: 9.662366 | F106: 78.221876 | G106: 0.20186434 | I106: 10.034637 | J106: footprint estimate | K106: https://www.openstreetmap.org/way/1227457839
A107: way/618569337 | B107: Valathadippatti | C107: Pudukkottai | D107: Pudukkottai | E107: 10.57876 | F107: 78.634561 | G107: 0.22970291 | H107: 10 | I107: 10 | J107: OSM MW tag | K107: https://www.openstreetmap.org/way/618569337
A108: way/986279205 | B108: Pambur | C108: Ramanathapuram | D108: Ramanathapuram | E108: 9.4529826 | F108: 78.572429 | G108: 0.52055951 | H108: 10 | I108: 10 | J108: OSM MW tag | K108: https://www.openstreetmap.org/way/986279205
A109: way/998307433 | B109: Karur | C109: Karur | D109: Karur | E109: 10.815852 | F109: 78.186576 | G109: 0.19249611 | H109: 10 | I109: 10 | J109: OSM MW tag | K109: https://www.openstreetmap.org/way/998307433
A110: way/999684607 | B110: Kottathur | C110: Perambalur | D110: Perambalur | E110: 11.121853 | F110: 78.688991 | G110: 0.22747902 | H110: 10 | I110: 10 | J110: OSM MW tag | K110: https://www.openstreetmap.org/way/999684607
A111: way/986403914 | C111: Dindigul | D111: Dindigul | E111: 10.565057 | F111: 77.935002 | G111: 0.20075608 | I111: 9.9795449 | J111: footprint estimate | K111: https://www.openstreetmap.org/way/986403914
A112: way/1268458748 | C112: Karur | D112: Karur | E112: 10.778153 | F112: 78.372624 | G112: 0.19912554 | I112: 9.8984913 | J112: footprint estimate | K112: https://www.openstreetmap.org/way/1268458748
A113: way/1231732015 | C113: Karur | D113: Karur | E113: 10.866291 | F113: 78.2338 | G113: 0.19828372 | I113: 9.8566446 | J113: footprint estimate | K113: https://www.openstreetmap.org/way/1231732015
...

Sheet Solar Methodology
A1: Sep26 Solar Allocation Methodology
A2: Topic | B2: Method / interpretation
A3: Scope | B3: Only unresolved/statewide solar records are redistributed; direct Sep26 district records are retained.
A4: Utility | B4: Validated hybrid OSM/official-anchor shares are retained and applied to Sep26 capacities.
A5: Tenkasi | B5: The old Tirunelveli combined utility share is split using current OSM plant proxy MW for Tirunelveli and Tenkasi.
A6: Rooftop | B6: The validated PM Surya Ghar installation shares are retained.
A7: Off-grid | B7: The validated PM Surya Ghar proxy shares are retained at Low confidence.
A8: Boundary source | B8: https://cdn.jsdelivr.net/gh/udit-001/india-maps-data@2884453/geojson/states/tamil-nadu.geojson

Sheet Wind District Evidence
A1: Sep26 Wind Residual Allocation - District Evidence
A2: Supplied OSM turbines were reassigned to current district polygons. Tenkasi is separate; other new districts are recombined to the established allocation geography.
A3: District | B3: OSM Proxy MW | C3: Scaled Target MW | D3: Known Sep26 Wind MW | E3: Positive Gap MW | F3: Residual Share | G3: Allocated N.A. MW | H3: Boundary Source | I3: Confidence
A4: Ariyalur | B4: 0 | C4: 0 | D4: 22 | E4: 0 | F4: 0 | G4: 0 | H4: https://cdn.jsdelivr.net/gh/udit-001/india-maps-data@2884453/geojson/states/tamil-nadu.geojson | I4: Medium
A5: Chennai | B5: 0 | C5: 0 | D5: 3.125 | E5: 0 | F5: 0 | G5: 0 | H5: https://cdn.jsdelivr.net/gh/udit-001/india-maps-data@2884453/geojson/states/tamil-nadu.geojson | I5: Medium
A6: Coimbatore | B6: 1128.75 | C6: 867.05655 | D6: 2175.4 | E6: 0 | F6: 0 | G6: 0 | H6: https://cdn.jsdelivr.net/gh/udit-001/india-maps-data@2884453/geojson/states/tamil-nadu.geojson | I6: Medium
A7: Dharmapuri | B7: 0 | C7: 0 | D7: 196 | E7: 0 | F7: 0 | G7: 0 | H7: https://cdn.jsdelivr.net/gh/udit-001/india-maps-data@2884453/geojson/states/tamil-nadu.geojson | I7: Medium
A8: Dindigul | B8: 450 | C8: 345.67038 | D8: 318.085 | E8: 27.585385 | F8: 0.0060256568 | G8: 1.5448278 | H8: https://cdn.jsdelivr.net/gh/udit-001/india-maps-data@2884453/geojson/states/tamil-nadu.geojson | I8: Medium
A9: Erode | B9: 0 | C9: 0 | D9: 129.33 | E9: 0 | F9: 0 | G9: 0 | H9: https://cdn.jsdelivr.net/gh/udit-001/india-maps-data@2884453/geojson/states/tamil-nadu.geojson | I9: Medium
A10: Kanchipuram | B10: 0 | C10: 0 | D10: 7.65 | E10: 0 | F10: 0 | G10: 0 | H10: https://cdn.jsdelivr.net/gh/udit-001/india-maps-data@2884453/geojson/states/tamil-nadu.geojson | I10: Medium
A11: Kanyakumari | B11: 431.25 | C11: 331.26745 | D11: 349.375 | E11: 0 | F11: 0 | G11: 0 | H11: https://cdn.jsdelivr.net/gh/udit-001/india-maps-data@2884453/geojson/states/tamil-nadu.geojson | I11: Medium
A12: Karur | B12: 71.25 | C12: 54.731144 | D12: 699.595 | E12: 0 | F12: 0 | G12: 0 | H12: https://cdn.jsdelivr.net/gh/udit-001/india-maps-data@2884453/geojson/states/tamil-nadu.geojson | I12: Medium
A13: Ramanathapuram | B13: 2.5 | C13: 1.920391 | D13: 34.03 | E13: 0 | F13: 0 | G13: 0 | H13: https://cdn.jsdelivr.net/gh/udit-001/india-maps-data@2884453/geojson/states/tamil-nadu.geojson | I13: Medium
A14: Salem | B14: 0 | C14: 0 | D14: 3.4 | E14: 0 | F14: 0 | G14: 0 | H14: https://cdn.jsdelivr.net/gh/udit-001/india-maps-data@2884453/geojson/states/tamil-nadu.geojson | I14: Medium
A15: Tenkasi | B15: 2435 | C15: 1870.4609 | D15: 22.88 | E15: 1847.5809 | F15: 0.40357922 | G15: 103.46762 | H15: https://cdn.jsdelivr.net/gh/udit-001/india-maps-data@2884453/geojson/states/tamil-nadu.geojson | I15: Medium
... A23: Viluppuram | B23: 2.5 | C23: 1.920391 | D23: 1.7 | E23: 0.22039103 | F23: 4.8141459e-05 | G23: 0.012342267 | H23: https://cdn.jsdelivr.net/gh/udit-001/india-maps-data@2884453/geojson/states/tamil-nadu.geojson | I23: Medium

Sheet Wind Allocation QC
A1: Allocation ID | B1: Source Record ID | C1: Name of Power Plant | D1: Source MW | E1: Verified Allocated MW | F1: Difference MW | G1: Check | H1: Allocation Rows
A2: base_row_0143 | B2: SEP26-0143 | C2: 151 MW SJVN Wind Palayam Green Shoe Tamil Nadu Karur | D2: 151.2 | E2: 151.2 | F2: 0 | G2: OK | H2: 1
A3: base_row_0144 | B3: SEP26-0144 | C3: 151.2 MW Wind SJVN FDRE Basis LOA Tamil Nadu Karur | D3: 151.2 | E3: 151.2 | F3: 0 | G3: OK | H3: 1
A4: base_row_0145 | B4: SEP26-0145 | C4: 82.5 MW NTPC FDRE Wind Tamil Nadu Karur | D4: 82.5 | E4: 82.5 | F4: 0 | G4: OK | H4: 1
A5: base_row_0146 | B5: SEP26-0146 | C5: 93.6 MW Karur - SJVN FDRE Green Shoe Tamil Nadu Karur | D5: 93.6 | E5: 93.6 | F5: 0 | G5: OK | H5: 1
A6: base_row_0147 | B6: SEP26-0147 | C6: Amplus Sun Beat Private Limited Tamil Nadu Karur | D6: 80 | E6: 80 | F6: 0 | G6: OK | H6: 1
A7: base_row_0148 | B7: SEP26-0148 | C7: Amplus Theta Energy Private Limited Tamil Nadu Karur | D7: 65 | E7: 65 | F7: 0 | G7: OK | H7: 1
A8: base_row_0149 | B8: SEP26-0149 | C8: Jindal Renewables - Wind Project - C&I Tamil Nadu Karur | D8: 300 | E8: 300 | F8: 0 | G8: OK | H8: 1
A9: base_row_0150 | B9: SEP26-0150 | C9: Jindal Renewables - Wind Project - C&I Tamil Nadu Karur | D9: 50 | E9: 50 | F9: 0 | G9: OK | H9: 1
A10: base_row_0151 | B10: SEP26-0151 | C10: Tamil Nadu-Ariyalur | D10: 22 | E10: 22 | F10: 0 | G10: OK | H10: 1
A11: base_row_0152 | B11: SEP26-0152 | C11: Tamil Nadu-Chennai | D11: 3.125 | E11: 3.125 | F11: 0 | G11: OK | H11: 1
A12: base_row_0153 | B12: SEP26-0153 | C12: Tamil Nadu-Coimbatore | D12: 2175.4 | E12: 2175.4 | F12: 0 | G12: OK | H12: 1
A13: base_row_0154 | B13: SEP26-0154 | C13: Tamil Nadu-Dharmapuri | D13: 196 | E13: 196 | F13: 0 | G13: OK | H13: 1
... A31: wind_unspecified | B31: SEP26-0160 | C31: Tamil Nadu-N.A. | D31: 256.375 | E31: 256.375 | F31: 0 | G31: OK | H31: 4

Sheet Overpass Wind Turbines
A1: Supplied Overpass / OpenStreetMap wind-turbine evidence
A2: Extract timestamp: 2026-08-19T12:39:27Z. 12,807 turbines were assigned to districts; 6 carry usable output tags. The 1.250 MW/turbine median proxy is used only to create geographic shares.
A4: OSM ID | B4: Name | C4: Harmonized district | D4: Latitude | E4: Longitude | F4: Output tag | G4: Explicit MW | H4: Proxy MW | I4: Capacity basis | J4: OSM URL
A5: node/11846640846 | C5: Coimbatore | D5: 10.846752 | E5: 77.107849 | H5: 1.25 | I5: untagged; 1.250 MW/turbine proxy | J5: https://www.openstreetmap.org/node/11846640846
A6: node/11847815108 | C6: Coimbatore | D6: 10.786553 | E6: 77.055269 | H6: 1.25 | I6: untagged; 1.250 MW/turbine proxy | J6: https://www.openstreetmap.org/node/11847815108
A7: node/11847815109 | C7: Coimbatore | D7: 10.787715 | E7: 77.049856 | H7: 1.25 | I7: untagged; 1.250 MW/turbine proxy | J7: https://www.openstreetmap.org/node/11847815109
A8: node/11848030196 | C8: Coimbatore | D8: 10.669892 | E8: 77.125773 | H8: 1.25 | I8: untagged; 1.250 MW/turbine proxy | J8: https://www.openstreetmap.org/node/11848030196
A9: node/11849861126 | C9: Coimbatore | D9: 10.587748 | E9: 77.14874 | H9: 1.25 | I9: untagged; 1.250 MW/turbine proxy | J9: https://www.openstreetmap.org/node/11849861126
A10: node/3449169674 | C10: Coimbatore | D10: 10.790035 | E10: 77.156483 | H10: 1.25 | I10: untagged; 1.250 MW/turbine proxy | J10: https://www.openstreetmap.org/node/3449169674
A11: node/3449169683 | C11: Coimbatore | D11: 10.793791 | E11: 77.150733 | H11: 1.25 | I11: untagged; 1.250 MW/turbine proxy | J11: https://www.openstreetmap.org/node/3449169683
A12: node/3449169690 | C12: Coimbatore | D12: 10.795105 | E12: 77.146276 | H12: 1.25 | I12: untagged; 1.250 MW/turbine proxy | J12: https://www.openstreetmap.org/node/3449169690
A13: node/3449170967 | C13: Coimbatore | D13: 10.799221 | E13: 77.147431 | H13: 1.25 | I13: untagged; 1.250 MW/turbine proxy | J13: https://www.openstreetmap.org/node/3449170967
A14: node/3449171143 | C14: Coimbatore | D14: 10.600236 | E14: 77.153481 | H14: 1.25 | I14: untagged; 1.250 MW/turbine proxy | J14: https://www.openstreetmap.org/node/3449171143
A15: node/3449171147 | C15: Coimbatore | D15: 10.601234 | E15: 77.156747 | H15: 1.25 | I15: untagged; 1.250 MW/turbine proxy | J15: https://www.openstreetmap.org/node/3449171147
A16: node/3449171148 | C16: Coimbatore | D16: 10.60244 | E16: 77.15385 | H16: 1.25 | I16: untagged; 1.250 MW/turbine proxy | J16: https://www.openstreetmap.org/node/3449171148
... A844: node/2375003785 | C844: Ramanathapuram | D844: 9.2858708 | E844: 79.02666 | H844: 1.25 | I844: untagged; 1.250 MW/turbine proxy | J844: https://www.openstreetmap.org/node/2375003785
A845: node/10872735440 | C845: Theni | D845: 9.8917141 | E845: 77.21959 | F845: yes | H845: 1.25 | I845: untagged; 1.250 MW/turbine proxy | J845: https://www.openstreetmap.org/node/10872735440
A846: node/10872735441 | C846: Theni | D846: 9.890377 | E846: 77.222004 | F846: yes | H846: 1.25 | I846: untagged; 1.250 MW/turbine proxy | J846: https://www.openstreetmap.org/node/10872735441
A847: node/10872735442 | C847: Theni | D847: 9.8890638 | E847: 77.221924 | F847: yes | H847: 1.25 | I847: untagged; 1.250 MW/turbine proxy | J847: https://www.openstreetmap.org/node/10872735442
A848: node/10872735443 | C848: Theni | D848: 9.8878853 | E848: 77.221495 | F848: yes | H848: 1.25 | I848: untagged; 1.250 MW/turbine proxy | J848: https://www.openstreetmap.org/node/10872735443
A849: node/10872735444 | C849: Theni | D849: 9.8866843 | E849: 77.221327 | F849: yes | H849: 1.25 | I849: untagged; 1.250 MW/turbine proxy | J849: https://www.openstreetmap.org/node/10872735444
A850: node/10872735445 | C850: Theni | D850: 9.8854067 | E850: 77.22144 | F850: yes | H850: 1.25 | I850: untagged; 1.250 MW/turbine proxy | J850: https://www.openstreetmap.org/node/10872735445
A851: node/11849861114 | C851: Theni | D851: 9.9211407 | E851: 77.346853 | H851: 1.25 | I851: untagged; 1.250 MW/turbine proxy | J851: https://www.openstreetmap.org/node/11849861114
A852: node/11849861115 | C852: Theni | D852: 9.9193092 | E852: 77.337732 | H852: 1.25 | I852: untagged; 1.250 MW/turbine proxy | J852: https://www.openstreetmap.org/node/11849861115
A853: node/11849861116 | C853: Theni | D853: 9.8779953 | E853: 77.303534 | H853: 1.25 | I853: untagged; 1.250 MW/turbine proxy | J853: https://www.openstreetmap.org/node/11849861116
A854: node/11849861117 | C854: Theni | D854: 9.8655575 | E854: 77.475277 | H854: 1.25 | I854: untagged; 1.250 MW/turbine proxy | J854: https://www.openstreetmap.org/node/11849861117
A855: node/11849861118 | C855: Theni | D855: 9.861457 | E855: 77.475906 | H855: 1.25 | I855: untagged; 1.250 MW/turbine proxy | J855: https://www.openstreetmap.org/node/11849861118
A856: node/11849861119 | C856: Theni | D856: 9.8689745 | E856: 77.463204 | H856: 1.25 | I856: untagged; 1.250 MW/turbine proxy | J856: https://www.openstreetmap.org/node/11849861119
A857: node/11849861120 | C857: Theni | D857: 9.8685006 | E857: 77.469847 | H857: 1.25 | I857: untagged; 1.250 MW/turbine proxy | J857: https://www.openstreetmap.org/node/11849861120
A858: node/3154159001 | C858: Theni | D858: 9.8732945 | E858: 77.488888 | H858: 1.25 | I858: untagged; 1.250 MW/turbine proxy | J858: https://www.openstreetmap.org/node/3154159001
A859: node/3154159020 | C859: Theni | D859: 9.8789187 | E859: 77.491548 | H859: 1.25 | I859: untagged; 1.250 MW/turbine proxy | J859: https://www.openstreetmap.org/node/3154159020
A860: node/3154159027 | C860: Theni | D860: 9.8849262 | E860: 77.490153 | H860: 1.25 | I860: untagged; 1.250 MW/turbine proxy | J860: https://www.openstreetmap.org/node/3154159027
A861: node/3154159029 | C861: Theni | D861: 9.886215 | E861: 77.495386 | H861: 1.25 | I861: untagged; 1.250 MW/turbine proxy | J861: https://www.openstreetmap.org/node/3154159029
A862: node/3154159040 | C862: Theni | D862: 9.8978236 | E862: 77.490139 | H862: 1.25 | I862: untagged; 1.250 MW/turbine proxy | J862: https://www.openstreetmap.org/node/3154159040
... A1454: node/13163738496 | C1454: Thoothukudi | D1454: 8.9129223 | E1454: 78.088734 | H1454: 1.25 | I1454: untagged; 1.250 MW/turbine proxy | J1454: https://www.openstreetmap.org/node/13163738496
A1455: node/13370043453 | C1455: Thoothukudi | D1455: 9.0732956 | E1455: 78.192549 | F1455: yes | H1455: 1.25 | I1455: untagged; 1.250 MW/turbine proxy | J1455: https://www.openstreetmap.org/node/13370043453
A1456: node/13370043454 | C1456: Thoothukudi | D1456: 9.110124 | E1456: 78.191018 | F1456: yes | H1456: 1.25 | I1456: untagged; 1.250 MW/turbine proxy | J1456: https://www.openstreetmap.org/node/13370043454
A1457: node/13370043455 | C1457: Thoothukudi | D1457: 9.1331412 | E1457: 78.063839 | F1457: yes | H1457: 1.25 | I1457: untagged; 1.250 MW/turbine proxy | J1457: https://www.openstreetmap.org/node/13370043455
A1458: node/13370043456 | C1458: Thoothukudi | D1458: 9.144794 | E1458: 78.071157 | F1458: yes | H1458: 1.25 | I1458: untagged; 1.250 MW/turbine proxy | J1458: https://www.openstreetmap.org/node/13370043456
A1459: node/13370043457 | C1459: Thoothukudi | D1459: 9.0838031 | E1459: 78.090419 | F1459: yes | H1459: 1.25 | I1459: untagged; 1.250 MW/turbine proxy | J1459: https://www.openstreetmap.org/node/13370043457
A1460: node/13370043458 | C1460: Thoothukudi | D1460: 9.0929808 | E1460: 78.089442 | F1460: yes | H1460: 1.25 | I1460: untagged; 1.250 MW/turbine proxy | J1460: https://www.openstreetmap.org/node/13370043458
A1461: node/13370043459 | C1461: Thoothukudi | D1461: 9.0904076 | E1461: 78.074111 | F1461: yes | H1461: 1.25 | I1461: untagged; 1.250 MW/turbine proxy | J1461: https://www.openstreetmap.org/node/13370043459
A1462: node/13370043460 | C1462: Thoothukudi | D1462: 9.1025228 | E1462: 78.0555 | F1462: yes | H1462: 1.25 | I1462: untagged; 1.250 MW/turbine proxy | J1462: https://www.openstreetmap.org/node/13370043460
A1463: node/13370043461 | C1463: Thoothukudi | D1463: 9.0931095 | E1463: 78.050549 | F1463: yes | H1463: 1.25 | I1463: untagged; 1.250 MW/turbine proxy | J1463: https://www.openstreetmap.org/node/13370043461
A1464: node/13370043462 | C1464: Thoothukudi | D1464: 9.0978269 | E1464: 78.057715 | F1464: yes | H1464: 1.25 | I1464: untagged; 1.250 MW/turbine proxy | J1464: https://www.openstreetmap.org/node/13370043462
A1465: node/13370043463 | C1465: Thoothukudi | D1465: 9.1055033 | E1465: 78.063883 | F1465: yes | H1465: 1.25 | I1465: untagged; 1.250 MW/turbine proxy | J1465: https://www.openstreetmap.org/node/13370043463
A1466: node/13370043464 | C1466: Thoothukudi | D1466: 9.1072615 | E1466: 78.072634 | F1466: yes | H1466: 1.25 | I1466: untagged; 1.250 MW/turbine proxy | J1466: https://www.openstreetmap.org/node/13370043464
... A1607: node/13370080202 | C1607: Thoothukudi | D1607: 9.0216222 | E1607: 78.15143 | F1607: yes | H1607: 1.25 | I1607: untagged; 1.250 MW/turbine proxy | J1607: https://www.openstreetmap.org/node/13370080202
A1608: node/3147420108 | C1608: Thoothukudi | D1608: 8.9598985 | E1608: 77.674252 | H1608: 1.25 | I1608: untagged; 1.250 MW/turbine proxy | J1608: https://www.openstreetmap.org/node/3147420108
A1609: node/3147420113 | C1609: Thoothukudi | D1609: 8.9602409 | E1609: 77.733295 | H1609: 1.25 | I1609: untagged; 1.250 MW/turbine proxy | J1609: https://www.openstreetmap.org/node/3147420113
A1610: node/3147420114 | C1610: Thoothukudi | D1610: 8.9605336 | E1610: 77.683862 | H1610: 1.25 | I1610: untagged; 1.250 MW/turbine proxy | J1610: https://www.openstreetmap.org/node/3147420114
A1611: node/3147420122 | C1611: Thoothukudi | D1611: 8.9614849 | E1611: 77.721844 | H1611: 1.25 | I1611: untagged; 1.250 MW/turbine proxy | J1611: https://www.openstreetmap.org/node/3147420122
A1612: node/3147420123 | C1612: Thoothukudi | D1612: 8.9614984 | E1612: 77.737072 | H1612: 1.25 | I1612: untagged; 1.250 MW/turbine proxy | J1612: https://www.openstreetmap.org/node/3147420123
A1613: node/3147420128 | C1613: Thoothukudi | D1613: 8.9621044 | E1613: 77.739283 | H1613: 1.25 | I1613: untagged; 1.250 MW/turbine proxy | J1613: https://www.openstreetmap.org/node/3147420128
A1614: node/3147421963 | C1614: Thoothukudi | D1614: 8.9735544 | E1614: 77.730078 | H1614: 1.25 | I1614: untagged; 1.250 MW/turbine proxy | J1614: https://www.openstreetmap.org/node/3147421963
A1615: node/3147421966 | C1615: Thoothukudi | D1615: 8.9742005 | E1615: 77.724428 | H1615: 1.25 | I1615: untagged; 1.250 MW/turbine proxy | J1615: https://www.openstreetmap.org/node/3147421966
A1616: node/3147421967 | C1616: Thoothukudi | D1616: 8.974299 | E1616: 77.727424 | H1616: 1.25 | I1616: untagged; 1.250 MW/turbine proxy | J1616: https://www.openstreetmap.org/node/3147421967
A1617: node/3147421970 | C1617: Thoothukudi | D1617: 8.9752589 | E1617: 77.730253 | H1617: 1.25 | I1617: untagged; 1.250 MW/turbine proxy | J1617: https://www.openstreetmap.org/node/3147421970
A1618: node/3147421971 | C1618: Thoothukudi | D1618: 8.9758544 | E1618: 77.724248 | H1618: 1.25 | I1618: untagged; 1.250 MW/turbine proxy | J1618: https://www.openstreetmap.org/node/3147421971
A1619: node/3147421974 | C1619: Thoothukudi | D1619: 8.9761327 | E1619: 77.727231 | H1619: 1.25 | I1619: untagged; 1.250 MW/turbine proxy | J1619: https://www.openstreetmap.org/node/3147421974
... A2613: node/9327762698 | C2613: Thoothukudi | D2613: 8.9321575 | E2613: 77.945752 | H2613: 1.25 | I2613: untagged; 1.250 MW/turbine proxy | J2613: https://www.openstreetmap.org/node/9327762698
A2614: node/10596126779 | C2614: Tirunelveli | D2614: 8.3635238 | E2614: 77.577613 | F2614: 4.2 MW | G2614: 4.2 | H2614: 4.2 | I2614: OSM output tag | J2614: https://www.openstreetmap.org/node/10596126779
A2615: node/10687795465 | C2615: Tirunelveli | D2615: 8.9637212 | E2615: 77.431131 | H2615: 1.25 | I2615: untagged; 1.250 MW/turbine proxy | J2615: https://www.openstreetmap.org/node/10687795465
A2616: node/10874974982 | C2616: Tirunelveli | D2616: 8.1843617 | E2616: 77.551089 | H2616: 1.25 | I2616: untagged; 1.250 MW/turbine proxy | J2616: https://www.openstreetmap.org/node/10874974982
A2617: node/10874974983 | C2617: Tirunelveli | D2617: 8.1727178 | E2617: 77.560611 | H2617: 1.25 | I2617: untagged; 1.250 MW/turbine proxy | J2617: https://www.openstreetmap.org/node/10874974983
A2618: node/10874974984 | C2618: Tirunelveli | D2618: 8.1707114 | E2618: 77.558674 | H2618: 1.25 | I2618: untagged; 1.250 MW/turbine proxy | J2618: https://www.openstreetmap.org/node/10874974984
A2619: node/10874974985 | C2619: Tirunelveli | D2619: 8.1714706 | E2619: 77.564126 | H2619: 1.25 | I2619: untagged; 1.250 MW/turbine proxy | J2619: https://www.openstreetmap.org/node/10874974985
A2620: node/11014632226 | C2620: Tirunelveli | D2620: 8.7903277 | E2620: 77.821307 | H2620: 1.25 | I2620: untagged; 1.250 MW/turbine proxy | J2620: https://www.openstreetmap.org/node/11014632226
A2621: node/1113762267 | C2621: Tirunelveli | D2621: 8.9794607 | E2621: 77.320865 | H2621: 1.25 | I2621: untagged; 1.250 MW/turbine proxy | J2621: https://www.openstreetmap.org/node/1113762267
A2622: node/1113762315 | C2622: Tirunelveli | D2622: 8.9913866 | E2622: 77.320018 | H2622: 1.25 | I2622: untagged; 1.250 MW/turbine proxy | J2622: https://www.openstreetmap.org/node/1113762315
A2623: node/1113762569 | C2623: Tirunelveli | D2623: 8.9885698 | E2623: 77.317503 | H2623: 1.25 | I2623: untagged; 1.250 MW/turbine proxy | J2623: https://www.openstreetmap.org/node/1113762569
A2624: node/1113762770 | C2624: Tirunelveli | D2624: 8.9831864 | E2624: 77.322351 | H2624: 1.25 | I2624: untagged; 1.250 MW/turbine proxy | J2624: https://www.openstreetmap.org/node/1113762770
A2625: node/1113762861 | C2625: Tirunelveli | D2625: 8.9966508 | E2625: 77.312685 | H2625: 1.25 | I2625: untagged; 1.250 MW/turbine proxy | J2625: https://www.openstreetmap.org/node/1113762861
A2626: node/1113766911 | C2626: Tirunelveli | D2626: 8.9870103 | E2626: 77.314734 | H2626: 1.25 | I2626: untagged; 1.250 MW/turbine proxy | J2626: https://www.openstreetmap.org/node/1113766911
... A2789: node/1496587470 | C2789: Tirunelveli | D2789: 8.1548533 | E2789: 77.60513 | H2789: 1.25 | I2789: untagged; 1.250 MW/turbine proxy | J2789: https://www.openstreetmap.org/node/1496587470
A2790: node/1496587471 | C2790: Tirunelveli | D2790: 8.1665986 | E2790: 77.633535 | F2790: 1250 KW | G2790: 1.25 | H2790: 1.25 | I2790: OSM output tag | J2790: https://www.openstreetmap.org/node/1496587471
A2791: node/1496589567 | C2791: Tirunelveli | D2791: 8.1654045 | E2791: 77.599466 | H2791: 1.25 | I2791: untagged; 1.250 MW/turbine proxy | J2791: https://www.openstreetmap.org/node/1496589567
A2792: node/1496589570 | C2792: Tirunelveli | D2792: 8.1694932 | E2792: 77.607705 | H2792: 1.25 | I2792: untagged; 1.250 MW/turbine proxy | J2792: https://www.openstreetmap.org/node/1496589570
A2793: node/1496589583 | C2793: Tirunelveli | D2793: 8.1656488 | E2793: 77.60247 | H2793: 1.25 | I2793: untagged; 1.250 MW/turbine proxy | J2793: https://www.openstreetmap.org/node/1496589583
A2794: node/1496589585 | C2794: Tirunelveli | D2794: 8.1725411 | E2794: 77.594434 | H2794: 1.25 | I2794: untagged; 1.250 MW/turbine proxy | J2794: https://www.openstreetmap.org/node/1496589585
A2795: node/1496589588 | C2795: Tirunelveli | D2795: 8.1658718 | E2795: 77.606675 | H2795: 1.25 | I2795: untagged; 1.250 MW/turbine proxy | J2795: https://www.openstreetmap.org/node/1496589588
A2796: node/1496589591 | C2796: Tirunelveli | D2796: 8.1705393 | E2796: 77.598929 | H2796: 1.25 | I2796: untagged; 1.250 MW/turbine proxy | J2796: https://www.openstreetmap.org/node/1496589591
A2797: node/1496589593 | C2797: Tirunelveli | D2797: 8.1740067 | E2797: 77.594836 | H2797: 1.25 | I2797: untagged; 1.250 MW/turbine proxy | J2797: https://www.openstreetmap.org/node/1496589593
A2798: node/1496589596 | C2798: Tirunelveli | D2798: 8.1695888 | E2798: 77.603682 | H2798: 1.25 | I2798: untagged; 1.250 MW/turbine proxy | J2798: https://www.openstreetmap.org/node/1496589596
A2799: node/1496589598 | C2799: Tirunelveli | D2799: 8.1762156 | E2799: 77.59416 | H2799: 1.25 | I2799: untagged; 1.250 MW/turbine proxy | J2799: https://www.openstreetmap.org/node/1496589598
A2800: node/1496590554 | C2800: Tirunelveli | D2800: 8.1834157 | E2800: 77.594412 | H2800: 1.25 | I2800: untagged; 1.250 MW/turbine proxy | J2800: https://www.openstreetmap.org/node/1496590554
A2801: node/1496590557 | C2801: Tirunelveli | D2801: 8.1804847 | E2801: 77.594911 | H2801: 1.25 | I2801: untagged; 1.250 MW/turbine proxy | J2801: https://www.openstreetmap.org/node/1496590557
A2802: node/1496591711 | C2802: Tirunelveli | D2802: 8.1871963 | E2802: 77.592733 | H2802: 1.25 | I2802: untagged; 1.250 MW/turbine proxy | J2802: https://www.openstreetmap.org/node/1496591711
... A2970: node/1496610838 | C2970: Tirunelveli | D2970: 8.1636416 | E2970: 77.605699 | H2970: 1.25 | I2970: untagged; 1.250 MW/turbine proxy | J2970: https://www.openstreetmap.org/node/1496610838
A2971: node/1496615673 | C2971: Tirunelveli | D2971: 8.1567627 | E2971: 77.622041 | F2971: 1250 KW | G2971: 1.25 | H2971: 1.25 | I2971: OSM output tag | J2971: https://www.openstreetmap.org/node/1496615673
A2972: node/1496616916 | C2972: Tirunelveli | D2972: 8.1614538 | E2972: 77.589219 | H2972: 1.25 | I2972: untagged; 1.250 MW/turbine proxy | J2972: https://www.openstreetmap.org/node/1496616916
A2973: node/1496616917 | C2973: Tirunelveli | D2973: 8.1589687 | E2973: 77.595174 | H2973: 1.25 | I2973: untagged; 1.250 MW/turbine proxy | J2973: https://www.openstreetmap.org/node/1496616917
A2974: node/1496616931 | C2974: Tirunelveli | D2974: 8.1589262 | E2974: 77.589456 | H2974: 1.25 | I2974: untagged; 1.250 MW/turbine proxy | J2974: https://www.openstreetmap.org/node/1496616931
A2975: node/1496616935 | C2975: Tirunelveli | D2975: 8.1570995 | E2975: 77.59247 | H2975: 1.25 | I2975: untagged; 1.250 MW/turbine proxy | J2975: https://www.openstreetmap.org/node/1496616935
A2976: node/1496616951 | C2976: Tirunelveli | D2976: 8.1616025 | E2976: 77.592975 | H2976: 1.25 | I2976: untagged; 1.250 MW/turbine proxy | J2976: https://www.openstreetmap.org/node/1496616951
A2977: node/1496618578 | C2977: Tirunelveli | D2977: 8.1958692 | E2977: 77.555219 | H2977: 1.25 | I2977: untagged; 1.250 MW/turbine proxy | J2977: https://www.openstreetmap.org/node/1496618578
A2978: node/1496618580 | C2978: Tirunelveli | D2978: 8.1959254 | E2978: 77.558599 | H2978: 1.25 | I2978: untagged; 1.250 MW/turbine proxy | J2978: https://www.openstreetmap.org/node/1496618580
A2979: node/1496618581 | C2979: Tirunelveli | D2979: 8.1929308 | E2979: 77.555316 | H2979: 1.25 | I2979: untagged; 1.250 MW/turbine proxy | J2979: https://www.openstreetmap.org/node/1496618581
A2980: node/1496618582 | C2980: Tirunelveli | D2980: 8.1928883 | E2980: 77.559125 | H2980: 1.25 | I2980: untagged; 1.250 MW/turbine proxy | J2980: https://www.openstreetmap.org/node/1496618582
A2981: node/1496618583 | C2981: Tirunelveli | D2981: 8.1948635 | E2981: 77.563401 | H2981: 1.25 | I2981: untagged; 1.250 MW/turbine proxy | J2981: https://www.openstreetmap.org/node/1496618583
...

Sheet Wind Methodology
A1: Sep26 Wind Allocation Methodology
A2: Topic | B2: Method / interpretation
A3: Scope | B3: Only the unresolved 256.375 MW operational wind record is redistributed.
A4: Proxy | B4: Supplied OSM turbines use their existing Proxy MW values and are rejoined to current district polygons.
A5: Residual gap | B5: Mapped proxy is scaled to 12,299.49 MW; known Sep26 district MW is subtracted; positive gaps are normalized to 256.375 MW.
A6: Tenkasi | B6: Tenkasi is retained separately from Tirunelveli.
A7: Boundary source | B7: https://cdn.jsdelivr.net/gh/udit-001/india-maps-data@2884453/geojson/states/tamil-nadu.geojson
A8: Confidence | B8: Medium. Most turbine capacities are proxy values rather than explicit MW tags.

Sheet Technology QC
A1: Source | B1: Commissioning Group | C1: Sep26 Base MW | D1: Verified Allocated MW | E1: Difference MW | F1: Check
A2: Bio Power | B2: operational | C2: 1055.12 | D2: 1055.12 | E2: 0 | F2: OK
A3: Coal | B3: operational | C3: 15032.5 | D3: 15032.5 | E3: 0 | F3: OK
A4: Coal | B4: pipeline | C4: 3300 | D4: 3300 | E4: 0 | F4: OK
A5: Coal | B5: retired | C5: 1050 | D5: 1050 | E5: 0 | F5: OK
A6: Hydro | B6: operational | C6: 2203.2 | D6: 2203.2 | E6: 0 | F6: OK
A7: Hydro | B7: pipeline | C7: 500 | D7: 500 | E7: 0 | F7: OK
A8: Nuclear | B8: operational | C8: 2440 | D8: 2440 | E8: 0 | F8: OK
A9: Nuclear | B9: pipeline | C9: 4500 | D9: 4500 | E9: 0 | F9: OK
A10: Oil & Gas | B10: Temporarily Closed | C10: 172.6 | D10: 172.6 | E10: 0 | F10: OK
A11: Oil & Gas | B11: operational | C11: 844.58 | D11: 844.58 | E11: 0 | F11: OK
A12: Small-Hydro | B12: operational | C12: 123.05 | D12: 123.05 | E12: 0 | F12: OK
A13: Solar | B13: operational | C13: 14121.46 | D13: 14121.46 | E13: 0 | F13: OK
... A16: Wind | B16: pipeline | C16: 973.5 | D16: 973.5 | E16: 0 | F16: OK

Sheet Change Log
A1: Technology | B1: District | C1: Previous Allocated MW | D1: Updated Allocated MW | E1: Change MW | F1: Reason
A2: Solar | B2: Ariyalur | C2: 24.330409 | D2: 9.6703044 | E2: -14.660105 | F2: Sep26 solar capacity update; validated shares retained, with Tirunelveli/Tenkasi coordinate split for utility solar.
A3: Solar | B3: Chennai | C3: 207.9671 | D3: 205.79516 | E3: -2.1719312 | F3: Sep26 solar capacity update; validated shares retained, with Tirunelveli/Tenkasi coordinate split for utility solar.
A4: Solar | B4: Coimbatore | C4: 291.60168 | D4: 338.93669 | E4: 47.335017 | F4: Sep26 solar capacity update; validated shares retained, with Tirunelveli/Tenkasi coordinate split for utility solar.
A5: Solar | B5: Cuddalore | C5: 366.64536 | D5: 985.61372 | E5: 618.96836 | F5: Sep26 solar capacity update; validated shares retained, with Tirunelveli/Tenkasi coordinate split for utility solar.
A6: Solar | B6: Dharmapuri | C6: 24.335586 | D6: 141.23669 | E6: 116.9011 | F6: Sep26 solar capacity update; validated shares retained, with Tirunelveli/Tenkasi coordinate split for utility solar.
A7: Solar | B7: Dindigul | C7: 989.31957 | D7: 432.58058 | E7: -556.73898 | F7: Sep26 solar capacity update; validated shares retained, with Tirunelveli/Tenkasi coordinate split for utility solar.
A8: Solar | B8: Erode | C8: 140.95543 | D8: 910.31885 | E8: 769.36342 | F8: Sep26 solar capacity update; validated shares retained, with Tirunelveli/Tenkasi coordinate split for utility solar.
A9: Solar | B9: Kanchipuram | C9: 221.83204 | D9: 720.64668 | E9: 498.81464 | F9: Sep26 solar capacity update; validated shares retained, with Tirunelveli/Tenkasi coordinate split for utility solar.
A10: Solar | B10: Kanyakumari | C10: 40.021415 | D10: 38.429365 | E10: -1.5920502 | F10: Sep26 solar capacity update; validated shares retained, with Tirunelveli/Tenkasi coordinate split for utility solar.
A11: Solar | B11: Karur | C11: 679.32396 | D11: 516.07981 | E11: -163.24415 | F11: Sep26 solar capacity update; validated shares retained, with Tirunelveli/Tenkasi coordinate split for utility solar.
A12: Solar | B12: Krishnagiri | C12: 26.94272 | D12: 21.024579 | E12: -5.9181409 | F12: Sep26 solar capacity update; validated shares retained, with Tirunelveli/Tenkasi coordinate split for utility solar.
A13: Solar | B13: Madurai | C13: 143.87815 | D13: 171.92142 | E13: 28.043267 | F13: Sep26 solar capacity update; validated shares retained, with Tirunelveli/Tenkasi coordinate split for utility solar.
... A54: Wind | B54: Viluppuram | C54: 1.7112407 | D54: 1.7123423 | E54: 0.0011015655 | F54: Wind residual-gap model rerun using Sep26 capacities and current district assignment; Tenkasi retained separately.
